Workbook
Name GroomName: '01 START HERE'!$H$14
Name BrideName: '01 START HERE'!$D$14
Name ContingencyPct: '01 START HERE'!$H$27
Name TotalBudget: '01 START HERE'!$D$27
Name WeddingDate: '01 START HERE'!$D$15

Sheet 01 START HERE
B2: SRI LANKAN WEDDING MASTER PLANNER
B3: One-day wedding | all amounts in Sri Lankan Rupees (LKR) | dates DD/MM/YYYY
B5: HOW TO USE THIS WORKBOOK
B6: 1. YELLOW cells are for you to type in. GREY cells calculate themselves - do not overwrite them.
B7: 2. Fill this sheet in first, then compare vendors on 05a, record the winners on 05 Vendors, then price it up on 03 Budget.
B8: 3. Open 02 Dashboard every time - it lists exactly what needs attention today.
B9: 4. Never type a vendor or a budget line twice. Pick it from the dropdown so the totals stay linked.
B10: 5. Sheets 14-21 are the wedding-day operating pack. Print them and hand them to your coordinator.
B13: THE COUPLE & THE DAY
B14: Bride's full name | D14: Methuli | F14: Groom's full name | H14: Udara
B15: Wedding date | D15: 46633 | F15: Day of the week | H15: =TEXT(WeddingDate,"dddd") -> Friday
B16: Days to go | D16: =WeddingDate-TODAY() -> 365 | F16: Wedding type | H16: Poruwa + Registration + Reception
B17: Poruwa / ceremony time | D17: 0.41666667 | F17: Reception start | H17: 0.375
B18: Registration (signing) time | D18: 0.39583333 | F18: Expected finish | H18: 0.66666667
B19: Venue (one venue for the whole day) | D19: [Hotel / banquet hall] | F19: Town / district | H19: [Town, District]
B20: Ceremony area | D20: Ballroom | F20: Reception area | H20: [Ballroom]
B21: Venue contact person | D21: [Name] | F21: Venue phone | H21: [07X XXX XXXX]
B22: Wedding theme | D22: [e.g. Classic Kandyan] | F22: Colour palette | H22: [e.g. Ivory / Gold / Maroon]
B23: Main coordinator | D23: [Name] | F23: Coordinator phone | H23: [07X XXX XXXX]
B24: Emergency contact (day-of) | D24: [Name] | F24: Emergency phone | H24: [07X XXX XXXX]
B26: MONEY
B27: TOTAL WEDDING BUDGET (LKR) | D27: 4000000 | F27: Contingency reserve % | H27: 0.01
B28: Guests invited (pax) | D28: =SUM('09 Guests'!K7:K300) -> 156 | F28: Guests confirmed (pax) | H28: =SUM('09 Guests'!Y7:Y300) -> 0
B29: Indicative budget - replace with your own figures
B30: Budgeted (originally planned) | D30: =SUM('03 Budget'!E7:E300) -> 7318000 | F30: Quoted by vendors | H30: =SUM('03 Budget'!I7:I300) -> 896000
B31: Negotiated / agreed | D31: =SUM('03 Budget'!J7:J300) -> 0 | F31: Actual invoiced | H31: =SUM('03 Budget'!K7:K300) -> 896000
B32: FORECAST FINAL COST | D32: =SUM('03 Budget'!L7:L300) -> 4702500 | F32: Paid to date | H32: =SUM('03 Budget'!M7:M300) -> 896000
B33: Outstanding still to pay | D33: =SUM('03 Budget'!N7:N300) -> 3806500 | F33: Refundable deposits out | H33: =SUM('03 Budget'!O7:O300) -> 0
B34: Remaining against budget | D34: =TotalBudget-SUM('03 Budget'!L7:L300) -> -702500 | F34: Budget utilisation | H34: =IFERROR(SUM('03 Budget'!L7:L300)/TotalBudget,0) -> 1.175625
B36: WHERE THE MONEY COMES FROM
B37: Family & couple contributions agreed | D37: =SUM('06 Contributions'!G7:G60) -> 0 | F37: Contributions received | H37: =SUM('06 Contributions'!H7:H60) -> 0
B38: Expected cash gifts from guests | D38: =SUMIFS('09 Guests'!AE7:AE300,'09 Guests'!U7:U300,"<>Declined") -> 605000 | F38: Cash gifts received | H38: =SUM('09 Guests'!AF7:AF300) -> 0
B39: NET COST AFTER GIFTS & CONTRIBUTIONS | D39: =D32-D37-D38 -> 4097500 | F39: Shortfall still to fund | H39: =MAX(0,D39-H37-H38) -> 4097500
B41: ASSUMPTIONS YOU SHOULD CHECK
B42: - Wedding date 03/09/2027 (a Friday) was supplied by you. No homecoming event - this is a one-day wedding.
B43: - Poruwa, marriage registration and Kandyan dancers/drummers are pre-set as REQUIRED. Church/temple service is Optional.
B44: - ASSUMPTION: all 84 guest groups carried over from your old sheet are marked GROOM'S side. Change column F on 09 Guests where that is wrong.
B45: - ASSUMPTION: budget amounts are indicative market estimates for a c.200-guest hotel wedding, not quotes. Replace with your own figures.
B46: - Items marked VERIFY on 13 Ceremony & Legal must be confirmed with your Divisional Secretariat / Registrar - rules vary by district and religion.

Sheet 02 Dashboard
B2: MASTER DASHBOARD
B3: Everything on this sheet calculates itself. Read the ATTENTION REQUIRED panel at the bottom every time you open the workbook.
B4: AT A GLANCE
C5: DAYS TO GO | F5: TOTAL BUDGET | I5: FORECAST FINAL COST | L5: PAID SO FAR | O5: STILL TO PAY | R5: LEFT IN BUDGET
C6: =WeddingDate-TODAY() -> 365 | F6: =TotalBudget -> 4000000 | I6: =SUM('03 Budget'!L7:L300) -> 4702500 | L6: =SUM('03 Budget'!M7:M300) -> 896000 | O6: =SUM('03 Budget'!N7:N300) -> 3806500 | R6: =TotalBudget-SUM('03 Budget'!L7:L300) -> -702500
C8: GUESTS INVITED | F8: GUESTS CONFIRMED | I8: RSVP RESPONSE RATE | L8: TASKS COMPLETE | O8: VENDORS CONFIRMED | R8: NET COST AFTER GIFTS
C9: =SUM('09 Guests'!K7:K300) -> 156 | F9: =SUM('09 Guests'!Y7:Y300) -> 0 | I9: =IFERROR((COUNTIF('09 Guests'!U7:U300,"Accepted")+COUNTIF('09 Guests'!U7:U300,"Declined"))/COUNTA('09 Guests'!D7:D300),0) -> 0 | L9: =IFERROR(COUNTIF('07 Tasks'!K7:K250,"Completed")/COUNTA('07 Tasks'!D7:D250),0) -> 0.010752688 | O9: =IFERROR((COUNTIF('05 Vendors'!S7:S200,"Confirmed")+COUNTIF('05 Vendors'!S7:S200,"Completed"))/COUNTA('05 Vendors'!D7:D200),0) -> 0.16666667 | R9: =SUM('03 Budget'!L7:L300)-SUM('06 Contributions'!G7:G60)-SUMIFS('09 Guests'!AE7:AE300,'09 Guests'!U7:U300,"<>Declined") -> 4097500
B11: WHERE THE MONEY IS GOING
B12: Category | C12: Budgeted | E12: Forecast | G12: Paid | I12: Outstanding | K12: Variance
B13: VENUE & HOTEL | C13: =SUMIFS('03 Budget'!$E$7:$E$300,'03 Budget'!$C$7:$C$300,$B13) -> 624000 | E13: =SUMIFS('03 Budget'!$L$7:$L$300,'03 Budget'!$C$7:$C$300,$B13) -> 524000 | G13: =SUMIFS('03 Budget'!$M$7:$M$300,'03 Budget'!$C$7:$C$300,$B13) -> 0 | I13: =SUMIFS('03 Budget'!$N$7:$N$300,'03 Budget'!$C$7:$C$300,$B13) -> 524000 | K13: =SUMIFS('03 Budget'!$P$7:$P$300,'03 Budget'!$C$7:$C$300,$B13) -> -100000
B14: FOOD & BEVERAGE | C14: =SUMIFS('03 Budget'!$E$7:$E$300,'03 Budget'!$C$7:$C$300,$B14) -> 2280000 | E14: =SUMIFS('03 Budget'!$L$7:$L$300,'03 Budget'!$C$7:$C$300,$B14) -> 2007000 | G14: =SUMIFS('03 Budget'!$M$7:$M$300,'03 Budget'!$C$7:$C$300,$B14) -> 0 | I14: =SUMIFS('03 Budget'!$N$7:$N$300,'03 Budget'!$C$7:$C$300,$B14) -> 2007000 | K14: =SUMIFS('03 Budget'!$P$7:$P$300,'03 Budget'!$C$7:$C$300,$B14) -> -273000
B15: CAKE | C15: =SUMIFS('03 Budget'!$E$7:$E$300,'03 Budget'!$C$7:$C$300,$B15) -> 135000 | E15: =SUMIFS('03 Budget'!$L$7:$L$300,'03 Budget'!$C$7:$C$300,$B15) -> 120000 | G15: =SUMIFS('03 Budget'!$M$7:$M$300,'03 Budget'!$C$7:$C$300,$B15) -> 0 | I15: =SUMIFS('03 Budget'!$N$7:$N$300,'03 Budget'!$C$7:$C$300,$B15) -> 120000 | K15: =SUMIFS('03 Budget'!$P$7:$P$300,'03 Budget'!$C$7:$C$300,$B15) -> -15000
B16: PHOTOGRAPHY | C16: =SUMIFS('03 Budget'!$E$7:$E$300,'03 Budget'!$C$7:$C$300,$B16) -> 350000 | E16: =SUMIFS('03 Budget'!$L$7:$L$300,'03 Budget'!$C$7:$C$300,$B16) -> 180000 | G16: =SUMIFS('03 Budget'!$M$7:$M$300,'03 Budget'!$C$7:$C$300,$B16) -> 0 | I16: =SUMIFS('03 Budget'!$N$7:$N$300,'03 Budget'!$C$7:$C$300,$B16) -> 180000 | K16: =SUMIFS('03 Budget'!$P$7:$P$300,'03 Budget'!$C$7:$C$300,$B16) -> -170000
B17: VIDEOGRAPHY | C17: =SUMIFS('03 Budget'!$E$7:$E$300,'03 Budget'!$C$7:$C$300,$B17) -> 345000 | E17: =SUMIFS('03 Budget'!$L$7:$L$300,'03 Budget'!$C$7:$C$300,$B17) -> 35000 | G17: =SUMIFS('03 Budget'!$M$7:$M$300,'03 Budget'!$C$7:$C$300,$B17) -> 0 | I17: =SUMIFS('03 Budget'!$N$7:$N$300,'03 Budget'!$C$7:$C$300,$B17) -> 35000 | K17: =SUMIFS('03 Budget'!$P$7:$P$300,'03 Budget'!$C$7:$C$300,$B17) -> -310000
B18: BRIDE - ATTIRE & BEAUTY | C18: =SUMIFS('03 Budget'!$E$7:$E$300,'03 Budget'!$C$7:$C$300,$B18) -> 298000 | E18: =SUMIFS('03 Budget'!$L$7:$L$300,'03 Budget'!$C$7:$C$300,$B18) -> 271000 | G18: =SUMIFS('03 Budget'!$M$7:$M$300,'03 Budget'!$C$7:$C$300,$B18) -> 0 | I18: =SUMIFS('03 Budget'!$N$7:$N$300,'03 Budget'!$C$7:$C$300,$B18) -> 271000 | K18: =SUMIFS('03 Budget'!$P$7:$P$300,'03 Budget'!$C$7:$C$300,$B18) -> -27000
B19: GROOM - ATTIRE & GROOMING | C19: =SUMIFS('03 Budget'!$E$7:$E$300,'03 Budget'!$C$7:$C$300,$B19) -> 46000 | E19: =SUMIFS('03 Budget'!$L$7:$L$300,'03 Budget'!$C$7:$C$300,$B19) -> 46000 | G19: =SUMIFS('03 Budget'!$M$7:$M$300,'03 Budget'!$C$7:$C$300,$B19) -> 0 | I19: =SUMIFS('03 Budget'!$N$7:$N$300,'03 Budget'!$C$7:$C$300,$B19) -> 46000 | K19: =SUMIFS('03 Budget'!$P$7:$P$300,'03 Budget'!$C$7:$C$300,$B19) -> 0
B20: JEWELLERY | C20: =SUMIFS('03 Budget'!$E$7:$E$300,'03 Budget'!$C$7:$C$300,$B20) -> 905500 | E20: =SUMIFS('03 Budget'!$L$7:$L$300,'03 Budget'!$C$7:$C$300,$B20) -> 896000 | G20: =SUMIFS('03 Budget'!$M$7:$M$300,'03 Budget'!$C$7:$C$300,$B20) -> 896000 | I20: =SUMIFS('03 Budget'!$N$7:$N$300,'03 Budget'!$C$7:$C$300,$B20) -> 0 | K20: =SUMIFS('03 Budget'!$P$7:$P$300,'03 Budget'!$C$7:$C$300,$B20) -> -9500
B21: BRIDAL PARTY | C21: =SUMIFS('03 Budget'!$E$7:$E$300,'03 Budget'!$C$7:$C$300,$B21) -> 122000 | E21: =SUMIFS('03 Budget'!$L$7:$L$300,'03 Budget'!$C$7:$C$300,$B21) -> 67000 | G21: =SUMIFS('03 Budget'!$M$7:$M$300,'03 Budget'!$C$7:$C$300,$B21) -> 0 | I21: =SUMIFS('03 Budget'!$N$7:$N$300,'03 Budget'!$C$7:$C$300,$B21) -> 67000 | K21: =SUMIFS('03 Budget'!$P$7:$P$300,'03 Budget'!$C$7:$C$300,$B21) -> -55000
B22: DECOR & FLORALS | C22: =SUMIFS('03 Budget'!$E$7:$E$300,'03 Budget'!$C$7:$C$300,$B22) -> 676000 | E22: =SUMIFS('03 Budget'!$L$7:$L$300,'03 Budget'!$C$7:$C$300,$B22) -> 6000 | G22: =SUMIFS('03 Budget'!$M$7:$M$300,'03 Budget'!$C$7:$C$300,$B22) -> 0 | I22: =SUMIFS('03 Budget'!$N$7:$N$300,'03 Budget'!$C$7:$C$300,$B22) -> 6000 | K22: =SUMIFS('03 Budget'!$P$7:$P$300,'03 Budget'!$C$7:$C$300,$B22) -> -670000
B23: LIGHTING, SOUND & AV | C23: =SUMIFS('03 Budget'!$E$7:$E$300,'03 Budget'!$C$7:$C$300,$B23) -> 180000 | E23: =SUMIFS('03 Budget'!$L$7:$L$300,'03 Budget'!$C$7:$C$300,$B23) -> 0 | G23: =SUMIFS('03 Budget'!$M$7:$M$300,'03 Budget'!$C$7:$C$300,$B23) -> 0 | I23: =SUMIFS('03 Budget'!$N$7:$N$300,'03 Budget'!$C$7:$C$300,$B23) -> 0 | K23: =SUMIFS('03 Budget'!$P$7:$P$300,'03 Budget'!$C$7:$C$300,$B23) -> -180000
B24: ENTERTAINMENT | C24: =SUMIFS('03 Budget'!$E$7:$E$300,'03 Budget'!$C$7:$C$300,$B24) -> 375000 | E24: =SUMIFS('03 Budget'!$L$7:$L$300,'03 Budget'!$C$7:$C$300,$B24) -> 240000 | G24: =SUMIFS('03 Budget'!$M$7:$M$300,'03 Budget'!$C$7:$C$300,$B24) -> 0 | I24: =SUMIFS('03 Budget'!$N$7:$N$300,'03 Budget'!$C$7:$C$300,$B24) -> 240000 | K24: =SUMIFS('03 Budget'!$P$7:$P$300,'03 Budget'!$C$7:$C$300,$B24) -> -135000
... B32: MISCELLANEOUS | C32: =SUMIFS('03 Budget'!$E$7:$E$300,'03 Budget'!$C$7:$C$300,$B32) -> 233000 | E32: =SUMIFS('03 Budget'!$L$7:$L$300,'03 Budget'!$C$7:$C$300,$B32) -> 125000 | G32: =SUMIFS('03 Budget'!$M$7:$M$300,'03 Budget'!$C$7:$C$300,$B32) -> 0 | I32: =SUMIFS('03 Budget'!$N$7:$N$300,'03 Budget'!$C$7:$C$300,$B32) -> 125000 | K32: =SUMIFS('03 Budget'!$P$7:$P$300,'03 Budget'!$C$7:$C$300,$B32) -> -108000
B33: TOTAL | C33: =SUM(C13:C32) -> 7318000 | E33: =SUM(E13:E32) -> 4702500 | G33: =SUM(G13:G32) -> 896000 | I33: =SUM(I13:I32) -> 3806500 | K33: =SUM(K13:K32) -> -2615500
B36: WEDDING READINESS - based on completed tasks in 07 Tasks
B37: Area | C37: Done | E37: Total tasks | G37: Complete | I37: Progress
B38: Venue | C38: =COUNTIFS('07 Tasks'!$C$7:$C$250,$B38,'07 Tasks'!$K$7:$K$250,"Completed") -> 0 | E38: =COUNTIF('07 Tasks'!$C$7:$C$250,$B38) -> 4 | G38: =IFERROR($C38/$E38,0) -> 0 | I38: =IFERROR($C38/$E38,0) -> 0
B39: Food & Beverage | C39: =COUNTIFS('07 Tasks'!$C$7:$C$250,$B39,'07 Tasks'!$K$7:$K$250,"Completed") -> 0 | E39: =COUNTIF('07 Tasks'!$C$7:$C$250,$B39) -> 2 | G39: =IFERROR($C39/$E39,0) -> 0 | I39: =IFERROR($C39/$E39,0) -> 0
B40: Cake | C40: =COUNTIFS('07 Tasks'!$C$7:$C$250,$B40,'07 Tasks'!$K$7:$K$250,"Completed") -> 0 | E40: =COUNTIF('07 Tasks'!$C$7:$C$250,$B40) -> 1 | G40: =IFERROR($C40/$E40,0) -> 0 | I40: =IFERROR($C40/$E40,0) -> 0
B41: Decor & Florals | C41: =COUNTIFS('07 Tasks'!$C$7:$C$250,$B41,'07 Tasks'!$K$7:$K$250,"Completed") -> 0 | E41: =COUNTIF('07 Tasks'!$C$7:$C$250,$B41) -> 4 | G41: =IFERROR($C41/$E41,0) -> 0 | I41: =IFERROR($C41/$E41,0) -> 0
B42: Photography | C42: =COUNTIFS('07 Tasks'!$C$7:$C$250,$B42,'07 Tasks'!$K$7:$K$250,"Completed") -> 0 | E42: =COUNTIF('07 Tasks'!$C$7:$C$250,$B42) -> 6 | G42: =IFERROR($C42/$E42,0) -> 0 | I42: =IFERROR($C42/$E42,0) -> 0
B43: Videography | C43: =COUNTIFS('07 Tasks'!$C$7:$C$250,$B43,'07 Tasks'!$K$7:$K$250,"Completed") -> 0 | E43: =COUNTIF('07 Tasks'!$C$7:$C$250,$B43) -> 2 | G43: =IFERROR($C43/$E43,0) -> 0 | I43: =IFERROR($C43/$E43,0) -> 0
B44: Attire | C44: =COUNTIFS('07 Tasks'!$C$7:$C$250,$B44,'07 Tasks'!$K$7:$K$250,"Completed") -> 0 | E44: =COUNTIF('07 Tasks'!$C$7:$C$250,$B44) -> 8 | G44: =IFERROR($C44/$E44,0) -> 0 | I44: =IFERROR($C44/$E44,0) -> 0
B45: Jewellery | C45: =COUNTIFS('07 Tasks'!$C$7:$C$250,$B45,'07 Tasks'!$K$7:$K$250,"Completed") -> 1 | E45: =COUNTIF('07 Tasks'!$C$7:$C$250,$B45) -> 5 | G45: =IFERROR($C45/$E45,0) -> 0.2 | I45: =IFERROR($C45/$E45,0) -> 0.2
B46: Beauty & Grooming | C46: =COUNTIFS('07 Tasks'!$C$7:$C$250,$B46,'07 Tasks'!$K$7:$K$250,"Completed") -> 0 | E46: =COUNTIF('07 Tasks'!$C$7:$C$250,$B46) -> 7 | G46: =IFERROR($C46/$E46,0) -> 0 | I46: =IFERROR($C46/$E46,0) -> 0
B47: Invitations | C47: =COUNTIFS('07 Tasks'!$C$7:$C$250,$B47,'07 Tasks'!$K$7:$K$250,"Completed") -> 0 | E47: =COUNTIF('07 Tasks'!$C$7:$C$250,$B47) -> 5 | G47: =IFERROR($C47/$E47,0) -> 0 | I47: =IFERROR($C47/$E47,0) -> 0
B48: Guests & RSVP | C48: =COUNTIFS('07 Tasks'!$C$7:$C$250,$B48,'07 Tasks'!$K$7:$K$250,"Completed") -> 0 | E48: =COUNTIF('07 Tasks'!$C$7:$C$250,$B48) -> 8 | G48: =IFERROR($C48/$E48,0) -> 0 | I48: =IFERROR($C48/$E48,0) -> 0
B49: Transport | C49: =COUNTIFS('07 Tasks'!$C$7:$C$250,$B49,'07 Tasks'!$K$7:$K$250,"Completed") -> 0 | E49: =COUNTIF('07 Tasks'!$C$7:$C$250,$B49) -> 2 | G49: =IFERROR($C49/$E49,0) -> 0 | I49: =IFERROR($C49/$E49,0) -> 0
... B57: Logistics | C57: =COUNTIFS('07 Tasks'!$C$7:$C$250,$B57,'07 Tasks'!$K$7:$K$250,"Completed") -> 0 | E57: =COUNTIF('07 Tasks'!$C$7:$C$250,$B57) -> 9 | G57: =IFERROR($C57/$E57,0) -> 0 | I57: =IFERROR($C57/$E57,0) -> 0
B60: ATTENTION REQUIRED - read this every time you open the workbook
B61: Count | C61: Severity | F61: What needs your attention
B62: =COUNTIF('04 Payments'!S7:S400,"Overdue") -> 0 | C62: CRITICAL | F62: Vendor payment(s) are OVERDUE - open 04 Payments and filter STATUS = Overdue
B63: =COUNTIF('04 Payments'!S7:S400,"Due")+COUNTIF('04 Payments'!S7:S400,"Due Soon") -> 0 | C63: HIGH | F63: Vendor payment(s) fall due in the next 30 days
B64: =MAX(0,COUNTA('05 Vendors'!D7:D200)-COUNTIF('05 Vendors'!S7:S200,"Confirmed")-COUNTIF('05 Vendors'!S7:S200,"Completed")-COUNTIF('05 Vendors'!S7:S200,"Cancelled")) -> 15 | C64: HIGH | F64: Vendor(s) are not yet CONFIRMED on 05 Vendors
B65: =COUNTIFS('05 Vendors'!D7:D200,"<>",'05 Vendors'!Q7:Q200,"<>Yes") -> 17 | C65: HIGH | F65: Vendor(s) have no signed contract recorded
B66: =COUNTIFS('05 Vendors'!D7:D200,"<>",'05 Vendors'!F7:F200,"") -> 17 | C66: MEDIUM | F66: Vendor(s) have no phone number - you cannot reach them on the day
B67: =COUNTIFS('05 Vendors'!D7:D200,"<>",'05 Vendors'!T7:T200,"") -> 17 | C67: MEDIUM | F67: Vendor(s) have no arrival time set - fill in 21 Vendor Schedule
B68: =COUNTIF('07 Tasks'!L7:L250,"OVERDUE") -> 0 | C68: CRITICAL | F68: Task(s) are OVERDUE on 07 Tasks
B69: =COUNTIF('07 Tasks'!L7:L250,"TODAY")+COUNTIF('07 Tasks'!L7:L250,"This week") -> 1 | C69: HIGH | F69: Task(s) are due today or this week
B70: =COUNTIFS('07 Tasks'!G7:G250,"Critical",'07 Tasks'!K7:K250,"<>Completed",'07 Tasks'!K7:K250,"<>Cancelled",'07 Tasks'!I7:I250,"<="&(TODAY()+30)) -> 3 | C70: HIGH | F70: CRITICAL task(s) due within 30 days are still not finished
B71: =COUNTIFS('07 Tasks'!D7:D250,"<>",'07 Tasks'!E7:E250,"") -> 0 | C71: MEDIUM | F71: Task(s) have nobody responsible - assign an owner
B72: =COUNTIFS('09 Guests'!S7:S300,"Yes",'09 Guests'!U7:U300,"Pending") -> 0 | C72: HIGH | F72: Guest group(s) were invited but have not replied - chase them
B73: =SUMIFS('09 Guests'!Y7:Y300,'09 Guests'!U7:U300,"Accepted",'09 Guests'!AD7:AD300,"") -> 0 | C73: HIGH | F73: Confirmed guest(s) have no table assigned on 10 RSVP & Seating
B74: =COUNTIF('10 RSVP & Seating'!O20:O60,"OVER CAPACITY") -> 0 | C74: CRITICAL | F74: Table(s) are OVER CAPACITY - people will have nowhere to sit
B75: =COUNTIFS('09 Guests'!F7:F300,"",'09 Guests'!D7:D300,"<>") -> 0 | C75: LOW | F75: Guest group(s) have no side (bride/groom) recorded
B76: =COUNTIF('03 Budget'!P7:P300,">0") -> 2 | C76: MEDIUM | F76: Budget line(s) are forecast to come in OVER their budgeted amount
B77: =IF(SUM('03 Budget'!L7:L300)>TotalBudget,1,0) -> 1 | C77: CRITICAL | F77: The FORECAST FINAL COST now exceeds your total budget
B78: =COUNTIFS('04 Payments'!S7:S400,"Paid",'04 Payments'!Q7:Q400,"<>Yes") -> 0 | C78: LOW | F78: Payment(s) marked Paid have no receipt recorded
B79: =COUNTIF('14 Ceremony & Legal'!K7:K200,"VERIFY") -> 12 | C79: HIGH | F79: Legal / registration item(s) still say VERIFY - confirm them with your Registrar
B80: =IF(TODAY()<WeddingDate,0,COUNTIFS('12 Attire & Jewellery'!E7:E120,"Rented",'12 Attire & Jewellery'!L7:L120,"No")) -> 0 | C80: CRITICAL | F80: Rented jewellery item(s) have not been returned (shows after the wedding)
B81: =IF(WeddingDate-TODAY()>45,0,COUNTIFS('23 Procurement & Packing'!E7:E120,"Required",'23 Procurement & Packing'!J7:J120,"No")) -> 0 | C81: MEDIUM | F81: Item(s) on 23 Procurement & Packing still not bought (shows inside 45 days)
B82: =IF(WeddingDate-TODAY()>14,0,COUNTIFS('23 Procurement & Packing'!O7:O120,"No",'23 Procurement & Packing'!N7:N120,"Yes")) -> 0 | C82: HIGH | F82: Item(s) needed on the day are still NOT PACKED (shows inside 14 days)
B83: =IF(TODAY()<WeddingDate,0,COUNTIFS('18 Photo & Video Plan'!D7:D90,"Must",'18 Photo & Video Plan'!I7:I90,"No")) -> 0 | C83: LOW | F83: Must-have photograph(s) not ticked off (shows after the wedding)
B84: =COUNTIF('05a Vendor Compare'!$I$7:$I$40,"NOT YET") -> 0 | C84: HIGH | F84: Vendor decision(s) made on 05a Vendor Compare but not yet recorded in 05 Vendors
B86: =IF(SUMPRODUCT(--(B62:B84>0))=0,"Nothing needs your attention right now.","There are "&SUMPRODUCT(--(B62:B84>0))&" item(s) above that need attention.") -> There are 9 item(s) above that need attention.

Sheet 03 Budget
B2: MASTER BUDGET
B3: Budgeted -> Quoted -> Negotiated -> Actual. FORECAST automatically uses the most advanced number you have entered. PAID is pulled from 04 Payments - never type it.
D5: TOTALS | E5: =SUM(E7:E300) -> 7318000 | I5: =SUM(I7:I300) -> 896000 | J5: =SUM(J7:J300) -> 0 | K5: =SUM(K7:K300) -> 896000 | L5: =SUM(L7:L300) -> 4702500 | M5: =SUM(M7:M300) -> 896000 | N5: =SUM(N7:N300) -> 3806500 | O5: =SUM(O7:O300) -> 0 | P5: =SUM(P7:P300) -> -2615500
B6: ID | C6: Category | D6: Line item | E6: Budgeted | F6: Applies? | G6: Who pays | H6: Vendor | I6: Quoted | J6: Negotiated | K6: Actual | L6: FORECAST | M6: Paid | N6: Outstanding | O6: Refundable deposit | P6: Variance vs budget | Q6: Status | R6: Notes
B7: BG001 | C7: VENUE & HOTEL | D7: Venue hire - ceremony & reception hall | E7: 0 | F7: Not Applicable | L7: =IF($F7="Not Applicable",0,IF(K7>0,K7,IF(J7>0,J7,IF(I7>0,I7,E7)))) -> 0 | M7: =SUMIFS('04 Payments'!$K$7:$K$400,'04 Payments'!$D$7:$D$400,$B7) -> 0 | N7: =MAX(0,L7-M7) -> 0 | P7: =L7-E7 -> 0 | Q7: Not Started
B8: BG002 | C8: VENUE & HOTEL | D8: Garden / outdoor area | E8: 0 | F8: Not Applicable | L8: =IF($F8="Not Applicable",0,IF(K8>0,K8,IF(J8>0,J8,IF(I8>0,I8,E8)))) -> 0 | M8: =SUMIFS('04 Payments'!$K$7:$K$400,'04 Payments'!$D$7:$D$400,$B8) -> 0 | N8: =MAX(0,L8-M8) -> 0 | P8: =L8-E8 -> 0 | Q8: Not Started
B9: BG003 | C9: VENUE & HOTEL | D9: Bridal suite (wedding night) | E9: 10000 | F9: Required | G9: Groom | L9: =IF($F9="Not Applicable",0,IF(K9>0,K9,IF(J9>0,J9,IF(I9>0,I9,E9)))) -> 10000 | M9: =SUMIFS('04 Payments'!$K$7:$K$400,'04 Payments'!$D$7:$D$400,$B9) -> 0 | N9: =MAX(0,L9-M9) -> 10000 | P9: =L9-E9 -> 0 | Q9: Not Started
B10: BG004 | C10: VENUE & HOTEL | D10: Groom's getting-ready room | E10: 10000 | F10: Required | G10: Groom | L10: =IF($F10="Not Applicable",0,IF(K10>0,K10,IF(J10>0,J10,IF(I10>0,I10,E10)))) -> 10000 | M10: =SUMIFS('04 Payments'!$K$7:$K$400,'04 Payments'!$D$7:$D$400,$B10) -> 0 | N10: =MAX(0,L10-M10) -> 10000 | P10: =L10-E10 -> 0 | Q10: Not Started
B11: BG005 | C11: VENUE & HOTEL | D11: Service charge (10%) | E11: 180000 | F11: Required | G11: Groom | L11: =IF($F11="Not Applicable",0,IF(K11>0,K11,IF(J11>0,J11,IF(I11>0,I11,E11)))) -> 180000 | M11: =SUMIFS('04 Payments'!$K$7:$K$400,'04 Payments'!$D$7:$D$400,$B11) -> 0 | N11: =MAX(0,L11-M11) -> 180000 | P11: =L11-E11 -> 0 | Q11: Not Started
B12: BG006 | C12: VENUE & HOTEL | D12: Government taxes (VAT / SSCL / TDL) (18%) | E12: 324000 | F12: Required | G12: Groom | L12: =IF($F12="Not Applicable",0,IF(K12>0,K12,IF(J12>0,J12,IF(I12>0,I12,E12)))) -> 324000 | M12: =SUMIFS('04 Payments'!$K$7:$K$400,'04 Payments'!$D$7:$D$400,$B12) -> 0 | N12: =MAX(0,L12-M12) -> 324000 | P12: =L12-E12 -> 0 | Q12: Not Started
B13: BG007 | C13: VENUE & HOTEL | D13: Corkage | E13: 0 | F13: Not Applicable | L13: =IF($F13="Not Applicable",0,IF(K13>0,K13,IF(J13>0,J13,IF(I13>0,I13,E13)))) -> 0 | M13: =SUMIFS('04 Payments'!$K$7:$K$400,'04 Payments'!$D$7:$D$400,$B13) -> 0 | N13: =MAX(0,L13-M13) -> 0 | P13: =L13-E13 -> 0 | Q13: Not Started
B14: BG008 | C14: VENUE & HOTEL | D14: Overtime / extra hours | E14: 40000 | F14: Not Applicable | L14: =IF($F14="Not Applicable",0,IF(K14>0,K14,IF(J14>0,J14,IF(I14>0,I14,E14)))) -> 0 | M14: =SUMIFS('04 Payments'!$K$7:$K$400,'04 Payments'!$D$7:$D$400,$B14) -> 0 | N14: =MAX(0,L14-M14) -> 0 | P14: =L14-E14 -> -40000 | Q14: Not Started
B15: BG009 | C15: VENUE & HOTEL | D15: Generator / power backup | E15: 25000 | F15: Not Applicable | L15: =IF($F15="Not Applicable",0,IF(K15>0,K15,IF(J15>0,J15,IF(I15>0,I15,E15)))) -> 0 | M15: =SUMIFS('04 Payments'!$K$7:$K$400,'04 Payments'!$D$7:$D$400,$B15) -> 0 | N15: =MAX(0,L15-M15) -> 0 | P15: =L15-E15 -> -25000 | Q15: Not Started
B16: BG010 | C16: VENUE & HOTEL | D16: Parking | E16: 0 | F16: Not Applicable | L16: =IF($F16="Not Applicable",0,IF(K16>0,K16,IF(J16>0,J16,IF(I16>0,I16,E16)))) -> 0 | M16: =SUMIFS('04 Payments'!$K$7:$K$400,'04 Payments'!$D$7:$D$400,$B16) -> 0 | N16: =MAX(0,L16-M16) -> 0 | P16: =L16-E16 -> 0 | Q16: Not Started
B17: BG011 | C17: VENUE & HOTEL | D17: Security | E17: 15000 | F17: Not Applicable | L17: =IF($F17="Not Applicable",0,IF(K17>0,K17,IF(J17>0,J17,IF(I17>0,I17,E17)))) -> 0 | M17: =SUMIFS('04 Payments'!$K$7:$K$400,'04 Payments'!$D$7:$D$400,$B17) -> 0 | N17: =MAX(0,L17-M17) -> 0 | P17: =L17-E17 -> -15000 | Q17: Not Started
B18: BG012 | C18: VENUE & HOTEL | D18: Cleaning | E18: 0 | F18: Not Applicable | L18: =IF($F18="Not Applicable",0,IF(K18>0,K18,IF(J18>0,J18,IF(I18>0,I18,E18)))) -> 0 | M18: =SUMIFS('04 Payments'!$K$7:$K$400,'04 Payments'!$D$7:$D$400,$B18) -> 0 | N18: =MAX(0,L18-M18) -> 0 | P18: =L18-E18 -> 0 | Q18: Not Started
B19: BG013 | C19: VENUE & HOTEL | D19: Additional venue equipment hire | E19: 20000 | F19: Not Applicable | L19: =IF($F19="Not Applicable",0,IF(K19>0,K19,IF(J19>0,J19,IF(I19>0,I19,E19)))) -> 0 | M19: =SUMIFS('04 Payments'!$K$7:$K$400,'04 Payments'!$D$7:$D$400,$B19) -> 0 | N19: =MAX(0,L19-M19) -> 0 | P19: =L19-E19 -> -20000 | Q19: Not Started
B20: BG014 | C20: FOOD & BEVERAGE | D20: Reception buffet - adults (per head x pax) | E20: 1800000 | F20: Required | G20: Groom | L20: =IF($F20="Not Applicable",0,IF(K20>0,K20,IF(J20>0,J20,IF(I20>0,I20,E20)))) -> 1800000 | M20: =SUMIFS('04 Payments'!$K$7:$K$400,'04 Payments'!$D$7:$D$400,$B20) -> 0 | N20: =MAX(0,L20-M20) -> 1800000 | P20: =L20-E20 -> 0 | Q20: Not Started
B21: BG015 | C21: FOOD & BEVERAGE | D21: Children's meals | E21: 45000 | F21: Not Applicable | L21: =IF($F21="Not Applicable",0,IF(K21>0,K21,IF(J21>0,J21,IF(I21>0,I21,E21)))) -> 0 | M21: =SUMIFS('04 Payments'!$K$7:$K$400,'04 Payments'!$D$7:$D$400,$B21) -> 0 | N21: =MAX(0,L21-M21) -> 0 | P21: =L21-E21 -> -45000 | Q21: Not Started
B22: BG016 | C22: FOOD & BEVERAGE | D22: Welcome drinks | E22: 60000 | F22: Not Applicable | L22: =IF($F22="Not Applicable",0,IF(K22>0,K22,IF(J22>0,J22,IF(I22>0,I22,E22)))) -> 0 | M22: =SUMIFS('04 Payments'!$K$7:$K$400,'04 Payments'!$D$7:$D$400,$B22) -> 0 | N22: =MAX(0,L22-M22) -> 0 | P22: =L22-E22 -> -60000 | Q22: Not Started
B23: BG017 | C23: FOOD & BEVERAGE | D23: Canapes / short eats on arrival | E23: 70000 | F23: Not Applicable | L23: =IF($F23="Not Applicable",0,IF(K23>0,K23,IF(J23>0,J23,IF(I23>0,I23,E23)))) -> 0 | M23: =SUMIFS('04 Payments'!$K$7:$K$400,'04 Payments'!$D$7:$D$400,$B23) -> 0 | N23: =MAX(0,L23-M23) -> 0 | P23: =L23-E23 -> -70000 | Q23: Not Started
B24: BG018 | C24: FOOD & BEVERAGE | D24: Dessert counter | E24: 50000 | F24: Not Applicable | L24: =IF($F24="Not Applicable",0,IF(K24>0,K24,IF(J24>0,J24,IF(I24>0,I24,E24)))) -> 0 | M24: =SUMIFS('04 Payments'!$K$7:$K$400,'04 Payments'!$D$7:$D$400,$B24) -> 0 | N24: =MAX(0,L24-M24) -> 0 | P24: =L24-E24 -> -50000 | Q24: Not Started
B25: BG019 | C25: FOOD & BEVERAGE | D25: Tea / coffee station | E25: 25000 | F25: Required | G25: Groom's Family | L25: =IF($F25="Not Applicable",0,IF(K25>0,K25,IF(J25>0,J25,IF(I25>0,I25,E25)))) -> 25000 | M25: =SUMIFS('04 Payments'!$K$7:$K$400,'04 Payments'!$D$7:$D$400,$B25) -> 0 | N25: =MAX(0,L25-M25) -> 25000 | P25: =L25-E25 -> 0 | Q25: Not Started
B26: BG020 | C26: FOOD & BEVERAGE | D26: Bottled water | E26: 18000 | F26: Not Applicable | L26: =IF($F26="Not Applicable",0,IF(K26>0,K26,IF(J26>0,J26,IF(I26>0,I26,E26)))) -> 0 | M26: =SUMIFS('04 Payments'!$K$7:$K$400,'04 Payments'!$D$7:$D$400,$B26) -> 0 | N26: =MAX(0,L26-M26) -> 0 | P26: =L26-E26 -> -18000 | Q26: Not Started
B27: BG021 | C27: FOOD & BEVERAGE | D27: Soft drinks | E27: 45000 | F27: Required | G27: Groom's Family | L27: =IF($F27="Not Applicable",0,IF(K27>0,K27,IF(J27>0,J27,IF(I27>0,I27,E27)))) -> 45000 | M27: =SUMIFS('04 Payments'!$K$7:$K$400,'04 Payments'!$D$7:$D$400,$B27) -> 0 | N27: =MAX(0,L27-M27) -> 45000 | P27: =L27-E27 -> 0 | Q27: Not Started
B28: BG022 | C28: FOOD & BEVERAGE | D28: Alcohol - bar stock | E28: 100000 | F28: Required | G28: Groom's Family | L28: =IF($F28="Not Applicable",0,IF(K28>0,K28,IF(J28>0,J28,IF(I28>0,I28,E28)))) -> 100000 | M28: =SUMIFS('04 Payments'!$K$7:$K$400,'04 Payments'!$D$7:$D$400,$B28) -> 0 | N28: =MAX(0,L28-M28) -> 100000 | P28: =L28-E28 -> 0 | Q28: Not Started
B29: BG023 | C29: FOOD & BEVERAGE | D29: Bar service / bartender | E29: 30000 | F29: Not Applicable | L29: =IF($F29="Not Applicable",0,IF(K29>0,K29,IF(J29>0,J29,IF(I29>0,I29,E29)))) -> 0 | M29: =SUMIFS('04 Payments'!$K$7:$K$400,'04 Payments'!$D$7:$D$400,$B29) -> 0 | N29: =MAX(0,L29-M29) -> 0 | P29: =L29-E29 -> -30000 | Q29: Not Started
B30: BG024 | C30: FOOD & BEVERAGE | D30: Ice | E30: 2000 | F30: Optional | G30: Groom | L30: =IF($F30="Not Applicable",0,IF(K30>0,K30,IF(J30>0,J30,IF(I30>0,I30,E30)))) -> 2000 | M30: =SUMIFS('04 Payments'!$K$7:$K$400,'04 Payments'!$D$7:$D$400,$B30) -> 0 | N30: =MAX(0,L30-M30) -> 2000 | P30: =L30-E30 -> 0 | Q30: Not Started
B31: BG025 | C31: FOOD & BEVERAGE | D31: Vendor & crew meals | E31: 25000 | F31: Required | G31: Groom | L31: =IF($F31="Not Applicable",0,IF(K31>0,K31,IF(J31>0,J31,IF(I31>0,I31,E31)))) -> 25000 | M31: =SUMIFS('04 Payments'!$K$7:$K$400,'04 Payments'!$D$7:$D$400,$B31) -> 0 | N31: =MAX(0,L31-M31) -> 25000 | P31: =L31-E31 -> 0 | Q31: Not Started
B32: BG026 | C32: FOOD & BEVERAGE | D32: Kiribath & sweets for the Poruwa | E32: 10000 | F32: Required | G32: Groom | L32: =IF($F32="Not Applicable",0,IF(K32>0,K32,IF(J32>0,J32,IF(I32>0,I32,E32)))) -> 10000 | M32: =SUMIFS('04 Payments'!$K$7:$K$400,'04 Payments'!$D$7:$D$400,$B32) -> 0 | N32: =MAX(0,L32-M32) -> 10000 | P32: =L32-E32 -> 0 | Q32: Not Started
B33: BG027 | C33: FOOD & BEVERAGE | D33: Late-night snack | E33: 0 | F33: Not Applicable | L33: =IF($F33="Not Applicable",0,IF(K33>0,K33,IF(J33>0,J33,IF(I33>0,I33,E33)))) -> 0 | M33: =SUMIFS('04 Payments'!$K$7:$K$400,'04 Payments'!$D$7:$D$400,$B33) -> 0 | N33: =MAX(0,L33-M33) -> 0 | P33: =L33-E33 -> 0 | Q33: Not Started
B34: BG028 | C34: CAKE | D34: Wedding cake (tiers) | E34: 30000 | F34: Required | G34: Shared | L34: =IF($F34="Not Applicable",0,IF(K34>0,K34,IF(J34>0,J34,IF(I34>0,I34,E34)))) -> 30000 | M34: =SUMIFS('04 Payments'!$K$7:$K$400,'04 Payments'!$D$7:$D$400,$B34) -> 0 | N34: =MAX(0,L34-M34) -> 30000 | P34: =L34-E34 -> 0 | Q34: Not Started
B35: BG029 | C35: CAKE | D35: Boxed cake pieces for guests | E35: 90000 | F35: Required | G35: Shared | L35: =IF($F35="Not Applicable",0,IF(K35>0,K35,IF(J35>0,J35,IF(I35>0,I35,E35)))) -> 90000 | M35: =SUMIFS('04 Payments'!$K$7:$K$400,'04 Payments'!$D$7:$D$400,$B35) -> 0 | N35: =MAX(0,L35-M35) -> 90000 | P35: =L35-E35 -> 0 | Q35: Not Started
B36: BG030 | C36: CAKE | D36: Cake stand & knife hire | E36: 6000 | F36: Not Applicable | L36: =IF($F36="Not Applicable",0,IF(K36>0,K36,IF(J36>0,J36,IF(I36>0,I36,E36)))) -> 0 | M36: =SUMIFS('04 Payments'!$K$7:$K$400,'04 Payments'!$D$7:$D$400,$B36) -> 0 | N36: =MAX(0,L36-M36) -> 0 | P36: =L36-E36 -> -6000 | Q36: Not Started
B37: BG031 | C37: CAKE | D37: Cake topper | E37: 4000 | F37: Not Applicable | L37: =IF($F37="Not Applicable",0,IF(K37>0,K37,IF(J37>0,J37,IF(I37>0,I37,E37)))) -> 0 | M37: =SUMIFS('04 Payments'!$K$7:$K$400,'04 Payments'!$D$7:$D$400,$B37) -> 0 | N37: =MAX(0,L37-M37) -> 0 | P37: =L37-E37 -> -4000 | Q37: Not Started
B38: BG032 | C38: CAKE | D38: Cake delivery & setup | E38: 5000 | F38: Not Applicable | L38: =IF($F38="Not Applicable",0,IF(K38>0,K38,IF(J38>0,J38,IF(I38>0,I38,E38)))) -> 0 | M38: =SUMIFS('04 Payments'!$K$7:$K$400,'04 Payments'!$D$7:$D$400,$B38) -> 0 | N38: =MAX(0,L38-M38) -> 0 | P38: =L38-E38 -> -5000 | Q38: Not Started
B39: BG033 | C39: PHOTOGRAPHY | D39: Pre-shoot photography | E39: 20000 | F39: Required | G39: Groom | L39: =IF($F39="Not Applicable",0,IF(K39>0,K39,IF(J39>0,J39,IF(I39>0,I39,E39)))) -> 20000 | M39: =SUMIFS('04 Payments'!$K$7:$K$400,'04 Payments'!$D$7:$D$400,$B39) -> 0 | N39: =MAX(0,L39-M39) -> 20000 | P39: =L39-E39 -> 0 | Q39: Not Started
B40: BG034 | C40: PHOTOGRAPHY | D40: Wedding-day photography | E40: 150000 | F40: Required | G40: Groom | L40: =IF($F40="Not Applicable",0,IF(K40>0,K40,IF(J40>0,J40,IF(I40>0,I40,E40)))) -> 150000 | M40: =SUMIFS('04 Payments'!$K$7:$K$400,'04 Payments'!$D$7:$D$400,$B40) -> 0 | N40: =MAX(0,L40-M40) -> 150000 | P40: =L40-E40 -> 0 | Q40: Not Started
B41: BG035 | C41: PHOTOGRAPHY | D41: Second photographer | E41: 45000 | F41: Not Applicable | L41: =IF($F41="Not Applicable",0,IF(K41>0,K41,IF(J41>0,J41,IF(I41>0,I41,E41)))) -> 0 | M41: =SUMIFS('04 Payments'!$K$7:$K$400,'04 Payments'!$D$7:$D$400,$B41) -> 0 | N41: =MAX(0,L41-M41) -> 0 | P41: =L41-E41 -> -45000 | Q41: Not Started
B42: BG036 | C42: PHOTOGRAPHY | D42: Assistant | E42: 15000 | F42: Not Applicable | L42: =IF($F42="Not Applicable",0,IF(K42>0,K42,IF(J42>0,J42,IF(I42>0,I42,E42)))) -> 0 | M42: =SUMIFS('04 Payments'!$K$7:$K$400,'04 Payments'!$D$7:$D$400,$B42) -> 0 | N42: =MAX(0,L42-M42) -> 0 | P42: =L42-E42 -> -15000 | Q42: Not Started
B43: BG037 | C43: PHOTOGRAPHY | D43: Signature album | E43: 55000 | F43: Not Applicable | L43: =IF($F43="Not Applicable",0,IF(K43>0,K43,IF(J43>0,J43,IF(I43>0,I43,E43)))) -> 0 | M43: =SUMIFS('04 Payments'!$K$7:$K$400,'04 Payments'!$D$7:$D$400,$B43) -> 0 | N43: =MAX(0,L43-M43) -> 0 | P43: =L43-E43 -> -55000 | Q43: Not Started
B44: BG038 | C44: PHOTOGRAPHY | D44: Parent albums (x2) | E44: 30000 | F44: Not Applicable | L44: =IF($F44="Not Applicable",0,IF(K44>0,K44,IF(J44>0,J44,IF(I44>0,I44,E44)))) -> 0 | M44: =SUMIFS('04 Payments'!$K$7:$K$400,'04 Payments'!$D$7:$D$400,$B44) -> 0 | N44: =MAX(0,L44-M44) -> 0 | P44: =L44-E44 -> -30000 | Q44: Not Started
B45: BG039 | C45: PHOTOGRAPHY | D45: Enlargements & frames | E45: 15000 | F45: Not Applicable | L45: =IF($F45="Not Applicable",0,IF(K45>0,K45,IF(J45>0,J45,IF(I45>0,I45,E45)))) -> 0 | M45: =SUMIFS('04 Payments'!$K$7:$K$400,'04 Payments'!$D$7:$D$400,$B45) -> 0 | N45: =MAX(0,L45-M45) -> 0 | P45: =L45-E45 -> -15000 | Q45: Not Started
B46: BG040 | C46: PHOTOGRAPHY | D46: Thank you card prints | E46: 10000 | F46: Optional | G46: Groom | L46: =IF($F46="Not Applicable",0,IF(K46>0,K46,IF(J46>0,J46,IF(I46>0,I46,E46)))) -> 10000 | M46: =SUMIFS('04 Payments'!$K$7:$K$400,'04 Payments'!$D$7:$D$400,$B46) -> 0 | N46: =MAX(0,L46-M46) -> 10000 | P46: =L46-E46 -> 0 | Q46: Not Started
B47: BG041 | C47: PHOTOGRAPHY | D47: Drone photography | E47: 10000 | F47: Not Applicable | L47: =IF($F47="Not Applicable",0,IF(K47>0,K47,IF(J47>0,J47,IF(I47>0,I47,E47)))) -> 0 | M47: =SUMIFS('04 Payments'!$K$7:$K$400,'04 Payments'!$D$7:$D$400,$B47) -> 0 | N47: =MAX(0,L47-M47) -> 0 | P47: =L47-E47 -> -10000 | Q47: Not Started
B48: BG042 | C48: PHOTOGRAPHY | D48: Raw files / USB delivery | E48: 0 | F48: Required | L48: =IF($F48="Not Applicable",0,IF(K48>0,K48,IF(J48>0,J48,IF(I48>0,I48,E48)))) -> 0 | M48: =SUMIFS('04 Payments'!$K$7:$K$400,'04 Payments'!$D$7:$D$400,$B48) -> 0 | N48: =MAX(0,L48-M48) -> 0 | P48: =L48-E48 -> 0 | Q48: Not Started
B49: BG043 | C49: PHOTOGRAPHY | D49: Same-day edit slideshow | E49: 0 | F49: Optional | L49: =IF($F49="Not Applicable",0,IF(K49>0,K49,IF(J49>0,J49,IF(I49>0,I49,E49)))) -> 0 | M49: =SUMIFS('04 Payments'!$K$7:$K$400,'04 Payments'!$D$7:$D$400,$B49) -> 0 | N49: =MAX(0,L49-M49) -> 0 | P49: =L49-E49 -> 0 | Q49: Not Started
B50: BG044 | C50: PHOTOGRAPHY | D50: Extra hours | E50: 0 | F50: Optional | L50: =IF($F50="Not Applicable",0,IF(K50>0,K50,IF(J50>0,J50,IF(I50>0,I50,E50)))) -> 0 | M50: =SUMIFS('04 Payments'!$K$7:$K$400,'04 Payments'!$D$7:$D$400,$B50) -> 0 | N50: =MAX(0,L50-M50) -> 0 | P50: =L50-E50 -> 0 | Q50: Not Started
B51: BG045 | C51: VIDEOGRAPHY | D51: Pre-shoot video | E51: 35000 | F51: Not Applicable | L51: =IF($F51="Not Applicable",0,IF(K51>0,K51,IF(J51>0,J51,IF(I51>0,I51,E51)))) -> 0 | M51: =SUMIFS('04 Payments'!$K$7:$K$400,'04 Payments'!$D$7:$D$400,$B51) -> 0 | N51: =MAX(0,L51-M51) -> 0 | P51: =L51-E51 -> -35000 | Q51: Not Started
B52: BG046 | C52: VIDEOGRAPHY | D52: Wedding-day videography | E52: 180000 | F52: Not Applicable | L52: =IF($F52="Not Applicable",0,IF(K52>0,K52,IF(J52>0,J52,IF(I52>0,I52,E52)))) -> 0 | M52: =SUMIFS('04 Payments'!$K$7:$K$400,'04 Payments'!$D$7:$D$400,$B52) -> 0 | N52: =MAX(0,L52-M52) -> 0 | P52: =L52-E52 -> -180000 | Q52: Not Started
B53: BG047 | C53: VIDEOGRAPHY | D53: Second videographer | E53: 40000 | F53: Not Applicable | L53: =IF($F53="Not Applicable",0,IF(K53>0,K53,IF(J53>0,J53,IF(I53>0,I53,E53)))) -> 0 | M53: =SUMIFS('04 Payments'!$K$7:$K$400,'04 Payments'!$D$7:$D$400,$B53) -> 0 | N53: =MAX(0,L53-M53) -> 0 | P53: =L53-E53 -> -40000 | Q53: Not Started
B54: BG048 | C54: VIDEOGRAPHY | D54: Cinematic highlight films | E54: 25000 | F54: Required | G54: Groom | L54: =IF($F54="Not Applicable",0,IF(K54>0,K54,IF(J54>0,J54,IF(I54>0,I54,E54)))) -> 25000 | M54: =SUMIFS('04 Payments'!$K$7:$K$400,'04 Payments'!$D$7:$D$400,$B54) -> 0 | N54: =MAX(0,L54-M54) -> 25000 | P54: =L54-E54 -> 0 | Q54: Not Started
B55: BG049 | C55: VIDEOGRAPHY | D55: Full-length edit | E55: 25000 | F55: Not Applicable | L55: =IF($F55="Not Applicable",0,IF(K55>0,K55,IF(J55>0,J55,IF(I55>0,I55,E55)))) -> 0 | M55: =SUMIFS('04 Payments'!$K$7:$K$400,'04 Payments'!$D$7:$D$400,$B55) -> 0 | N55: =MAX(0,L55-M55) -> 0 | P55: =L55-E55 -> -25000 | Q55: Not Started
B56: BG050 | C56: VIDEOGRAPHY | D56: Drone video | E56: 10000 | F56: Optional | G56: Groom | L56: =IF($F56="Not Applicable",0,IF(K56>0,K56,IF(J56>0,J56,IF(I56>0,I56,E56)))) -> 10000 | M56: =SUMIFS('04 Payments'!$K$7:$K$400,'04 Payments'!$D$7:$D$400,$B56) -> 0 | N56: =MAX(0,L56-M56) -> 10000 | P56: =L56-E56 -> 0 | Q56: Not Started
B57: BG051 | C57: VIDEOGRAPHY | D57: Live stream for overseas family | E57: 30000 | F57: Not Applicable | L57: =IF($F57="Not Applicable",0,IF(K57>0,K57,IF(J57>0,J57,IF(I57>0,I57,E57)))) -> 0 | M57: =SUMIFS('04 Payments'!$K$7:$K$400,'04 Payments'!$D$7:$D$400,$B57) -> 0 | N57: =MAX(0,L57-M57) -> 0 | P57: =L57-E57 -> -30000 | Q57: Not Started
B58: BG052 | C58: VIDEOGRAPHY | D58: Raw footage / storage drive | E58: 0 | F58: Required | L58: =IF($F58="Not Applicable",0,IF(K58>0,K58,IF(J58>0,J58,IF(I58>0,I58,E58)))) -> 0 | M58: =SUMIFS('04 Payments'!$K$7:$K$400,'04 Payments'!$D$7:$D$400,$B58) -> 0 | N58: =MAX(0,L58-M58) -> 0 | P58: =L58-E58 -> 0 | Q58: Not Started
B59: BG053 | C59: VIDEOGRAPHY | D59: Extra hours | E59: 0 | F59: Not Applicable | L59: =IF($F59="Not Applicable",0,IF(K59>0,K59,IF(J59>0,J59,IF(I59>0,I59,E59)))) -> 0 | M59: =SUMIFS('04 Payments'!$K$7:$K$400,'04 Payments'!$D$7:$D$400,$B59) -> 0 | N59: =MAX(0,L59-M59) -> 0 | P59: =L59-E59 -> 0 | Q59: Not Started
B60: BG054 | C60: BRIDE - ATTIRE & BEAUTY | D60: Kandyan / Poruwa saree (osari) | E60: 50000 | F60: Required | G60: Bride's Family | L60: =IF($F60="Not Applicable",0,IF(K60>0,K60,IF(J60>0,J60,IF(I60>0,I60,E60)))) -> 50000 | M60: =SUMIFS('04 Payments'!$K$7:$K$400,'04 Payments'!$D$7:$D$400,$B60) -> 0 | N60: =MAX(0,L60-M60) -> 50000 | P60: =L60-E60 -> 0 | Q60: Not Started
B61: BG055 | C61: BRIDE - ATTIRE & BEAUTY | D61: Reception / going-away outfit | E61: 0 | F61: Optional | L61: =IF($F61="Not Applicable",0,IF(K61>0,K61,IF(J61>0,J61,IF(I61>0,I61,E61)))) -> 0 | M61: =SUMIFS('04 Payments'!$K$7:$K$400,'04 Payments'!$D$7:$D$400,$B61) -> 0 | N61: =MAX(0,L61-M61) -> 0 | P61: =L61-E61 -> 0 | Q61: Not Started
B62: BG056 | C62: BRIDE - ATTIRE & BEAUTY | D62: Bridal shoes | E62: 5000 | F62: Required | G62: Bride's Family | L62: =IF($F62="Not Applicable",0,IF(K62>0,K62,IF(J62>0,J62,IF(I62>0,I62,E62)))) -> 5000 | M62: =SUMIFS('04 Payments'!$K$7:$K$400,'04 Payments'!$D$7:$D$400,$B62) -> 0 | N62: =MAX(0,L62-M62) -> 5000 | P62: =L62-E62 -> 0 | Q62: Not Started
B63: BG057 | C63: BRIDE - ATTIRE & BEAUTY | D63: Veil | E63: 12000 | F63: Not Applicable | L63: =IF($F63="Not Applicable",0,IF(K63>0,K63,IF(J63>0,J63,IF(I63>0,I63,E63)))) -> 0 | M63: =SUMIFS('04 Payments'!$K$7:$K$400,'04 Payments'!$D$7:$D$400,$B63) -> 0 | N63: =MAX(0,L63-M63) -> 0 | P63: =L63-E63 -> -12000 | Q63: Not Started
B64: BG058 | C64: BRIDE - ATTIRE & BEAUTY | D64: Bridal bouquet | E64: 5000 | F64: Required | G64: Bride's Family | L64: =IF($F64="Not Applicable",0,IF(K64>0,K64,IF(J64>0,J64,IF(I64>0,I64,E64)))) -> 5000 | M64: =SUMIFS('04 Payments'!$K$7:$K$400,'04 Payments'!$D$7:$D$400,$B64) -> 0 | N64: =MAX(0,L64-M64) -> 5000 | P64: =L64-E64 -> 0 | Q64: Not Started
B65: BG059 | C65: BRIDE - ATTIRE & BEAUTY | D65: Bridal dressing - hair & makeup (day) | E65: 120000 | F65: Required | G65: Bride's Family | L65: =IF($F65="Not Applicable",0,IF(K65>0,K65,IF(J65>0,J65,IF(I65>0,I65,E65)))) -> 120000 | M65: =SUMIFS('04 Payments'!$K$7:$K$400,'04 Payments'!$D$7:$D$400,$B65) -> 0 | N65: =MAX(0,L65-M65) -> 120000 | P65: =L65-E65 -> 0 | Q65: Not Started
B66: BG060 | C66: BRIDE - ATTIRE & BEAUTY | D66: Hair & makeup trial | E66: 20000 | F66: Required | G66: Bride's Family | L66: =IF($F66="Not Applicable",0,IF(K66>0,K66,IF(J66>0,J66,IF(I66>0,I66,E66)))) -> 20000 | M66: =SUMIFS('04 Payments'!$K$7:$K$400,'04 Payments'!$D$7:$D$400,$B66) -> 0 | N66: =MAX(0,L66-M66) -> 20000 | P66: =L66-E66 -> 0 | Q66: Not Started
B67: BG061 | C67: BRIDE - ATTIRE & BEAUTY | D67: Nails | E67: 6000 | F67: Required | G67: Bride's Family | L67: =IF($F67="Not Applicable",0,IF(K67>0,K67,IF(J67>0,J67,IF(I67>0,I67,E67)))) -> 6000 | M67: =SUMIFS('04 Payments'!$K$7:$K$400,'04 Payments'!$D$7:$D$400,$B67) -> 0 | N67: =MAX(0,L67-M67) -> 6000 | P67: =L67-E67 -> 0 | Q67: Not Started
B68: BG062 | C68: BRIDE - ATTIRE & BEAUTY | D68: Facial / skin treatment course | E68: 35000 | F68: Required | G68: Bride's Family | L68: =IF($F68="Not Applicable",0,IF(K68>0,K68,IF(J68>0,J68,IF(I68>0,I68,E68)))) -> 35000 | M68: =SUMIFS('04 Payments'!$K$7:$K$400,'04 Payments'!$D$7:$D$400,$B68) -> 0 | N68: =MAX(0,L68-M68) -> 35000 | P68: =L68-E68 -> 0 | Q68: Not Started
B69: BG063 | C69: BRIDE - ATTIRE & BEAUTY | D69: Hair treatment | E69: 12000 | F69: Optional | G69: Bride's Family | L69: =IF($F69="Not Applicable",0,IF(K69>0,K69,IF(J69>0,J69,IF(I69>0,I69,E69)))) -> 12000 | M69: =SUMIFS('04 Payments'!$K$7:$K$400,'04 Payments'!$D$7:$D$400,$B69) -> 0 | N69: =MAX(0,L69-M69) -> 12000 | P69: =L69-E69 -> 0 | Q69: Not Started
B70: BG064 | C70: BRIDE - ATTIRE & BEAUTY | D70: Undergarments & fittings | E70: 10000 | F70: Required | G70: Bride's Family | L70: =IF($F70="Not Applicable",0,IF(K70>0,K70,IF(J70>0,J70,IF(I70>0,I70,E70)))) -> 10000 | M70: =SUMIFS('04 Payments'!$K$7:$K$400,'04 Payments'!$D$7:$D$400,$B70) -> 0 | N70: =MAX(0,L70-M70) -> 10000 | P70: =L70-E70 -> 0 | Q70: Not Started
B71: BG065 | C71: BRIDE - ATTIRE & BEAUTY | D71: Saree draping / dresser assistant | E71: 15000 | F71: Not Applicable | L71: =IF($F71="Not Applicable",0,IF(K71>0,K71,IF(J71>0,J71,IF(I71>0,I71,E71)))) -> 0 | M71: =SUMIFS('04 Payments'!$K$7:$K$400,'04 Payments'!$D$7:$D$400,$B71) -> 0 | N71: =MAX(0,L71-M71) -> 0 | P71: =L71-E71 -> -15000 | Q71: Not Started
B72: BG066 | C72: BRIDE - ATTIRE & BEAUTY | D72: Bridal emergency kit | E72: 8000 | F72: Required | G72: Bride's Family | L72: =IF($F72="Not Applicable",0,IF(K72>0,K72,IF(J72>0,J72,IF(I72>0,I72,E72)))) -> 8000 | M72: =SUMIFS('04 Payments'!$K$7:$K$400,'04 Payments'!$D$7:$D$400,$B72) -> 0 | N72: =MAX(0,L72-M72) -> 8000 | P72: =L72-E72 -> 0 | Q72: Not Started
B73: BG067 | C73: GROOM - ATTIRE & GROOMING | D73: Wedding suit / national dress | E73: 10000 | F73: Required | G73: Groom | L73: =IF($F73="Not Applicable",0,IF(K73>0,K73,IF(J73>0,J73,IF(I73>0,I73,E73)))) -> 10000 | M73: =SUMIFS('04 Payments'!$K$7:$K$400,'04 Payments'!$D$7:$D$400,$B73) -> 0 | N73: =MAX(0,L73-M73) -> 10000 | P73: =L73-E73 -> 0 | Q73: Not Started
B74: BG068 | C74: GROOM - ATTIRE & GROOMING | D74: Shirt | E74: 3000 | F74: Required | G74: Groom | L74: =IF($F74="Not Applicable",0,IF(K74>0,K74,IF(J74>0,J74,IF(I74>0,I74,E74)))) -> 3000 | M74: =SUMIFS('04 Payments'!$K$7:$K$400,'04 Payments'!$D$7:$D$400,$B74) -> 0 | N74: =MAX(0,L74-M74) -> 3000 | P74: =L74-E74 -> 0 | Q74: Not Started
B75: BG069 | C75: GROOM - ATTIRE & GROOMING | D75: Tie / bow tie | E75: 1000 | F75: Required | G75: Groom | L75: =IF($F75="Not Applicable",0,IF(K75>0,K75,IF(J75>0,J75,IF(I75>0,I75,E75)))) -> 1000 | M75: =SUMIFS('04 Payments'!$K$7:$K$400,'04 Payments'!$D$7:$D$400,$B75) -> 0 | N75: =MAX(0,L75-M75) -> 1000 | P75: =L75-E75 -> 0 | Q75: Not Started
B76: BG070 | C76: GROOM - ATTIRE & GROOMING | D76: Shoes | E76: 4000 | F76: Required | G76: Groom | L76: =IF($F76="Not Applicable",0,IF(K76>0,K76,IF(J76>0,J76,IF(I76>0,I76,E76)))) -> 4000 | M76: =SUMIFS('04 Payments'!$K$7:$K$400,'04 Payments'!$D$7:$D$400,$B76) -> 0 | N76: =MAX(0,L76-M76) -> 4000 | P76: =L76-E76 -> 0 | Q76: Not Started
B77: BG071 | C77: GROOM - ATTIRE & GROOMING | D77: Belt | E77: 2000 | F77: Required | G77: Groom | L77: =IF($F77="Not Applicable",0,IF(K77>0,K77,IF(J77>0,J77,IF(I77>0,I77,E77)))) -> 2000 | M77: =SUMIFS('04 Payments'!$K$7:$K$400,'04 Payments'!$D$7:$D$400,$B77) -> 0 | N77: =MAX(0,L77-M77) -> 2000 | P77: =L77-E77 -> 0 | Q77: Not Started
B78: BG072 | C78: GROOM - ATTIRE & GROOMING | D78: Cufflinks & accessories | E78: 2000 | F78: Required | G78: Groom | L78: =IF($F78="Not Applicable",0,IF(K78>0,K78,IF(J78>0,J78,IF(I78>0,I78,E78)))) -> 2000 | M78: =SUMIFS('04 Payments'!$K$7:$K$400,'04 Payments'!$D$7:$D$400,$B78) -> 0 | N78: =MAX(0,L78-M78) -> 2000 | P78: =L78-E78 -> 0 | Q78: Not Started
B79: BG073 | C79: GROOM - ATTIRE & GROOMING | D79: Watch | E79: 0 | F79: Optional | L79: =IF($F79="Not Applicable",0,IF(K79>0,K79,IF(J79>0,J79,IF(I79>0,I79,E79)))) -> 0 | M79: =SUMIFS('04 Payments'!$K$7:$K$400,'04 Payments'!$D$7:$D$400,$B79) -> 0 | N79: =MAX(0,L79-M79) -> 0 | P79: =L79-E79 -> 0 | Q79: Not Started
B80: BG074 | C80: GROOM - ATTIRE & GROOMING | D80: Grooming & dressing on the day | E80: 15000 | F80: Required | G80: Groom | L80: =IF($F80="Not Applicable",0,IF(K80>0,K80,IF(J80>0,J80,IF(I80>0,I80,E80)))) -> 15000 | M80: =SUMIFS('04 Payments'!$K$7:$K$400,'04 Payments'!$D$7:$D$400,$B80) -> 0 | N80: =MAX(0,L80-M80) -> 15000 | P80: =L80-E80 -> 0 | Q80: Not Started
B81: BG075 | C81: GROOM - ATTIRE & GROOMING | D81: Haircut | E81: 3000 | F81: Required | G81: Groom | L81: =IF($F81="Not Applicable",0,IF(K81>0,K81,IF(J81>0,J81,IF(I81>0,I81,E81)))) -> 3000 | M81: =SUMIFS('04 Payments'!$K$7:$K$400,'04 Payments'!$D$7:$D$400,$B81) -> 0 | N81: =MAX(0,L81-M81) -> 3000 | P81: =L81-E81 -> 0 | Q81: Not Started
B82: BG076 | C82: GROOM - ATTIRE & GROOMING | D82: Facial / grooming treatment | E82: 6000 | F82: Optional | G82: Groom | L82: =IF($F82="Not Applicable",0,IF(K82>0,K82,IF(J82>0,J82,IF(I82>0,I82,E82)))) -> 6000 | M82: =SUMIFS('04 Payments'!$K$7:$K$400,'04 Payments'!$D$7:$D$400,$B82) -> 0 | N82: =MAX(0,L82-M82) -> 6000 | P82: =L82-E82 -> 0 | Q82: Not Started
B83: BG077 | C83: JEWELLERY | D83: Bridal necklace set | E83: 260000 | F83: Required | G83: Groom | H83: panadura gold house | I83: 395000 | K83: 395000 | L83: =IF($F83="Not Applicable",0,IF(K83>0,K83,IF(J83>0,J83,IF(I83>0,I83,E83)))) -> 395000 | M83: 395000 | N83: =MAX(0,L83-M83) -> 0 | P83: =L83-E83 -> 135000 | Q83: Completed
B84: BG078 | C84: JEWELLERY | D84: Earrings | E84: 40000 | F84: Not Applicable | L84: =IF($F84="Not Applicable",0,IF(K84>0,K84,IF(J84>0,J84,IF(I84>0,I84,E84)))) -> 0 | M84: =SUMIFS('04 Payments'!$K$7:$K$400,'04 Payments'!$D$7:$D$400,$B84) -> 0 | N84: =MAX(0,L84-M84) -> 0 | P84: =L84-E84 -> -40000 | Q84: Not Started
B85: BG079 | C85: JEWELLERY | D85: Bangles | E85: 35000 | F85: Not Applicable | L85: =IF($F85="Not Applicable",0,IF(K85>0,K85,IF(J85>0,J85,IF(I85>0,I85,E85)))) -> 0 | M85: =SUMIFS('04 Payments'!$K$7:$K$400,'04 Payments'!$D$7:$D$400,$B85) -> 0 | N85: =MAX(0,L85-M85) -> 0 | P85: =L85-E85 -> -35000 | Q85: Not Started
B86: BG080 | C86: JEWELLERY | D86: Hair jewellery (nalalpata / konda mal) | E86: 30000 | F86: Not Applicable | L86: =IF($F86="Not Applicable",0,IF(K86>0,K86,IF(J86>0,J86,IF(I86>0,I86,E86)))) -> 0 | M86: =SUMIFS('04 Payments'!$K$7:$K$400,'04 Payments'!$D$7:$D$400,$B86) -> 0 | N86: =MAX(0,L86-M86) -> 0 | P86: =L86-E86 -> -30000 | Q86: Not Started
B87: BG081 | C87: JEWELLERY | D87: Anklets | E87: 0 | F87: Not Applicable | L87: =IF($F87="Not Applicable",0,IF(K87>0,K87,IF(J87>0,J87,IF(I87>0,I87,E87)))) -> 0 | M87: =SUMIFS('04 Payments'!$K$7:$K$400,'04 Payments'!$D$7:$D$400,$B87) -> 0 | N87: =MAX(0,L87-M87) -> 0 | P87: =L87-E87 -> 0 | Q87: Not Started
B88: BG082 | C88: JEWELLERY | D88: Wedding rings (pair) | E88: 432500 | F88: Required | G88: Groom | H88: panadura gold house | I88: 485000 | K88: 485000 | L88: =IF($F88="Not Applicable",0,IF(K88>0,K88,IF(J88>0,J88,IF(I88>0,I88,E88)))) -> 485000 | M88: 485000 | N88: =MAX(0,L88-M88) -> 0 | P88: =L88-E88 -> 52500 | Q88: Completed
B89: BG083 | C89: JEWELLERY | D89: Bride's brother ring | E89: 43000 | F89: Optional | G89: Groom | H89: panadura gold house | I89: 16000 | K89: 16000 | L89: =IF($F89="Not Applicable",0,IF(K89>0,K89,IF(J89>0,J89,IF(I89>0,I89,E89)))) -> 16000 | M89: 16000 | N89: =MAX(0,L89-M89) -> 0 | P89: =L89-E89 -> -27000 | Q89: Completed
B90: BG084 | C90: JEWELLERY | D90: Jewellery rental deposit (refundable) | E90: 50000 | F90: Not Applicable | L90: =IF($F90="Not Applicable",0,IF(K90>0,K90,IF(J90>0,J90,IF(I90>0,I90,E90)))) -> 0 | M90: =SUMIFS('04 Payments'!$K$7:$K$400,'04 Payments'!$D$7:$D$400,$B90) -> 0 | N90: =MAX(0,L90-M90) -> 0 | P90: =L90-E90 -> -50000 | Q90: Not Started
B91: BG085 | C91: JEWELLERY | D91: Jewellery insurance / security escort | E91: 15000 | F91: Not Applicable | L91: =IF($F91="Not Applicable",0,IF(K91>0,K91,IF(J91>0,J91,IF(I91>0,I91,E91)))) -> 0 | M91: =SUMIFS('04 Payments'!$K$7:$K$400,'04 Payments'!$D$7:$D$400,$B91) -> 0 | N91: =MAX(0,L91-M91) -> 0 | P91: =L91-E91 -> -15000 | Q91: Not Started
B92: BG086 | C92: JEWELLERY | D92: Safe storage & transport | E92: 0 | F92: Not Applicable | L92: =IF($F92="Not Applicable",0,IF(K92>0,K92,IF(J92>0,J92,IF(I92>0,I92,E92)))) -> 0 | M92: =SUMIFS('04 Payments'!$K$7:$K$400,'04 Payments'!$D$7:$D$400,$B92) -> 0 | N92: =MAX(0,L92-M92) -> 0 | P92: =L92-E92 -> 0 | Q92: Not Started
B93: BG087 | C93: BRIDAL PARTY | D93: Bridesmaids' outfits | E93: 30000 | F93: Required | G93: Bride's Family | L93: =IF($F93="Not Applicable",0,IF(K93>0,K93,IF(J93>0,J93,IF(I93>0,I93,E93)))) -> 30000 | M93: =SUMIFS('04 Payments'!$K$7:$K$400,'04 Payments'!$D$7:$D$400,$B93) -> 0 | N93: =MAX(0,L93-M93) -> 30000 | P93: =L93-E93 -> 0 | Q93: Not Started
B94: BG088 | C94: BRIDAL PARTY | D94: Groomsmen's outfits | E94: 5000 | F94: Required | G94: Groom | L94: =IF($F94="Not Applicable",0,IF(K94>0,K94,IF(J94>0,J94,IF(I94>0,I94,E94)))) -> 5000 | M94: =SUMIFS('04 Payments'!$K$7:$K$400,'04 Payments'!$D$7:$D$400,$B94) -> 0 | N94: =MAX(0,L94-M94) -> 5000 | P94: =L94-E94 -> 0 | Q94: Not Started
B95: BG089 | C95: BRIDAL PARTY | D95: Flower girl / page boy outfits | E95: 25000 | F95: Not Applicable | L95: =IF($F95="Not Applicable",0,IF(K95>0,K95,IF(J95>0,J95,IF(I95>0,I95,E95)))) -> 0 | M95: =SUMIFS('04 Payments'!$K$7:$K$400,'04 Payments'!$D$7:$D$400,$B95) -> 0 | N95: =MAX(0,L95-M95) -> 0 | P95: =L95-E95 -> -25000 | Q95: Not Started
B96: BG090 | C96: BRIDAL PARTY | D96: Bridesmaids' hair & makeup | E96: 20000 | F96: Required | G96: Bride's Family | L96: =IF($F96="Not Applicable",0,IF(K96>0,K96,IF(J96>0,J96,IF(I96>0,I96,E96)))) -> 20000 | M96: =SUMIFS('04 Payments'!$K$7:$K$400,'04 Payments'!$D$7:$D$400,$B96) -> 0 | N96: =MAX(0,L96-M96) -> 20000 | P96: =L96-E96 -> 0 | Q96: Not Started
B97: BG091 | C97: BRIDAL PARTY | D97: Bridal party bouquets | E97: 10000 | F97: Required | G97: Bride's Family | L97: =IF($F97="Not Applicable",0,IF(K97>0,K97,IF(J97>0,J97,IF(I97>0,I97,E97)))) -> 10000 | M97: =SUMIFS('04 Payments'!$K$7:$K$400,'04 Payments'!$D$7:$D$400,$B97) -> 0 | N97: =MAX(0,L97-M97) -> 10000 | P97: =L97-E97 -> 0 | Q97: Not Started
B98: BG092 | C98: BRIDAL PARTY | D98: Boutonnieres (groomsmen's blazer flower) | E98: 2000 | F98: Required | G98: Groom | L98: =IF($F98="Not Applicable",0,IF(K98>0,K98,IF(J98>0,J98,IF(I98>0,I98,E98)))) -> 2000 | M98: =SUMIFS('04 Payments'!$K$7:$K$400,'04 Payments'!$D$7:$D$400,$B98) -> 0 | N98: =MAX(0,L98-M98) -> 2000 | P98: =L98-E98 -> 0 | Q98: Not Started
B99: BG093 | C99: BRIDAL PARTY | D99: Bridal party gifts | E99: 30000 | F99: Not Applicable | L99: =IF($F99="Not Applicable",0,IF(K99>0,K99,IF(J99>0,J99,IF(I99>0,I99,E99)))) -> 0 | M99: =SUMIFS('04 Payments'!$K$7:$K$400,'04 Payments'!$D$7:$D$400,$B99) -> 0 | N99: =MAX(0,L99-M99) -> 0 | P99: =L99-E99 -> -30000 | Q99: Not Started
B100: BG094 | C100: DECOR & FLORALS | D100: Poruwa structure & decoration | E100: 120000 | F100: Not Applicable | L100: =IF($F100="Not Applicable",0,IF(K100>0,K100,IF(J100>0,J100,IF(I100>0,I100,E100)))) -> 0 | M100: =SUMIFS('04 Payments'!$K$7:$K$400,'04 Payments'!$D$7:$D$400,$B100) -> 0 | N100: =MAX(0,L100-M100) -> 0 | P100: =L100-E100 -> -120000 | Q100: Not Started
B101: BG095 | C101: DECOR & FLORALS | D101: Ceremony backdrop | E101: 60000 | F101: Not Applicable | L101: =IF($F101="Not Applicable",0,IF(K101>0,K101,IF(J101>0,J101,IF(I101>0,I101,E101)))) -> 0 | M101: =SUMIFS('04 Payments'!$K$7:$K$400,'04 Payments'!$D$7:$D$400,$B101) -> 0 | N101: =MAX(0,L101-M101) -> 0 | P101: =L101-E101 -> -60000 | Q101: Not Started
B102: BG096 | C102: DECOR & FLORALS | D102: Stage & head table decor | E102: 90000 | F102: Not Applicable | L102: =IF($F102="Not Applicable",0,IF(K102>0,K102,IF(J102>0,J102,IF(I102>0,I102,E102)))) -> 0 | M102: =SUMIFS('04 Payments'!$K$7:$K$400,'04 Payments'!$D$7:$D$400,$B102) -> 0 | N102: =MAX(0,L102-M102) -> 0 | P102: =L102-E102 -> -90000 | Q102: Not Started
...

Sheet 04 Payments
B2: PAYMENT & EXPENSE LEDGER
B3: One row per payment, planned or made. Type the Budget ID (column B on 03 Budget) and the category and line item fill themselves. This is the only place money is recorded - 03 Budget and 05 Vendors both read from it.
F5: TOTALS | I5: =SUM(I7:I400) -> 896000 | K5: =SUM(K7:K400) -> 896000 | M5: =SUM(M7:M400) -> 0
B6: ID | C6: Date raised | D6: Budget ID (type it in) | E6: Category (auto) | F6: Line item (auto) | G6: VENDOR (pick from the list) | H6: Payment stage | I6: Amount due | J6: Due date | K6: Amount paid | L6: Paid on | M6: Balance | N6: Method | O6: Reference | P6: Refundable? | Q6: Receipt? | R6: Receipt kept where | S6: STATUS | T6: Paid by | U6: Notes
B7: =IF($D7="","","PY"&TEXT(ROW()-6,"000")) -> PY001 | D7: BG077 | E7: {=IFERROR(INDEX('03 Budget'!$C$7:$C$300,MATCH($D7,'03 Budget'!$B$7:$B$300,0)),IF($D7="","","** ID not found **"))} -> JEWELLERY | F7: {=IFERROR(INDEX('03 Budget'!$D$7:$D$300,MATCH($D7,'03 Budget'!$B$7:$B$300,0)),IF($D7="","","** ID not found **"))} -> Bridal necklace set | G7: panadura gold house | H7: Final Payment | I7: 395000 | K7: 395000 | L7: 46268 | M7: =IF(I7="","",MAX(0,I7-K7)) -> 0 | N7: Card | Q7: Yes | R7: With me | S7: =IF(I7="","",IF(K7>=I7,"Paid",IF(J7="","Not Due",IF(J7<TODAY(),"Overdue",IF(J7<=TODAY()+7,"Due",IF(J7<=TODAY()+30,"Due Soon","Not Due")))))) -> Paid
B8: =IF($D8="","","PY"&TEXT(ROW()-6,"000")) -> PY002 | D8: BG082 | E8: {=IFERROR(INDEX('03 Budget'!$C$7:$C$300,MATCH($D8,'03 Budget'!$B$7:$B$300,0)),IF($D8="","","** ID not found **"))} -> JEWELLERY | F8: {=IFERROR(INDEX('03 Budget'!$D$7:$D$300,MATCH($D8,'03 Budget'!$B$7:$B$300,0)),IF($D8="","","** ID not found **"))} -> Wedding rings (pair) | G8: panadura gold house | H8: Final Payment | I8: 485000 | K8: 485000 | L8: 46268 | M8: =IF(I8="","",MAX(0,I8-K8)) -> 0 | N8: Card | Q8: Yes | R8: With me | S8: =IF(I8="","",IF(K8>=I8,"Paid",IF(J8="","Not Due",IF(J8<TODAY(),"Overdue",IF(J8<=TODAY()+7,"Due",IF(J8<=TODAY()+30,"Due Soon","Not Due")))))) -> Paid
B9: =IF($D9="","","PY"&TEXT(ROW()-6,"000")) -> PY003 | D9: BG083 | E9: {=IFERROR(INDEX('03 Budget'!$C$7:$C$300,MATCH($D9,'03 Budget'!$B$7:$B$300,0)),IF($D9="","","** ID not found **"))} -> JEWELLERY | F9: {=IFERROR(INDEX('03 Budget'!$D$7:$D$300,MATCH($D9,'03 Budget'!$B$7:$B$300,0)),IF($D9="","","** ID not found **"))} -> Bride's brother ring | G9: panadura gold house | H9: Final Payment | I9: 16000 | K9: 16000 | L9: 46268 | M9: =IF(I9="","",MAX(0,I9-K9)) -> 0 | N9: Card | Q9: Yes | R9: With me | S9: =IF(I9="","",IF(K9>=I9,"Paid",IF(J9="","Not Due",IF(J9<TODAY(),"Overdue",IF(J9<=TODAY()+7,"Due",IF(J9<=TODAY()+30,"Due Soon","Not Due")))))) -> Paid
B10: =IF($D10="","","PY"&TEXT(ROW()-6,"000")) | E10: {=IFERROR(INDEX('03 Budget'!$C$7:$C$300,MATCH($D10,'03 Budget'!$B$7:$B$300,0)),IF($D10="","","** ID not found **"))} | F10: {=IFERROR(INDEX('03 Budget'!$D$7:$D$300,MATCH($D10,'03 Budget'!$B$7:$B$300,0)),IF($D10="","","** ID not found **"))} | M10: =IF(I10="","",MAX(0,I10-K10)) | S10: =IF(I10="","",IF(K10>=I10,"Paid",IF(J10="","Not Due",IF(J10<TODAY(),"Overdue",IF(J10<=TODAY()+7,"Due",IF(J10<=TODAY()+30,"Due Soon","Not Due"))))))
B11: =IF($D11="","","PY"&TEXT(ROW()-6,"000")) | E11: {=IFERROR(INDEX('03 Budget'!$C$7:$C$300,MATCH($D11,'03 Budget'!$B$7:$B$300,0)),IF($D11="","","** ID not found **"))} | F11: {=IFERROR(INDEX('03 Budget'!$D$7:$D$300,MATCH($D11,'03 Budget'!$B$7:$B$300,0)),IF($D11="","","** ID not found **"))} | M11: =IF(I11="","",MAX(0,I11-K11)) | S11: =IF(I11="","",IF(K11>=I11,"Paid",IF(J11="","Not Due",IF(J11<TODAY(),"Overdue",IF(J11<=TODAY()+7,"Due",IF(J11<=TODAY()+30,"Due Soon","Not Due"))))))
B12: =IF($D12="","","PY"&TEXT(ROW()-6,"000")) | E12: {=IFERROR(INDEX('03 Budget'!$C$7:$C$300,MATCH($D12,'03 Budget'!$B$7:$B$300,0)),IF($D12="","","** ID not found **"))} | F12: {=IFERROR(INDEX('03 Budget'!$D$7:$D$300,MATCH($D12,'03 Budget'!$B$7:$B$300,0)),IF($D12="","","** ID not found **"))} | M12: =IF(I12="","",MAX(0,I12-K12)) | S12: =IF(I12="","",IF(K12>=I12,"Paid",IF(J12="","Not Due",IF(J12<TODAY(),"Overdue",IF(J12<=TODAY()+7,"Due",IF(J12<=TODAY()+30,"Due Soon","Not Due"))))))
B13: =IF($D13="","","PY"&TEXT(ROW()-6,"000")) | E13: {=IFERROR(INDEX('03 Budget'!$C$7:$C$300,MATCH($D13,'03 Budget'!$B$7:$B$300,0)),IF($D13="","","** ID not found **"))} | F13: {=IFERROR(INDEX('03 Budget'!$D$7:$D$300,MATCH($D13,'03 Budget'!$B$7:$B$300,0)),IF($D13="","","** ID not found **"))} | M13: =IF(I13="","",MAX(0,I13-K13)) | S13: =IF(I13="","",IF(K13>=I13,"Paid",IF(J13="","Not Due",IF(J13<TODAY(),"Overdue",IF(J13<=TODAY()+7,"Due",IF(J13<=TODAY()+30,"Due Soon","Not Due"))))))
B14: =IF($D14="","","PY"&TEXT(ROW()-6,"000")) | E14: {=IFERROR(INDEX('03 Budget'!$C$7:$C$300,MATCH($D14,'03 Budget'!$B$7:$B$300,0)),IF($D14="","","** ID not found **"))} | F14: {=IFERROR(INDEX('03 Budget'!$D$7:$D$300,MATCH($D14,'03 Budget'!$B$7:$B$300,0)),IF($D14="","","** ID not found **"))} | M14: =IF(I14="","",MAX(0,I14-K14)) | S14: =IF(I14="","",IF(K14>=I14,"Paid",IF(J14="","Not Due",IF(J14<TODAY(),"Overdue",IF(J14<=TODAY()+7,"Due",IF(J14<=TODAY()+30,"Due Soon","Not Due"))))))
B15: =IF($D15="","","PY"&TEXT(ROW()-6,"000")) | E15: {=IFERROR(INDEX('03 Budget'!$C$7:$C$300,MATCH($D15,'03 Budget'!$B$7:$B$300,0)),IF($D15="","","** ID not found **"))} | F15: {=IFERROR(INDEX('03 Budget'!$D$7:$D$300,MATCH($D15,'03 Budget'!$B$7:$B$300,0)),IF($D15="","","** ID not found **"))} | M15: =IF(I15="","",MAX(0,I15-K15)) | S15: =IF(I15="","",IF(K15>=I15,"Paid",IF(J15="","Not Due",IF(J15<TODAY(),"Overdue",IF(J15<=TODAY()+7,"Due",IF(J15<=TODAY()+30,"Due Soon","Not Due"))))))
B16: =IF($D16="","","PY"&TEXT(ROW()-6,"000")) | E16: {=IFERROR(INDEX('03 Budget'!$C$7:$C$300,MATCH($D16,'03 Budget'!$B$7:$B$300,0)),IF($D16="","","** ID not found **"))} | F16: {=IFERROR(INDEX('03 Budget'!$D$7:$D$300,MATCH($D16,'03 Budget'!$B$7:$B$300,0)),IF($D16="","","** ID not found **"))} | M16: =IF(I16="","",MAX(0,I16-K16)) | S16: =IF(I16="","",IF(K16>=I16,"Paid",IF(J16="","Not Due",IF(J16<TODAY(),"Overdue",IF(J16<=TODAY()+7,"Due",IF(J16<=TODAY()+30,"Due Soon","Not Due"))))))
B17: =IF($D17="","","PY"&TEXT(ROW()-6,"000")) | E17: {=IFERROR(INDEX('03 Budget'!$C$7:$C$300,MATCH($D17,'03 Budget'!$B$7:$B$300,0)),IF($D17="","","** ID not found **"))} | F17: {=IFERROR(INDEX('03 Budget'!$D$7:$D$300,MATCH($D17,'03 Budget'!$B$7:$B$300,0)),IF($D17="","","** ID not found **"))} | M17: =IF(I17="","",MAX(0,I17-K17)) | S17: =IF(I17="","",IF(K17>=I17,"Paid",IF(J17="","Not Due",IF(J17<TODAY(),"Overdue",IF(J17<=TODAY()+7,"Due",IF(J17<=TODAY()+30,"Due Soon","Not Due"))))))
B18: =IF($D18="","","PY"&TEXT(ROW()-6,"000")) | E18: {=IFERROR(INDEX('03 Budget'!$C$7:$C$300,MATCH($D18,'03 Budget'!$B$7:$B$300,0)),IF($D18="","","** ID not found **"))} | F18: {=IFERROR(INDEX('03 Budget'!$D$7:$D$300,MATCH($D18,'03 Budget'!$B$7:$B$300,0)),IF($D18="","","** ID not found **"))} | M18: =IF(I18="","",MAX(0,I18-K18)) | S18: =IF(I18="","",IF(K18>=I18,"Paid",IF(J18="","Not Due",IF(J18<TODAY(),"Overdue",IF(J18<=TODAY()+7,"Due",IF(J18<=TODAY()+30,"Due Soon","Not Due"))))))
B19: =IF($D19="","","PY"&TEXT(ROW()-6,"000")) | E19: {=IFERROR(INDEX('03 Budget'!$C$7:$C$300,MATCH($D19,'03 Budget'!$B$7:$B$300,0)),IF($D19="","","** ID not found **"))} | F19: {=IFERROR(INDEX('03 Budget'!$D$7:$D$300,MATCH($D19,'03 Budget'!$B$7:$B$300,0)),IF($D19="","","** ID not found **"))} | M19: =IF(I19="","",MAX(0,I19-K19)) | S19: =IF(I19="","",IF(K19>=I19,"Paid",IF(J19="","Not Due",IF(J19<TODAY(),"Overdue",IF(J19<=TODAY()+7,"Due",IF(J19<=TODAY()+30,"Due Soon","Not Due"))))))
B20: =IF($D20="","","PY"&TEXT(ROW()-6,"000")) | E20: {=IFERROR(INDEX('03 Budget'!$C$7:$C$300,MATCH($D20,'03 Budget'!$B$7:$B$300,0)),IF($D20="","","** ID not found **"))} | F20: {=IFERROR(INDEX('03 Budget'!$D$7:$D$300,MATCH($D20,'03 Budget'!$B$7:$B$300,0)),IF($D20="","","** ID not found **"))} | M20: =IF(I20="","",MAX(0,I20-K20)) | S20: =IF(I20="","",IF(K20>=I20,"Paid",IF(J20="","Not Due",IF(J20<TODAY(),"Overdue",IF(J20<=TODAY()+7,"Due",IF(J20<=TODAY()+30,"Due Soon","Not Due"))))))
B21: =IF($D21="","","PY"&TEXT(ROW()-6,"000")) | E21: {=IFERROR(INDEX('03 Budget'!$C$7:$C$300,MATCH($D21,'03 Budget'!$B$7:$B$300,0)),IF($D21="","","** ID not found **"))} | F21: {=IFERROR(INDEX('03 Budget'!$D$7:$D$300,MATCH($D21,'03 Budget'!$B$7:$B$300,0)),IF($D21="","","** ID not found **"))} | M21: =IF(I21="","",MAX(0,I21-K21)) | S21: =IF(I21="","",IF(K21>=I21,"Paid",IF(J21="","Not Due",IF(J21<TODAY(),"Overdue",IF(J21<=TODAY()+7,"Due",IF(J21<=TODAY()+30,"Due Soon","Not Due"))))))
... B400: =IF($D400="","","PY"&TEXT(ROW()-6,"000")) | E400: {=IFERROR(INDEX('03 Budget'!$C$7:$C$300,MATCH($D400,'03 Budget'!$B$7:$B$300,0)),IF($D400="","","** ID not found **"))} | F400: {=IFERROR(INDEX('03 Budget'!$D$7:$D$300,MATCH($D400,'03 Budget'!$B$7:$B$300,0)),IF($D400="","","** ID not found **"))} | M400: =IF(I400="","",MAX(0,I400-K400)) | S400: =IF(I400="","",IF(K400>=I400,"Paid",IF(J400="","Not Due",IF(J400<TODAY(),"Overdue",IF(J400<=TODAY()+7,"Due",IF(J400<=TODAY()+30,"Due Soon","Not Due"))))))

Sheet 05 Vendors
B2: VENDOR MASTER
B3: Enter every supplier ONCE here. Compare your shortlist and work through the questions on 05a Vendor Compare first, then record the winner here - the rest of the workbook reads from this sheet.
B6: ID | C6: Category | D6: Vendor name | E6: Contact person | F6: Phone | G6: WhatsApp | H6: Email | I6: Address | J6: Package / inclusions | K6: Quoted | L6: Negotiated | M6: Deposit paid | N6: Total paid | O6: Balance owing | P6: Overdue payments | Q6: Contract signed? | R6: Contract kept where | S6: Booking status | T6: Arrival time | U6: Setup done by | V6: Finish time | W6: Overtime rate | X6: Key deliverables | Y6: Final confirmation date | Z6: Rating /5 | AA6: Notes
B7: V001 | C7: Venue / Hotel | D7: [Hotel name] | M7: =SUMIFS('04 Payments'!$K$7:$K$400,'04 Payments'!$G$7:$G$400,$D7,'04 Payments'!$H$7:$H$400,"Booking Deposit") -> 0 | N7: =SUMIFS('04 Payments'!$K$7:$K$400,'04 Payments'!$G$7:$G$400,$D7) -> 0 | O7: =IF(L7>0,L7-N7,IF(K7>0,K7-N7,0)) -> 0 | P7: =COUNTIFS('04 Payments'!$G$7:$G$400,$D7,'04 Payments'!$S$7:$S$400,"Overdue") -> 0 | S7: Confirmed
B8: V002 | C8: Caterer | D8: [In-house catering] | M8: =SUMIFS('04 Payments'!$K$7:$K$400,'04 Payments'!$G$7:$G$400,$D8,'04 Payments'!$H$7:$H$400,"Booking Deposit") -> 0 | N8: =SUMIFS('04 Payments'!$K$7:$K$400,'04 Payments'!$G$7:$G$400,$D8) -> 0 | O8: =IF(L8>0,L8-N8,IF(K8>0,K8-N8,0)) -> 0 | P8: =COUNTIFS('04 Payments'!$G$7:$G$400,$D8,'04 Payments'!$S$7:$S$400,"Overdue") -> 0 | S8: Confirmed
B9: V003 | C9: Photographer | D9: [Studio name] | M9: =SUMIFS('04 Payments'!$K$7:$K$400,'04 Payments'!$G$7:$G$400,$D9,'04 Payments'!$H$7:$H$400,"Booking Deposit") -> 0 | N9: =SUMIFS('04 Payments'!$K$7:$K$400,'04 Payments'!$G$7:$G$400,$D9) -> 0 | O9: =IF(L9>0,L9-N9,IF(K9>0,K9-N9,0)) -> 0 | P9: =COUNTIFS('04 Payments'!$G$7:$G$400,$D9,'04 Payments'!$S$7:$S$400,"Overdue") -> 0 | S9: Shortlisted
B10: V004 | C10: Videographer | D10: [Studio name] | M10: =SUMIFS('04 Payments'!$K$7:$K$400,'04 Payments'!$G$7:$G$400,$D10,'04 Payments'!$H$7:$H$400,"Booking Deposit") -> 0 | N10: =SUMIFS('04 Payments'!$K$7:$K$400,'04 Payments'!$G$7:$G$400,$D10) -> 0 | O10: =IF(L10>0,L10-N10,IF(K10>0,K10-N10,0)) -> 0 | P10: =COUNTIFS('04 Payments'!$G$7:$G$400,$D10,'04 Payments'!$S$7:$S$400,"Overdue") -> 0 | S10: Shortlisted
B11: V005 | C11: Makeup Artist | D11: [Bridal dresser] | M11: =SUMIFS('04 Payments'!$K$7:$K$400,'04 Payments'!$G$7:$G$400,$D11,'04 Payments'!$H$7:$H$400,"Booking Deposit") -> 0 | N11: =SUMIFS('04 Payments'!$K$7:$K$400,'04 Payments'!$G$7:$G$400,$D11) -> 0 | O11: =IF(L11>0,L11-N11,IF(K11>0,K11-N11,0)) -> 0 | P11: =COUNTIFS('04 Payments'!$G$7:$G$400,$D11,'04 Payments'!$S$7:$S$400,"Overdue") -> 0 | S11: Shortlisted
B12: V006 | C12: Saree / Dress Designer | D12: [Designer] | M12: =SUMIFS('04 Payments'!$K$7:$K$400,'04 Payments'!$G$7:$G$400,$D12,'04 Payments'!$H$7:$H$400,"Booking Deposit") -> 0 | N12: =SUMIFS('04 Payments'!$K$7:$K$400,'04 Payments'!$G$7:$G$400,$D12) -> 0 | O12: =IF(L12>0,L12-N12,IF(K12>0,K12-N12,0)) -> 0 | P12: =COUNTIFS('04 Payments'!$G$7:$G$400,$D12,'04 Payments'!$S$7:$S$400,"Overdue") -> 0 | S12: Researching
B13: V007 | C13: Jewellery | D13: Panadura Gold House | E13: Ismi | F13: 705116588 | G13: 765816588 | H13: pghjewel@gmail.com | I13: panadura | K13: 900000 | L13: 896000 | M13: =SUMIFS('04 Payments'!$K$7:$K$400,'04 Payments'!$G$7:$G$400,$D13,'04 Payments'!$H$7:$H$400,"Booking Deposit") -> 0 | N13: 896000 | O13: =IF(L13>0,L13-N13,IF(K13>0,K13-N13,0)) -> 0 | P13: =COUNTIFS('04 Payments'!$G$7:$G$400,$D13,'04 Payments'!$S$7:$S$400,"Overdue") -> 0 | Q13: Yes | R13: with me | S13: Completed | T13: 46295 | Y13: 46295 | Z13: 5
B14: V008 | C14: Decorator | D14: [Decorator] | M14: =SUMIFS('04 Payments'!$K$7:$K$400,'04 Payments'!$G$7:$G$400,$D14,'04 Payments'!$H$7:$H$400,"Booking Deposit") -> 0 | N14: =SUMIFS('04 Payments'!$K$7:$K$400,'04 Payments'!$G$7:$G$400,$D14) -> 0 | O14: =IF(L14>0,L14-N14,IF(K14>0,K14-N14,0)) -> 0 | P14: =COUNTIFS('04 Payments'!$G$7:$G$400,$D14,'04 Payments'!$S$7:$S$400,"Overdue") -> 0 | S14: Researching
B15: V009 | C15: Cake | D15: [Bakery] | M15: =SUMIFS('04 Payments'!$K$7:$K$400,'04 Payments'!$G$7:$G$400,$D15,'04 Payments'!$H$7:$H$400,"Booking Deposit") -> 0 | N15: =SUMIFS('04 Payments'!$K$7:$K$400,'04 Payments'!$G$7:$G$400,$D15) -> 0 | O15: =IF(L15>0,L15-N15,IF(K15>0,K15-N15,0)) -> 0 | P15: =COUNTIFS('04 Payments'!$G$7:$G$400,$D15,'04 Payments'!$S$7:$S$400,"Overdue") -> 0 | S15: Researching
B16: V010 | C16: Kandyan Dancers | D16: [Dance troupe] | M16: =SUMIFS('04 Payments'!$K$7:$K$400,'04 Payments'!$G$7:$G$400,$D16,'04 Payments'!$H$7:$H$400,"Booking Deposit") -> 0 | N16: =SUMIFS('04 Payments'!$K$7:$K$400,'04 Payments'!$G$7:$G$400,$D16) -> 0 | O16: =IF(L16>0,L16-N16,IF(K16>0,K16-N16,0)) -> 0 | P16: =COUNTIFS('04 Payments'!$G$7:$G$400,$D16,'04 Payments'!$S$7:$S$400,"Overdue") -> 0 | S16: Researching
B17: V011 | C17: Drummers | D17: [Hewisi group] | M17: =SUMIFS('04 Payments'!$K$7:$K$400,'04 Payments'!$G$7:$G$400,$D17,'04 Payments'!$H$7:$H$400,"Booking Deposit") -> 0 | N17: =SUMIFS('04 Payments'!$K$7:$K$400,'04 Payments'!$G$7:$G$400,$D17) -> 0 | O17: =IF(L17>0,L17-N17,IF(K17>0,K17-N17,0)) -> 0 | P17: =COUNTIFS('04 Payments'!$G$7:$G$400,$D17,'04 Payments'!$S$7:$S$400,"Overdue") -> 0 | S17: Researching
B18: V012 | C18: Poruwa Officiant | D18: [Ashtaka chanter] | M18: =SUMIFS('04 Payments'!$K$7:$K$400,'04 Payments'!$G$7:$G$400,$D18,'04 Payments'!$H$7:$H$400,"Booking Deposit") -> 0 | N18: =SUMIFS('04 Payments'!$K$7:$K$400,'04 Payments'!$G$7:$G$400,$D18) -> 0 | O18: =IF(L18>0,L18-N18,IF(K18>0,K18-N18,0)) -> 0 | P18: =COUNTIFS('04 Payments'!$G$7:$G$400,$D18,'04 Payments'!$S$7:$S$400,"Overdue") -> 0 | S18: Researching
B19: V013 | C19: MC | D19: [MC name] | M19: =SUMIFS('04 Payments'!$K$7:$K$400,'04 Payments'!$G$7:$G$400,$D19,'04 Payments'!$H$7:$H$400,"Booking Deposit") -> 0 | N19: =SUMIFS('04 Payments'!$K$7:$K$400,'04 Payments'!$G$7:$G$400,$D19) -> 0 | O19: =IF(L19>0,L19-N19,IF(K19>0,K19-N19,0)) -> 0 | P19: =COUNTIFS('04 Payments'!$G$7:$G$400,$D19,'04 Payments'!$S$7:$S$400,"Overdue") -> 0 | S19: Researching
B20: V014 | C20: DJ | D20: [DJ name] | M20: =SUMIFS('04 Payments'!$K$7:$K$400,'04 Payments'!$G$7:$G$400,$D20,'04 Payments'!$H$7:$H$400,"Booking Deposit") -> 0 | N20: =SUMIFS('04 Payments'!$K$7:$K$400,'04 Payments'!$G$7:$G$400,$D20) -> 0 | O20: =IF(L20>0,L20-N20,IF(K20>0,K20-N20,0)) -> 0 | P20: =COUNTIFS('04 Payments'!$G$7:$G$400,$D20,'04 Payments'!$S$7:$S$400,"Overdue") -> 0 | S20: Researching
B21: V015 | C21: Transport | D21: [Bridal car hire] | M21: =SUMIFS('04 Payments'!$K$7:$K$400,'04 Payments'!$G$7:$G$400,$D21,'04 Payments'!$H$7:$H$400,"Booking Deposit") -> 0 | N21: =SUMIFS('04 Payments'!$K$7:$K$400,'04 Payments'!$G$7:$G$400,$D21) -> 0 | O21: =IF(L21>0,L21-N21,IF(K21>0,K21-N21,0)) -> 0 | P21: =COUNTIFS('04 Payments'!$G$7:$G$400,$D21,'04 Payments'!$S$7:$S$400,"Overdue") -> 0 | S21: Researching
B22: V016 | C22: Printing / Invitations | D22: [Printer] | M22: =SUMIFS('04 Payments'!$K$7:$K$400,'04 Payments'!$G$7:$G$400,$D22,'04 Payments'!$H$7:$H$400,"Booking Deposit") -> 0 | N22: =SUMIFS('04 Payments'!$K$7:$K$400,'04 Payments'!$G$7:$G$400,$D22) -> 0 | O22: =IF(L22>0,L22-N22,IF(K22>0,K22-N22,0)) -> 0 | P22: =COUNTIFS('04 Payments'!$G$7:$G$400,$D22,'04 Payments'!$S$7:$S$400,"Overdue") -> 0 | S22: Researching
B23: V017 | C23: Sound & AV | D23: [AV supplier] | M23: =SUMIFS('04 Payments'!$K$7:$K$400,'04 Payments'!$G$7:$G$400,$D23,'04 Payments'!$H$7:$H$400,"Booking Deposit") -> 0 | N23: =SUMIFS('04 Payments'!$K$7:$K$400,'04 Payments'!$G$7:$G$400,$D23) -> 0 | O23: =IF(L23>0,L23-N23,IF(K23>0,K23-N23,0)) -> 0 | P23: =COUNTIFS('04 Payments'!$G$7:$G$400,$D23,'04 Payments'!$S$7:$S$400,"Overdue") -> 0 | S23: Researching
B24: V018 | C24: Coordinator | D24: [Coordinator] | M24: =SUMIFS('04 Payments'!$K$7:$K$400,'04 Payments'!$G$7:$G$400,$D24,'04 Payments'!$H$7:$H$400,"Booking Deposit") -> 0 | N24: =SUMIFS('04 Payments'!$K$7:$K$400,'04 Payments'!$G$7:$G$400,$D24) -> 0 | O24: =IF(L24>0,L24-N24,IF(K24>0,K24-N24,0)) -> 0 | P24: =COUNTIFS('04 Payments'!$G$7:$G$400,$D24,'04 Payments'!$S$7:$S$400,"Overdue") -> 0 | S24: Researching
M25: =SUMIFS('04 Payments'!$K$7:$K$400,'04 Payments'!$G$7:$G$400,$D25,'04 Payments'!$H$7:$H$400,"Booking Deposit") -> 0 | N25: =SUMIFS('04 Payments'!$K$7:$K$400,'04 Payments'!$G$7:$G$400,$D25) -> 0 | O25: =IF(L25>0,L25-N25,IF(K25>0,K25-N25,0)) -> 0 | P25: =COUNTIFS('04 Payments'!$G$7:$G$400,$D25,'04 Payments'!$S$7:$S$400,"Overdue") -> 0
M26: =SUMIFS('04 Payments'!$K$7:$K$400,'04 Payments'!$G$7:$G$400,$D26,'04 Payments'!$H$7:$H$400,"Booking Deposit") -> 0 | N26: =SUMIFS('04 Payments'!$K$7:$K$400,'04 Payments'!$G$7:$G$400,$D26) -> 0 | O26: =IF(L26>0,L26-N26,IF(K26>0,K26-N26,0)) -> 0 | P26: =COUNTIFS('04 Payments'!$G$7:$G$400,$D26,'04 Payments'!$S$7:$S$400,"Overdue") -> 0
M27: =SUMIFS('04 Payments'!$K$7:$K$400,'04 Payments'!$G$7:$G$400,$D27,'04 Payments'!$H$7:$H$400,"Booking Deposit") -> 0 | N27: =SUMIFS('04 Payments'!$K$7:$K$400,'04 Payments'!$G$7:$G$400,$D27) -> 0 | O27: =IF(L27>0,L27-N27,IF(K27>0,K27-N27,0)) -> 0 | P27: =COUNTIFS('04 Payments'!$G$7:$G$400,$D27,'04 Payments'!$S$7:$S$400,"Overdue") -> 0
M28: =SUMIFS('04 Payments'!$K$7:$K$400,'04 Payments'!$G$7:$G$400,$D28,'04 Payments'!$H$7:$H$400,"Booking Deposit") -> 0 | N28: =SUMIFS('04 Payments'!$K$7:$K$400,'04 Payments'!$G$7:$G$400,$D28) -> 0 | O28: =IF(L28>0,L28-N28,IF(K28>0,K28-N28,0)) -> 0 | P28: =COUNTIFS('04 Payments'!$G$7:$G$400,$D28,'04 Payments'!$S$7:$S$400,"Overdue") -> 0
M29: =SUMIFS('04 Payments'!$K$7:$K$400,'04 Payments'!$G$7:$G$400,$D29,'04 Payments'!$H$7:$H$400,"Booking Deposit") -> 0 | N29: =SUMIFS('04 Payments'!$K$7:$K$400,'04 Payments'!$G$7:$G$400,$D29) -> 0 | O29: =IF(L29>0,L29-N29,IF(K29>0,K29-N29,0)) -> 0 | P29: =COUNTIFS('04 Payments'!$G$7:$G$400,$D29,'04 Payments'!$S$7:$S$400,"Overdue") -> 0
M30: =SUMIFS('04 Payments'!$K$7:$K$400,'04 Payments'!$G$7:$G$400,$D30,'04 Payments'!$H$7:$H$400,"Booking Deposit") -> 0 | N30: =SUMIFS('04 Payments'!$K$7:$K$400,'04 Payments'!$G$7:$G$400,$D30) -> 0 | O30: =IF(L30>0,L30-N30,IF(K30>0,K30-N30,0)) -> 0 | P30: =COUNTIFS('04 Payments'!$G$7:$G$400,$D30,'04 Payments'!$S$7:$S$400,"Overdue") -> 0
M31: =SUMIFS('04 Payments'!$K$7:$K$400,'04 Payments'!$G$7:$G$400,$D31,'04 Payments'!$H$7:$H$400,"Booking Deposit") -> 0 | N31: =SUMIFS('04 Payments'!$K$7:$K$400,'04 Payments'!$G$7:$G$400,$D31) -> 0 | O31: =IF(L31>0,L31-N31,IF(K31>0,K31-N31,0)) -> 0 | P31: =COUNTIFS('04 Payments'!$G$7:$G$400,$D31,'04 Payments'!$S$7:$S$400,"Overdue") -> 0
M32: =SUMIFS('04 Payments'!$K$7:$K$400,'04 Payments'!$G$7:$G$400,$D32,'04 Payments'!$H$7:$H$400,"Booking Deposit") -> 0 | N32: =SUMIFS('04 Payments'!$K$7:$K$400,'04 Payments'!$G$7:$G$400,$D32) -> 0 | O32: =IF(L32>0,L32-N32,IF(K32>0,K32-N32,0)) -> 0 | P32: =COUNTIFS('04 Payments'!$G$7:$G$400,$D32,'04 Payments'!$S$7:$S$400,"Overdue") -> 0
M33: =SUMIFS('04 Payments'!$K$7:$K$400,'04 Payments'!$G$7:$G$400,$D33,'04 Payments'!$H$7:$H$400,"Booking Deposit") -> 0 | N33: =SUMIFS('04 Payments'!$K$7:$K$400,'04 Payments'!$G$7:$G$400,$D33) -> 0 | O33: =IF(L33>0,L33-N33,IF(K33>0,K33-N33,0)) -> 0 | P33: =COUNTIFS('04 Payments'!$G$7:$G$400,$D33,'04 Payments'!$S$7:$S$400,"Overdue") -> 0
M34: =SUMIFS('04 Payments'!$K$7:$K$400,'04 Payments'!$G$7:$G$400,$D34,'04 Payments'!$H$7:$H$400,"Booking Deposit") -> 0 | N34: =SUMIFS('04 Payments'!$K$7:$K$400,'04 Payments'!$G$7:$G$400,$D34) -> 0 | O34: =IF(L34>0,L34-N34,IF(K34>0,K34-N34,0)) -> 0 | P34: =COUNTIFS('04 Payments'!$G$7:$G$400,$D34,'04 Payments'!$S$7:$S$400,"Overdue") -> 0
M35: =SUMIFS('04 Payments'!$K$7:$K$400,'04 Payments'!$G$7:$G$400,$D35,'04 Payments'!$H$7:$H$400,"Booking Deposit") -> 0 | N35: =SUMIFS('04 Payments'!$K$7:$K$400,'04 Payments'!$G$7:$G$400,$D35) -> 0 | O35: =IF(L35>0,L35-N35,IF(K35>0,K35-N35,0)) -> 0 | P35: =COUNTIFS('04 Payments'!$G$7:$G$400,$D35,'04 Payments'!$S$7:$S$400,"Overdue") -> 0
M36: =SUMIFS('04 Payments'!$K$7:$K$400,'04 Payments'!$G$7:$G$400,$D36,'04 Payments'!$H$7:$H$400,"Booking Deposit") -> 0 | N36: =SUMIFS('04 Payments'!$K$7:$K$400,'04 Payments'!$G$7:$G$400,$D36) -> 0 | O36: =IF(L36>0,L36-N36,IF(K36>0,K36-N36,0)) -> 0 | P36: =COUNTIFS('04 Payments'!$G$7:$G$400,$D36,'04 Payments'!$S$7:$S$400,"Overdue") -> 0
... M200: =SUMIFS('04 Payments'!$K$7:$K$400,'04 Payments'!$G$7:$G$400,$D200,'04 Payments'!$H$7:$H$400,"Booking Deposit") -> 0 | N200: =SUMIFS('04 Payments'!$K$7:$K$400,'04 Payments'!$G$7:$G$400,$D200) -> 0 | O200: =IF(L200>0,L200-N200,IF(K200>0,K200-N200,0)) -> 0 | P200: =COUNTIFS('04 Payments'!$G$7:$G$400,$D200,'04 Payments'!$S$7:$S$400,"Overdue") -> 0

Sheet 05a Vendor Compare
B2: VENDOR COMPARISON & QUESTIONS TO ASK
B3: Shortlist up to three options per vendor type, compare them side by side, and work through the questions before you commit. The DECISION row at the end of each section is what you then record in 05 Vendors.
B5: JUMP TO A SECTION - and see every decision at a glance
B6: # | C6: Row | D6: Vendor type | E6: Options entered | F6: DECISION | G6: Chosen vendor | H6: Agreed price | I6: In 05 Vendors?
B7: 1 | C7: 25 | D7: VENUE / HOTEL | E7: =COUNTA(F27:H27) -> 0 | F7: =$F$65 -> Not decided | G7: =$G$65 | H7: =$H$65 -> 0 | I7: =$I$65 -> -
B8: 2 | C8: 68 | D8: CATERER (only if separate from the hotel) | E8: =COUNTA(F70:H70) -> 0 | F8: =$F$97 -> Not decided | G8: =$G$97 | H8: =$H$97 -> 0 | I8: =$I$97 -> -
B9: 3 | C9: 100 | D9: PHOTOGRAPHER | E9: =COUNTA(F102:H102) -> 0 | F9: =$F$133 -> Not decided | G9: =$G$133 | H9: =$H$133 -> 0 | I9: =$I$133 -> -
B10: 4 | C10: 136 | D10: VIDEOGRAPHER | E10: =COUNTA(F138:H138) -> 0 | F10: =$F$165 -> Not decided | G10: =$G$165 | H10: =$H$165 -> 0 | I10: =$I$165 -> -
B11: 5 | C11: 168 | D11: DECORATOR / FLORIST | E11: =COUNTA(F170:H170) -> 0 | F11: =$F$199 -> Not decided | G11: =$G$199 | H11: =$H$199 -> 0 | I11: =$I$199 -> -
B12: 6 | C12: 202 | D12: BRIDAL DRESSER (hair & makeup) | E12: =COUNTA(F204:H204) -> 0 | F12: =$F$230 -> Not decided | G12: =$G$230 | H12: =$H$230 -> 0 | I12: =$I$230 -> -
B13: 7 | C13: 233 | D13: SAREE / DRESS DESIGNER | E13: =COUNTA(F235:H235) -> 0 | F13: =$F$260 -> Not decided | G13: =$G$260 | H13: =$H$260 -> 0 | I13: =$I$260 -> -
B14: 8 | C14: 263 | D14: JEWELLERY | E14: =COUNTA(F265:H265) -> 1 | F14: =$F$288 -> Option A | G14: =$G$288 -> Panadura Gold house | H14: =$H$288 | I14: =$I$288 -> Yes
B15: 9 | C15: 291 | D15: CAKE | E15: =COUNTA(F293:H293) -> 0 | F15: =$F$316 -> Not decided | G15: =$G$316 | H15: =$H$316 -> 0 | I15: =$I$316 -> -
B16: 10 | C16: 319 | D16: KANDYAN DANCERS & DRUMMERS | E16: =COUNTA(F321:H321) -> 0 | F16: =$F$343 -> Not decided | G16: =$G$343 | H16: =$H$343 -> 0 | I16: =$I$343 -> -
B17: 11 | C17: 346 | D17: PORUWA OFFICIANT (Ashtaka chanter) | E17: =COUNTA(F348:H348) -> 0 | F17: =$F$369 -> Not decided | G17: =$G$369 | H17: =$H$369 -> 0 | I17: =$I$369 -> -
B18: 12 | C18: 372 | D18: MC / COMPERE | E18: =COUNTA(F374:H374) -> 0 | F18: =$F$394 -> Not decided | G18: =$G$394 | H18: =$H$394 -> 0 | I18: =$I$394 -> -
B19: 13 | C19: 397 | D19: DJ / BAND | E19: =COUNTA(F399:H399) -> 0 | F19: =$F$422 -> Not decided | G19: =$G$422 | H19: =$H$422 -> 0 | I19: =$I$422 -> -
B20: 14 | C20: 425 | D20: TRANSPORT | E20: =COUNTA(F427:H427) -> 0 | F20: =$F$450 -> Not decided | G20: =$G$450 | H20: =$H$450 -> 0 | I20: =$I$450 -> -
B21: 15 | C21: 453 | D21: PRINTING / INVITATIONS | E21: =COUNTA(F455:H455) -> 0 | F21: =$F$477 -> Not decided | G21: =$G$477 | H21: =$H$477 -> 0 | I21: =$I$477 -> -
B22: 16 | C22: 480 | D22: SOUND, AV & LIGHTING | E22: =COUNTA(F482:H482) -> 0 | F22: =$F$505 -> Not decided | G22: =$G$505 | H22: =$H$505 -> 0 | I22: =$I$505 -> -
B25: 01 · VENUE / HOTEL | I25: back to index: row 5
B26: # | C26: Group | D26: What to ask / compare | E26: Why it matters - what to watch for | F26: OPTION A | G26: OPTION B | H26: OPTION C | I26: Your notes
D27: Vendor / company name
D28: Contact person
D29: Phone / WhatsApp
D30: Package or option quoted
D31: Total quoted (LKR)
D32: After negotiation (LKR)
D33: Deposit required (LKR)
D34: Met them / site visit done?
D35: Your rating out of 5
B36: QUESTIONS TO CONFIRM BEFORE YOU BOOK
B37: 1 | C37: MONEY | D37: Package rate per head for adults - and exactly what does it cover? | E37: The headline number is meaningless until you know what is inside it.
B38: 2 | C38: MONEY | D38: Minimum guaranteed guests you must pay for, even if fewer come | E38: You pay this whether they turn up or not. It sets your real floor price.
B39: 3 | C39: MONEY | D39: Rate for children, and up to what age is a child a child? | E39: Some hotels charge full price from age 6, others from 12.
B40: 4 | C40: MONEY | D40: Are service charge and taxes (VAT / SSCL / TDL) included or added on top? | E40: Adding these later can lift a quote by 25-30%.
B41: 5 | C41: MONEY | D41: Charge per extra hour beyond the agreed finish time | E41: Sri Lankan receptions run late. Agree this before, not at midnight.
B42: 6 | C42: MONEY | D42: Corkage per bottle - hard liquor, beer and wine separately | E42: Corkage can cost more than the alcohol itself.
B43: 7 | C43: MONEY | D43: Is there a minimum bar spend? | E43: A minimum can force you to buy drink you do not need.
B44: 8 | C44: MONEY | D44: Do vendors and crew count in the head count, and what is the crew meal rate? | E44: 20 crew at full guest rate is a large hidden line.
B45: 9 | C45: INCLUDED | D45: Which halls / areas, and the exact seated capacity WITH a Poruwa and dance floor | E45: Stated capacity is usually theatre style, not a seated wedding.
B46: 10 | C46: INCLUDED | D46: Is the bridal suite included? Check-in time on the day and check-out next day | E46: You need the room from mid-morning for dressing, not from 2pm.
B47: 11 | C47: INCLUDED | D47: Is a getting-ready room for the groom included or charged? | E47: Often forgotten and then charged on the day.
B48: 12 | C48: INCLUDED | D48: How many complimentary rooms, and the group rate for extra rooms? | E48: Matters if you have outstation or overseas family.
... B63: 27 | C63: RISK | D63: Is the quotation itemised and in writing, with the taxes shown separately? | E63: A one-line quote is where disputes start.
D65: DECISION - which option are you going with? | E65: Record the chosen vendor on 05 Vendors, then the rest of the workbook picks them up. | F65: Not decided | G65: =IF($F65="Option A",$F27,IF($F65="Option B",$G27,IF($F65="Option C",$H27,""))) | H65: =IF($F65="Option A",IF($F32>0,$F32,$F31),IF($F65="Option B",IF($G32>0,$G32,$G31),IF($F65="Option C",IF($H32>0,$H32,$H31),0))) -> 0 | I65: =IF($G65="","-",IF(COUNTIF('05 Vendors'!$D$7:$D$200,$G65)>0,"Yes","NOT YET")) -> -
B68: 02 · CATERER (only if separate from the hotel) | I68: back to index: row 5
B69: # | C69: Group | D69: What to ask / compare | E69: Why it matters - what to watch for | F69: OPTION A | G69: OPTION B | H69: OPTION C | I69: Your notes
D70: Vendor / company name
D71: Contact person
D72: Phone / WhatsApp
D73: Package or option quoted
D74: Total quoted (LKR)
D75: After negotiation (LKR)
D76: Deposit required (LKR)
D77: Met them / site visit done?
D78: Your rating out of 5
B79: QUESTIONS TO CONFIRM BEFORE YOU BOOK
B80: 1 | C80: MONEY | D80: Rate per head, and the exact menu at that rate | E80: Menus get quietly downgraded between quote and wedding.
B81: 2 | C81: MONEY | D81: Minimum number of guests | E81: Sets your floor price.
B82: 3 | C82: MONEY | D82: Crew and vendor meal rate | E82: Photographers, dancers and drivers all need feeding.
B83: 4 | C83: MONEY | D83: Transport charge to the venue | E83: Often excluded from the per-head rate.
B84: 5 | C84: INCLUDED | D84: Does it include rice, at least three vegetarian mains, dhal, mallum and papadam? | E84: The staples are what guests actually judge.
B85: 6 | C85: INCLUDED | D85: Is a live station (hoppers or kottu) included or extra? | E85: Popular, and almost always an extra.
B86: 7 | C86: INCLUDED | D86: How many desserts, and is watalappan included? | E86: A Sri Lankan wedding without watalappan gets noticed.
B87: 8 | C87: INCLUDED | D87: Do they supply crockery, cutlery, linen and chafing dishes? | E87: If not, you are hiring them separately.
B88: 9 | C88: INCLUDED | D88: How many service staff per 100 guests? | E88: Under-staffing shows as long buffet queues.
B89: 10 | C89: INCLUDED | D89: Are welcome drinks and short eats included? | E89: Guests arrive up to an hour before the ceremony.
B90: 11 | C90: INCLUDED | D90: Is a tasting included - when, and for how many people? | E90: Taste before you pay the balance, not after.
B91: 12 | C91: LOGISTICS | D91: What time do they arrive, and how long do they need to set up? | E91: Feeds straight into 21 Vendor Schedule.
... B95: 16 | C95: RISK | D95: Deposit, payment schedule and cancellation terms | E95: Get it in writing.
D97: DECISION - which option are you going with? | E97: Record the chosen vendor on 05 Vendors, then the rest of the workbook picks them up. | F97: Not decided | G97: =IF($F97="Option A",$F70,IF($F97="Option B",$G70,IF($F97="Option C",$H70,""))) | H97: =IF($F97="Option A",IF($F75>0,$F75,$F74),IF($F97="Option B",IF($G75>0,$G75,$G74),IF($F97="Option C",IF($H75>0,$H75,$H74),0))) -> 0 | I97: =IF($G97="","-",IF(COUNTIF('05 Vendors'!$D$7:$D$200,$G97)>0,"Yes","NOT YET")) -> -
B100: 03 · PHOTOGRAPHER | I100: back to index: row 5
B101: # | C101: Group | D101: What to ask / compare | E101: Why it matters - what to watch for | F101: OPTION A | G101: OPTION B | H101: OPTION C | I101: Your notes
D102: Vendor / company name
D103: Contact person
D104: Phone / WhatsApp
D105: Package or option quoted
D106: Total quoted (LKR)
D107: After negotiation (LKR)
D108: Deposit required (LKR)
D109: Met them / site visit done?
D110: Your rating out of 5
B111: QUESTIONS TO CONFIRM BEFORE YOU BOOK
B112: 1 | C112: MONEY | D112: Total price and exactly how many hours of coverage it buys | E112: Coverage hours are the thing people forget to check.
B113: 2 | C113: MONEY | D113: Charge per extra hour | E113: You will almost certainly run over.
B114: 3 | C114: MONEY | D114: Is the pre-shoot included? Any travel charge for the location? | E114: Out-of-Colombo locations attract travel and stay costs.
B115: 4 | C115: MONEY | D115: Cost of parent albums and enlargements | E115: Both sets of parents will want one.
B116: 5 | C116: MONEY | D116: Cost to receive the raw / unedited files | E116: Some studios never release them. Ask now.
B117: 6 | C117: INCLUDED | D117: How many photographers and assistants are included on the day? | E117: One person cannot cover a Poruwa and a groom's entrance.
B118: 7 | C118: INCLUDED | D118: How many edited images do we receive, and how are they delivered? | E118: 'Selected images' can mean 200 or 2,000.
B119: 8 | C119: INCLUDED | D119: Album specification - size, number of spreads, cover, print lab | E119: This is the thing you keep for 40 years.
B120: 9 | C120: INCLUDED | D120: Is a same-day edit offered, and what does the venue need to provide? | E120: Needs a screen and a slot in the running order.
B121: 10 | C121: INCLUDED | D121: Drone - do they have one and a licensed operator? | E121: Many venues and all airport-adjacent areas restrict drones.
B122: 11 | C122: LOGISTICS | D122: Who exactly will shoot our wedding - the person we are meeting? | E122: Big studios assign whoever is free. Get the name in the contract.
B123: 12 | C123: LOGISTICS | D123: Can we see TWO complete weddings, start to finish - not just highlights? | E123: A 30-image highlight reel hides a weak photographer.
... B131: 20 | C131: RISK | D131: Deposit, payment schedule and cancellation terms | E131: Get it in writing.
D133: DECISION - which option are you going with? | E133: Record the chosen vendor on 05 Vendors, then the rest of the workbook picks them up. | F133: Not decided | G133: =IF($F133="Option A",$F102,IF($F133="Option B",$G102,IF($F133="Option C",$H102,""))) | H133: =IF($F133="Option A",IF($F107>0,$F107,$F106),IF($F133="Option B",IF($G107>0,$G107,$G106),IF($F133="Option C",IF($H107>0,$H107,$H106),0))) -> 0 | I133: =IF($G133="","-",IF(COUNTIF('05 Vendors'!$D$7:$D$200,$G133)>0,"Yes","NOT YET")) -> -
B136: 04 · VIDEOGRAPHER | I136: back to index: row 5
B137: # | C137: Group | D137: What to ask / compare | E137: Why it matters - what to watch for | F137: OPTION A | G137: OPTION B | H137: OPTION C | I137: Your notes
...

Sheet 06 Contributions
B2: FAMILY & COUPLE CONTRIBUTIONS
B3: Who has agreed to fund what, and how much has actually arrived. Nothing is assumed - fill this in to match your own family arrangement.
E5: TOTALS | G5: =SUM(G7:G60) -> 0 | H5: =SUM(H7:H60) -> 0 | I5: =SUM(I7:I60) -> 0
B6: ID | C6: Contributor | D6: Relationship | E6: Purpose / category | F6: Agreed on | G6: Agreed amount | H6: Received to date | I6: Still to come | J6: Last received on | K6: Notes
B7: C01 | C7: Groom's family | D7: Groom's parents | E7: General wedding fund | I7: =IF(G7="","",MAX(0,G7-H7))
B8: C02 | C8: Bride's family | D8: Bride's parents | E8: General wedding fund | I8: =IF(G8="","",MAX(0,G8-H8))
B9: C03 | C9: Couple - joint savings | D9: Bride & Groom | E9: General wedding fund | I9: =IF(G9="","",MAX(0,G9-H9))
B10: C04 | C10: Groom | D10: Groom | E10: Jewellery & rings | I10: =IF(G10="","",MAX(0,G10-H10))
B11: C05 | C11: Other | I11: =IF(G11="","",MAX(0,G11-H11))
I12: =IF(G12="","",MAX(0,G12-H12))
I13: =IF(G13="","",MAX(0,G13-H13))
I14: =IF(G14="","",MAX(0,G14-H14))
I15: =IF(G15="","",MAX(0,G15-H15))
I16: =IF(G16="","",MAX(0,G16-H16))
I17: =IF(G17="","",MAX(0,G17-H17))
I18: =IF(G18="","",MAX(0,G18-H18))
I19: =IF(G19="","",MAX(0,G19-H19))
I20: =IF(G20="","",MAX(0,G20-H20))
I21: =IF(G21="","",MAX(0,G21-H21))
I22: =IF(G22="","",MAX(0,G22-H22))
I23: =IF(G23="","",MAX(0,G23-H23))
... I60: =IF(G60="","",MAX(0,G60-H60))

Sheet 07 Tasks
B2: MASTER TASK LIST
B3: Due dates are formulas counted back from the wedding date - change the date on 01 START HERE and the whole plan re-dates itself. Sort or filter by Flag to see what is overdue.
D5: TASK SUMMARY | E5: ="Total: "&COUNTA(D7:D250) -> Total: 93 | G5: ="Done: "&COUNTIF(K7:K250,"Completed") -> Done: 1 | J5: ="Overdue: "&COUNTIF(L7:L250,"OVERDUE") -> Overdue: 0 | K5: ="This week: "&COUNTIF(L7:L250,"This week") -> This week: 1
B6: ID | C6: Category | D6: Task | E6: Owner | F6: Backup | G6: Priority | H6: Start date | I6: Due date | J6: Days left | K6: Status | L6: Flag | M6: Depends on | N6: Vendor | O6: Cost | P6: Payment needed? | Q6: Completed on | R6: Notes
B7: T001 | C7: Finance | D7: Agree the total wedding budget and who contributes what | E7: Couple | G7: Critical | I7: =WeddingDate-360 -> 46273 | J7: =IF($I7="","",$I7-TODAY()) -> 5 | K7: Not Started | L7: =IF($D7="","",IF($K7="Completed","Done",IF($K7="Cancelled","-",IF($I7="","No date",IF($I7<TODAY(),"OVERDUE",IF($I7=TODAY(),"TODAY",IF($I7<=TODAY()+7,"This week",IF($I7<=TODAY()+30,"This month","Upcoming")))))))) -> This week
B8: T002 | C8: Finance | D8: Open a dedicated wedding savings account | E8: Couple | G8: High | I8: =WeddingDate-350 -> 46283 | J8: =IF($I8="","",$I8-TODAY()) -> 15 | K8: Not Started | L8: =IF($D8="","",IF($K8="Completed","Done",IF($K8="Cancelled","-",IF($I8="","No date",IF($I8<TODAY(),"OVERDUE",IF($I8=TODAY(),"TODAY",IF($I8<=TODAY()+7,"This week",IF($I8<=TODAY()+30,"This month","Upcoming")))))))) -> This month
B9: T003 | C9: Venue | D9: Shortlist and visit 3-4 hotels / banquet halls | E9: Couple | G9: Critical | I9: =WeddingDate-345 -> 46288 | J9: =IF($I9="","",$I9-TODAY()) -> 20 | K9: Not Started | L9: =IF($D9="","",IF($K9="Completed","Done",IF($K9="Cancelled","-",IF($I9="","No date",IF($I9<TODAY(),"OVERDUE",IF($I9=TODAY(),"TODAY",IF($I9<=TODAY()+7,"This week",IF($I9<=TODAY()+30,"This month","Upcoming")))))))) -> This month
B10: T004 | C10: Venue | D10: Confirm the auspicious time (nekath) with the astrologer | E10: Groom's Family | G10: Critical | I10: =WeddingDate-340 -> 46293 | J10: =IF($I10="","",$I10-TODAY()) -> 25 | K10: Not Started | L10: =IF($D10="","",IF($K10="Completed","Done",IF($K10="Cancelled","-",IF($I10="","No date",IF($I10<TODAY(),"OVERDUE",IF($I10=TODAY(),"TODAY",IF($I10<=TODAY()+7,"This week",IF($I10<=TODAY()+30,"This month","Upcoming")))))))) -> This month
B11: T005 | C11: Venue | D11: Block the date and pay the venue booking deposit | E11: Couple | G11: Critical | I11: =WeddingDate-330 -> 46303 | J11: =IF($I11="","",$I11-TODAY()) -> 35 | K11: Not Started | L11: =IF($D11="","",IF($K11="Completed","Done",IF($K11="Cancelled","-",IF($I11="","No date",IF($I11<TODAY(),"OVERDUE",IF($I11=TODAY(),"TODAY",IF($I11<=TODAY()+7,"This week",IF($I11<=TODAY()+30,"This month","Upcoming")))))))) -> Upcoming
B12: T006 | C12: Guests & RSVP | D12: Agree the guest ceiling with both families | E12: Couple | G12: Critical | I12: =WeddingDate-330 -> 46303 | J12: =IF($I12="","",$I12-TODAY()) -> 35 | K12: Not Started | L12: =IF($D12="","",IF($K12="Completed","Done",IF($K12="Cancelled","-",IF($I12="","No date",IF($I12<TODAY(),"OVERDUE",IF($I12=TODAY(),"TODAY",IF($I12<=TODAY()+7,"This week",IF($I12<=TODAY()+30,"This month","Upcoming")))))))) -> Upcoming
B13: T007 | C13: Venue | D13: Sign the venue contract and read the cancellation clause | E13: Couple | G13: Critical | I13: =WeddingDate-320 -> 46313 | J13: =IF($I13="","",$I13-TODAY()) -> 45 | K13: Not Started | L13: =IF($D13="","",IF($K13="Completed","Done",IF($K13="Cancelled","-",IF($I13="","No date",IF($I13<TODAY(),"OVERDUE",IF($I13=TODAY(),"TODAY",IF($I13<=TODAY()+7,"This week",IF($I13<=TODAY()+30,"This month","Upcoming")))))))) -> Upcoming
B14: T008 | C14: Photography | D14: Shortlist photographers and review full wedding albums | E14: Couple | G14: High | I14: =WeddingDate-300 -> 46333 | J14: =IF($I14="","",$I14-TODAY()) -> 65 | K14: Not Started | L14: =IF($D14="","",IF($K14="Completed","Done",IF($K14="Cancelled","-",IF($I14="","No date",IF($I14<TODAY(),"OVERDUE",IF($I14=TODAY(),"TODAY",IF($I14<=TODAY()+7,"This week",IF($I14<=TODAY()+30,"This month","Upcoming")))))))) -> Upcoming
B15: T009 | C15: Videography | D15: Shortlist videographers and watch full highlight films | E15: Couple | G15: High | I15: =WeddingDate-300 -> 46333 | J15: =IF($I15="","",$I15-TODAY()) -> 65 | K15: Not Started | L15: =IF($D15="","",IF($K15="Completed","Done",IF($K15="Cancelled","-",IF($I15="","No date",IF($I15<TODAY(),"OVERDUE",IF($I15=TODAY(),"TODAY",IF($I15<=TODAY()+7,"This week",IF($I15<=TODAY()+30,"This month","Upcoming")))))))) -> Upcoming
B16: T010 | C16: Photography | D16: Book the photographer and pay the deposit | E16: Couple | G16: Critical | I16: =WeddingDate-285 -> 46348 | J16: =IF($I16="","",$I16-TODAY()) -> 80 | K16: Not Started | L16: =IF($D16="","",IF($K16="Completed","Done",IF($K16="Cancelled","-",IF($I16="","No date",IF($I16<TODAY(),"OVERDUE",IF($I16=TODAY(),"TODAY",IF($I16<=TODAY()+7,"This week",IF($I16<=TODAY()+30,"This month","Upcoming")))))))) -> Upcoming
B17: T011 | C17: Videography | D17: Book the videographer and pay the deposit | E17: Couple | G17: Critical | I17: =WeddingDate-285 -> 46348 | J17: =IF($I17="","",$I17-TODAY()) -> 80 | K17: Not Started | L17: =IF($D17="","",IF($K17="Completed","Done",IF($K17="Cancelled","-",IF($I17="","No date",IF($I17<TODAY(),"OVERDUE",IF($I17=TODAY(),"TODAY",IF($I17<=TODAY()+7,"This week",IF($I17<=TODAY()+30,"This month","Upcoming")))))))) -> Upcoming
B18: T012 | C18: Attire | D18: Book the bridal saree designer / osari maker | E18: Bride | G18: Critical | I18: =WeddingDate-280 -> 46353 | J18: =IF($I18="","",$I18-TODAY()) -> 85 | K18: Not Started | L18: =IF($D18="","",IF($K18="Completed","Done",IF($K18="Cancelled","-",IF($I18="","No date",IF($I18<TODAY(),"OVERDUE",IF($I18=TODAY(),"TODAY",IF($I18<=TODAY()+7,"This week",IF($I18<=TODAY()+30,"This month","Upcoming")))))))) -> Upcoming
B19: T013 | C19: Beauty & Grooming | D19: Book the bridal dresser (hair & makeup) for the day | E19: Bride | G19: Critical | I19: =WeddingDate-275 -> 46358 | J19: =IF($I19="","",$I19-TODAY()) -> 90 | K19: Not Started | L19: =IF($D19="","",IF($K19="Completed","Done",IF($K19="Cancelled","-",IF($I19="","No date",IF($I19<TODAY(),"OVERDUE",IF($I19=TODAY(),"TODAY",IF($I19<=TODAY()+7,"This week",IF($I19<=TODAY()+30,"This month","Upcoming")))))))) -> Upcoming
B20: T014 | C20: Ceremony | D20: Decide the ceremony format - Poruwa, registration, blessing | E20: Couple | G20: Critical | I20: =WeddingDate-270 -> 46363 | J20: =IF($I20="","",$I20-TODAY()) -> 95 | K20: Not Started | L20: =IF($D20="","",IF($K20="Completed","Done",IF($K20="Cancelled","-",IF($I20="","No date",IF($I20<TODAY(),"OVERDUE",IF($I20=TODAY(),"TODAY",IF($I20<=TODAY()+7,"This week",IF($I20<=TODAY()+30,"This month","Upcoming")))))))) -> Upcoming
B21: T015 | C21: Ceremony | D21: Book the Ashtaka chanter / Poruwa officiant | E21: Groom's Family | G21: Critical | I21: =WeddingDate-260 -> 46373 | J21: =IF($I21="","",$I21-TODAY()) -> 105 | K21: Not Started | L21: =IF($D21="","",IF($K21="Completed","Done",IF($K21="Cancelled","-",IF($I21="","No date",IF($I21<TODAY(),"OVERDUE",IF($I21=TODAY(),"TODAY",IF($I21<=TODAY()+7,"This week",IF($I21<=TODAY()+30,"This month","Upcoming")))))))) -> Upcoming
B22: T016 | C22: Entertainment | D22: Book the Kandyan dancers and Hewisi drummers | E22: Groom's Family | G22: High | I22: =WeddingDate-255 -> 46378 | J22: =IF($I22="","",$I22-TODAY()) -> 110 | K22: Not Started | L22: =IF($D22="","",IF($K22="Completed","Done",IF($K22="Cancelled","-",IF($I22="","No date",IF($I22<TODAY(),"OVERDUE",IF($I22=TODAY(),"TODAY",IF($I22<=TODAY()+7,"This week",IF($I22<=TODAY()+30,"This month","Upcoming")))))))) -> Upcoming
B23: T017 | C23: Decor & Florals | D23: Shortlist decorators and review Poruwa portfolios | E23: Couple | G23: High | I23: =WeddingDate-250 -> 46383 | J23: =IF($I23="","",$I23-TODAY()) -> 115 | K23: Not Started | L23: =IF($D23="","",IF($K23="Completed","Done",IF($K23="Cancelled","-",IF($I23="","No date",IF($I23<TODAY(),"OVERDUE",IF($I23=TODAY(),"TODAY",IF($I23<=TODAY()+7,"This week",IF($I23<=TODAY()+30,"This month","Upcoming")))))))) -> Upcoming
B24: T018 | C24: Decor & Florals | D24: Confirm the decorator and agree the Poruwa design | E24: Couple | G24: Critical | I24: =WeddingDate-230 -> 46403 | J24: =IF($I24="","",$I24-TODAY()) -> 135 | K24: Not Started | L24: =IF($D24="","",IF($K24="Completed","Done",IF($K24="Cancelled","-",IF($I24="","No date",IF($I24<TODAY(),"OVERDUE",IF($I24=TODAY(),"TODAY",IF($I24<=TODAY()+7,"This week",IF($I24<=TODAY()+30,"This month","Upcoming")))))))) -> Upcoming
B25: T019 | C25: Guests & RSVP | D25: Build the full guest list with both families | E25: Couple | G25: Critical | I25: =WeddingDate-240 -> 46393 | J25: =IF($I25="","",$I25-TODAY()) -> 125 | K25: Not Started | L25: =IF($D25="","",IF($K25="Completed","Done",IF($K25="Cancelled","-",IF($I25="","No date",IF($I25<TODAY(),"OVERDUE",IF($I25=TODAY(),"TODAY",IF($I25<=TODAY()+7,"This week",IF($I25<=TODAY()+30,"This month","Upcoming")))))))) -> Upcoming
B26: T020 | C26: Attire | D26: Book the groom's suit / national dress tailor | E26: Groom | G26: High | I26: =WeddingDate-230 -> 46403 | J26: =IF($I26="","",$I26-TODAY()) -> 135 | K26: Not Started | L26: =IF($D26="","",IF($K26="Completed","Done",IF($K26="Cancelled","-",IF($I26="","No date",IF($I26<TODAY(),"OVERDUE",IF($I26=TODAY(),"TODAY",IF($I26<=TODAY()+7,"This week",IF($I26<=TODAY()+30,"This month","Upcoming")))))))) -> Upcoming
B27: T021 | C27: Jewellery | D27: Decide bought vs rented for the bridal jewellery set | E27: Couple | G27: High | I27: =WeddingDate-225 -> 46408 | J27: =IF($I27="","",$I27-TODAY()) -> 140 | K27: Not Started | L27: =IF($D27="","",IF($K27="Completed","Done",IF($K27="Cancelled","-",IF($I27="","No date",IF($I27<TODAY(),"OVERDUE",IF($I27=TODAY(),"TODAY",IF($I27<=TODAY()+7,"This week",IF($I27<=TODAY()+30,"This month","Upcoming")))))))) -> Upcoming
B28: T022 | C28: Registration & Legal | D28: VERIFY registration requirements with the Registrar | E28: Couple | G28: Critical | I28: =WeddingDate-220 -> 46413 | J28: =IF($I28="","",$I28-TODAY()) -> 145 | K28: Not Started | L28: =IF($D28="","",IF($K28="Completed","Done",IF($K28="Cancelled","-",IF($I28="","No date",IF($I28<TODAY(),"OVERDUE",IF($I28=TODAY(),"TODAY",IF($I28<=TODAY()+7,"This week",IF($I28<=TODAY()+30,"This month","Upcoming")))))))) -> Upcoming
B29: T023 | C29: Cake | D29: Taste and select the wedding cake baker | E29: Couple | G29: Medium | I29: =WeddingDate-210 -> 46423 | J29: =IF($I29="","",$I29-TODAY()) -> 155 | K29: Not Started | L29: =IF($D29="","",IF($K29="Completed","Done",IF($K29="Cancelled","-",IF($I29="","No date",IF($I29<TODAY(),"OVERDUE",IF($I29=TODAY(),"TODAY",IF($I29<=TODAY()+7,"This week",IF($I29<=TODAY()+30,"This month","Upcoming")))))))) -> Upcoming
B30: T024 | C30: Entertainment | D30: Book the MC and the DJ / band | E30: Couple | G30: High | I30: =WeddingDate-200 -> 46433 | J30: =IF($I30="","",$I30-TODAY()) -> 165 | K30: Not Started | L30: =IF($D30="","",IF($K30="Completed","Done",IF($K30="Cancelled","-",IF($I30="","No date",IF($I30<TODAY(),"OVERDUE",IF($I30=TODAY(),"TODAY",IF($I30<=TODAY()+7,"This week",IF($I30<=TODAY()+30,"This month","Upcoming")))))))) -> Upcoming
B31: T025 | C31: Transport | D31: Book the bridal car and family vehicles | E31: Groom's Family | G31: High | I31: =WeddingDate-190 -> 46443 | J31: =IF($I31="","",$I31-TODAY()) -> 175 | K31: Not Started | L31: =IF($D31="","",IF($K31="Completed","Done",IF($K31="Cancelled","-",IF($I31="","No date",IF($I31<TODAY(),"OVERDUE",IF($I31=TODAY(),"TODAY",IF($I31<=TODAY()+7,"This week",IF($I31<=TODAY()+30,"This month","Upcoming")))))))) -> Upcoming
B32: T026 | C32: Accommodation | D32: Block a room allocation for outstation guests | E32: Couple | G32: Medium | I32: =WeddingDate-185 -> 46448 | J32: =IF($I32="","",$I32-TODAY()) -> 180 | K32: Not Started | L32: =IF($D32="","",IF($K32="Completed","Done",IF($K32="Cancelled","-",IF($I32="","No date",IF($I32<TODAY(),"OVERDUE",IF($I32=TODAY(),"TODAY",IF($I32<=TODAY()+7,"This week",IF($I32<=TODAY()+30,"This month","Upcoming")))))))) -> Upcoming
B33: T027 | C33: Invitations | D33: Choose the invitation design and printer | E33: Couple | G33: High | I33: =WeddingDate-180 -> 46453 | J33: =IF($I33="","",$I33-TODAY()) -> 185 | K33: Not Started | L33: =IF($D33="","",IF($K33="Completed","Done",IF($K33="Cancelled","-",IF($I33="","No date",IF($I33<TODAY(),"OVERDUE",IF($I33=TODAY(),"TODAY",IF($I33<=TODAY()+7,"This week",IF($I33<=TODAY()+30,"This month","Upcoming")))))))) -> Upcoming
B34: T028 | C34: Photography | D34: Plan and book the pre-shoot (location, date, outfits) | E34: Couple | G34: Medium | I34: =WeddingDate-175 -> 46458 | J34: =IF($I34="","",$I34-TODAY()) -> 190 | K34: Not Started | L34: =IF($D34="","",IF($K34="Completed","Done",IF($K34="Cancelled","-",IF($I34="","No date",IF($I34<TODAY(),"OVERDUE",IF($I34=TODAY(),"TODAY",IF($I34<=TODAY()+7,"This week",IF($I34<=TODAY()+30,"This month","Upcoming")))))))) -> Upcoming
B35: T029 | C35: Attire | D35: First bridal saree fitting | E35: Bride | G35: High | I35: =WeddingDate-165 -> 46468 | J35: =IF($I35="","",$I35-TODAY()) -> 200 | K35: Not Started | L35: =IF($D35="","",IF($K35="Completed","Done",IF($K35="Cancelled","-",IF($I35="","No date",IF($I35<TODAY(),"OVERDUE",IF($I35=TODAY(),"TODAY",IF($I35<=TODAY()+7,"This week",IF($I35<=TODAY()+30,"This month","Upcoming")))))))) -> Upcoming
B36: T030 | C36: Beauty & Grooming | D36: Start the bridal facial / skin treatment course | E36: Bride | G36: Medium | I36: =WeddingDate-160 -> 46473 | J36: =IF($I36="","",$I36-TODAY()) -> 205 | K36: Not Started | L36: =IF($D36="","",IF($K36="Completed","Done",IF($K36="Cancelled","-",IF($I36="","No date",IF($I36<TODAY(),"OVERDUE",IF($I36=TODAY(),"TODAY",IF($I36<=TODAY()+7,"This week",IF($I36<=TODAY()+30,"This month","Upcoming")))))))) -> Upcoming
B37: T031 | C37: Guests & RSVP | D37: Collect addresses and phone numbers for all guests | E37: Couple | G37: High | I37: =WeddingDate-155 -> 46478 | J37: =IF($I37="","",$I37-TODAY()) -> 210 | K37: Not Started | L37: =IF($D37="","",IF($K37="Completed","Done",IF($K37="Cancelled","-",IF($I37="","No date",IF($I37<TODAY(),"OVERDUE",IF($I37=TODAY(),"TODAY",IF($I37<=TODAY()+7,"This week",IF($I37<=TODAY()+30,"This month","Upcoming")))))))) -> Upcoming
B38: T032 | C38: Reception | D38: Attend the menu tasting and finalise the buffet | E38: Couple | G38: Critical | I38: =WeddingDate-150 -> 46483 | J38: =IF($I38="","",$I38-TODAY()) -> 215 | K38: Not Started | L38: =IF($D38="","",IF($K38="Completed","Done",IF($K38="Cancelled","-",IF($I38="","No date",IF($I38<TODAY(),"OVERDUE",IF($I38=TODAY(),"TODAY",IF($I38<=TODAY()+7,"This week",IF($I38<=TODAY()+30,"This month","Upcoming")))))))) -> Upcoming
B39: T033 | C39: Food & Beverage | D39: Decide on alcohol - corkage vs hotel bar | E39: Couple | G39: Medium | I39: =WeddingDate-150 -> 46483 | J39: =IF($I39="","",$I39-TODAY()) -> 215 | K39: Not Started | L39: =IF($D39="","",IF($K39="Completed","Done",IF($K39="Cancelled","-",IF($I39="","No date",IF($I39<TODAY(),"OVERDUE",IF($I39=TODAY(),"TODAY",IF($I39<=TODAY()+7,"This week",IF($I39<=TODAY()+30,"This month","Upcoming")))))))) -> Upcoming
B40: T034 | C40: Invitations | D40: Proofread the invitation text (both families check names) | E40: Couple | G40: Critical | I40: =WeddingDate-145 -> 46488 | J40: =IF($I40="","",$I40-TODAY()) -> 220 | K40: Not Started | L40: =IF($D40="","",IF($K40="Completed","Done",IF($K40="Cancelled","-",IF($I40="","No date",IF($I40<TODAY(),"OVERDUE",IF($I40=TODAY(),"TODAY",IF($I40<=TODAY()+7,"This week",IF($I40<=TODAY()+30,"This month","Upcoming")))))))) -> Upcoming
B41: T035 | C41: Invitations | D41: Print the invitations | E41: Couple | G41: High | I41: =WeddingDate-135 -> 46498 | J41: =IF($I41="","",$I41-TODAY()) -> 230 | K41: Not Started | L41: =IF($D41="","",IF($K41="Completed","Done",IF($K41="Cancelled","-",IF($I41="","No date",IF($I41<TODAY(),"OVERDUE",IF($I41=TODAY(),"TODAY",IF($I41<=TODAY()+7,"This week",IF($I41<=TODAY()+30,"This month","Upcoming")))))))) -> Upcoming
B42: T036 | C42: Jewellery | D42: Order or reserve the bridal jewellery set | E42: Bride | G42: High | I42: =WeddingDate-130 -> 46503 | J42: =IF($I42="","",$I42-TODAY()) -> 235 | K42: Not Started | L42: =IF($D42="","",IF($K42="Completed","Done",IF($K42="Cancelled","-",IF($I42="","No date",IF($I42<TODAY(),"OVERDUE",IF($I42=TODAY(),"TODAY",IF($I42<=TODAY()+7,"This week",IF($I42<=TODAY()+30,"This month","Upcoming")))))))) -> Upcoming
B43: T037 | C43: Jewellery | D43: Order the wedding rings and confirm sizing | E43: Couple | G43: Critical | I43: =WeddingDate-130 -> 46503 | J43: =IF($I43="","",$I43-TODAY()) -> 235 | K43: Completed | L43: =IF($D43="","",IF($K43="Completed","Done",IF($K43="Cancelled","-",IF($I43="","No date",IF($I43<TODAY(),"OVERDUE",IF($I43=TODAY(),"TODAY",IF($I43<=TODAY()+7,"This week",IF($I43<=TODAY()+30,"This month","Upcoming")))))))) -> Done | P43: Yes
B44: T038 | C44: Photography | D44: Do the pre-shoot | E44: Couple | G44: Medium | I44: =WeddingDate-125 -> 46508 | J44: =IF($I44="","",$I44-TODAY()) -> 240 | K44: Not Started | L44: =IF($D44="","",IF($K44="Completed","Done",IF($K44="Cancelled","-",IF($I44="","No date",IF($I44<TODAY(),"OVERDUE",IF($I44=TODAY(),"TODAY",IF($I44<=TODAY()+7,"This week",IF($I44<=TODAY()+30,"This month","Upcoming")))))))) -> Upcoming
B45: T039 | C45: Attire | D45: Choose bridesmaids' and groomsmen's outfits | E45: Bride | G45: Medium | I45: =WeddingDate-120 -> 46513 | J45: =IF($I45="","",$I45-TODAY()) -> 245 | K45: Not Started | L45: =IF($D45="","",IF($K45="Completed","Done",IF($K45="Cancelled","-",IF($I45="","No date",IF($I45<TODAY(),"OVERDUE",IF($I45=TODAY(),"TODAY",IF($I45<=TODAY()+7,"This week",IF($I45<=TODAY()+30,"This month","Upcoming")))))))) -> Upcoming
B46: T040 | C46: Beauty & Grooming | D46: Bridal hair and makeup trial | E46: Bride | G46: High | I46: =WeddingDate-110 -> 46523 | J46: =IF($I46="","",$I46-TODAY()) -> 255 | K46: Not Started | L46: =IF($D46="","",IF($K46="Completed","Done",IF($K46="Cancelled","-",IF($I46="","No date",IF($I46<TODAY(),"OVERDUE",IF($I46=TODAY(),"TODAY",IF($I46<=TODAY()+7,"This week",IF($I46<=TODAY()+30,"This month","Upcoming")))))))) -> Upcoming
B47: T041 | C47: Invitations | D47: Start distributing invitations (hand delivery first) | E47: Couple | G47: Critical | I47: =WeddingDate-100 -> 46533 | J47: =IF($I47="","",$I47-TODAY()) -> 265 | K47: Not Started | L47: =IF($D47="","",IF($K47="Completed","Done",IF($K47="Cancelled","-",IF($I47="","No date",IF($I47<TODAY(),"OVERDUE",IF($I47=TODAY(),"TODAY",IF($I47<=TODAY()+7,"This week",IF($I47<=TODAY()+30,"This month","Upcoming")))))))) -> Upcoming
B48: T042 | C48: Guests & RSVP | D48: Log every invitation as sent in 09 Guests | E48: Couple | G48: High | I48: =WeddingDate-95 -> 46538 | J48: =IF($I48="","",$I48-TODAY()) -> 270 | K48: Not Started | L48: =IF($D48="","",IF($K48="Completed","Done",IF($K48="Cancelled","-",IF($I48="","No date",IF($I48<TODAY(),"OVERDUE",IF($I48=TODAY(),"TODAY",IF($I48<=TODAY()+7,"This week",IF($I48<=TODAY()+30,"This month","Upcoming")))))))) -> Upcoming
B49: T043 | C49: Decor & Florals | D49: Approve the final decor drawings and colour samples | E49: Couple | G49: High | I49: =WeddingDate-90 -> 46543 | J49: =IF($I49="","",$I49-TODAY()) -> 275 | K49: Not Started | L49: =IF($D49="","",IF($K49="Completed","Done",IF($K49="Cancelled","-",IF($I49="","No date",IF($I49<TODAY(),"OVERDUE",IF($I49=TODAY(),"TODAY",IF($I49<=TODAY()+7,"This week",IF($I49<=TODAY()+30,"This month","Upcoming")))))))) -> Upcoming
B50: T044 | C50: Registration & Legal | D50: Submit the notice of marriage | E50: Couple | G50: Critical | I50: =WeddingDate-90 -> 46543 | J50: =IF($I50="","",$I50-TODAY()) -> 275 | K50: Not Started | L50: =IF($D50="","",IF($K50="Completed","Done",IF($K50="Cancelled","-",IF($I50="","No date",IF($I50<TODAY(),"OVERDUE",IF($I50=TODAY(),"TODAY",IF($I50<=TODAY()+7,"This week",IF($I50<=TODAY()+30,"This month","Upcoming")))))))) -> Upcoming
B51: T045 | C51: Registration & Legal | D51: Confirm the registrar's attendance and fee | E51: Couple | G51: Critical | I51: =WeddingDate-85 -> 46548 | J51: =IF($I51="","",$I51-TODAY()) -> 280 | K51: Not Started | L51: =IF($D51="","",IF($K51="Completed","Done",IF($K51="Cancelled","-",IF($I51="","No date",IF($I51<TODAY(),"OVERDUE",IF($I51=TODAY(),"TODAY",IF($I51<=TODAY()+7,"This week",IF($I51<=TODAY()+30,"This month","Upcoming")))))))) -> Upcoming
B52: T046 | C52: Registration & Legal | D52: Confirm two witnesses and check their NICs are valid | E52: Couple | G52: Critical | I52: =WeddingDate-80 -> 46553 | J52: =IF($I52="","",$I52-TODAY()) -> 285 | K52: Not Started | L52: =IF($D52="","",IF($K52="Completed","Done",IF($K52="Cancelled","-",IF($I52="","No date",IF($I52<TODAY(),"OVERDUE",IF($I52=TODAY(),"TODAY",IF($I52<=TODAY()+7,"This week",IF($I52<=TODAY()+30,"This month","Upcoming")))))))) -> Upcoming
B53: T047 | C53: Transport | D53: Arrange guest buses / vans from key pick-up points | E53: Coordinator | G53: Medium | I53: =WeddingDate-75 -> 46558 | J53: =IF($I53="","",$I53-TODAY()) -> 290 | K53: Not Started | L53: =IF($D53="","",IF($K53="Completed","Done",IF($K53="Cancelled","-",IF($I53="","No date",IF($I53<TODAY(),"OVERDUE",IF($I53=TODAY(),"TODAY",IF($I53<=TODAY()+7,"This week",IF($I53<=TODAY()+30,"This month","Upcoming")))))))) -> Upcoming
B54: T048 | C54: Reception | D54: Draft the reception running order with the MC | E54: Couple | G54: High | I54: =WeddingDate-70 -> 46563 | J54: =IF($I54="","",$I54-TODAY()) -> 295 | K54: Not Started | L54: =IF($D54="","",IF($K54="Completed","Done",IF($K54="Cancelled","-",IF($I54="","No date",IF($I54<TODAY(),"OVERDUE",IF($I54=TODAY(),"TODAY",IF($I54<=TODAY()+7,"This week",IF($I54<=TODAY()+30,"This month","Upcoming")))))))) -> Upcoming
B55: T049 | C55: Entertainment | D55: Give the DJ the must-play and do-not-play list | E55: Couple | G55: Medium | I55: =WeddingDate-65 -> 46568 | J55: =IF($I55="","",$I55-TODAY()) -> 300 | K55: Not Started | L55: =IF($D55="","",IF($K55="Completed","Done",IF($K55="Cancelled","-",IF($I55="","No date",IF($I55<TODAY(),"OVERDUE",IF($I55=TODAY(),"TODAY",IF($I55<=TODAY()+7,"This week",IF($I55<=TODAY()+30,"This month","Upcoming")))))))) -> Upcoming
B56: T050 | C56: Guests & RSVP | D56: Begin RSVP follow-up calls for anyone who has not replied | E56: Couple | G56: High | I56: =WeddingDate-60 -> 46573 | J56: =IF($I56="","",$I56-TODAY()) -> 305 | K56: Not Started | L56: =IF($D56="","",IF($K56="Completed","Done",IF($K56="Cancelled","-",IF($I56="","No date",IF($I56<TODAY(),"OVERDUE",IF($I56=TODAY(),"TODAY",IF($I56<=TODAY()+7,"This week",IF($I56<=TODAY()+30,"This month","Upcoming")))))))) -> Upcoming
B57: T051 | C57: Attire | D57: Second bridal saree fitting | E57: Bride | G57: High | I57: =WeddingDate-60 -> 46573 | J57: =IF($I57="","",$I57-TODAY()) -> 305 | K57: Not Started | L57: =IF($D57="","",IF($K57="Completed","Done",IF($K57="Cancelled","-",IF($I57="","No date",IF($I57<TODAY(),"OVERDUE",IF($I57=TODAY(),"TODAY",IF($I57<=TODAY()+7,"This week",IF($I57<=TODAY()+30,"This month","Upcoming")))))))) -> Upcoming
B58: T052 | C58: Gifts & Favours | D58: Order guest favours and family gifts | E58: Couple | G58: Medium | I58: =WeddingDate-55 -> 46578 | J58: =IF($I58="","",$I58-TODAY()) -> 310 | K58: Not Started | L58: =IF($D58="","",IF($K58="Completed","Done",IF($K58="Cancelled","-",IF($I58="","No date",IF($I58<TODAY(),"OVERDUE",IF($I58=TODAY(),"TODAY",IF($I58<=TODAY()+7,"This week",IF($I58<=TODAY()+30,"This month","Upcoming")))))))) -> Upcoming
B59: T053 | C59: Photography | D59: Agree the shot list with the photographer (18 Photo & Video) | E59: Couple | G59: High | I59: =WeddingDate-50 -> 46583 | J59: =IF($I59="","",$I59-TODAY()) -> 315 | K59: Not Started | L59: =IF($D59="","",IF($K59="Completed","Done",IF($K59="Cancelled","-",IF($I59="","No date",IF($I59<TODAY(),"OVERDUE",IF($I59=TODAY(),"TODAY",IF($I59<=TODAY()+7,"This week",IF($I59<=TODAY()+30,"This month","Upcoming")))))))) -> Upcoming
B60: T054 | C60: Accommodation | D60: Confirm the bridal suite and family rooms | E60: Couple | G60: High | I60: =WeddingDate-45 -> 46588 | J60: =IF($I60="","",$I60-TODAY()) -> 320 | K60: Not Started | L60: =IF($D60="","",IF($K60="Completed","Done",IF($K60="Cancelled","-",IF($I60="","No date",IF($I60<TODAY(),"OVERDUE",IF($I60=TODAY(),"TODAY",IF($I60<=TODAY()+7,"This week",IF($I60<=TODAY()+30,"This month","Upcoming")))))))) -> Upcoming
B61: T055 | C61: Beauty & Grooming | D61: Book bridesmaids' hair and makeup | E61: Bride | G61: Medium | I61: =WeddingDate-45 -> 46588 | J61: =IF($I61="","",$I61-TODAY()) -> 320 | K61: Not Started | L61: =IF($D61="","",IF($K61="Completed","Done",IF($K61="Cancelled","-",IF($I61="","No date",IF($I61<TODAY(),"OVERDUE",IF($I61=TODAY(),"TODAY",IF($I61<=TODAY()+7,"This week",IF($I61<=TODAY()+30,"This month","Upcoming")))))))) -> Upcoming
B62: T056 | C62: Reception | D62: Confirm the cake design, tiers and delivery time | E62: Couple | G62: Medium | I62: =WeddingDate-40 -> 46593 | J62: =IF($I62="","",$I62-TODAY()) -> 325 | K62: Not Started | L62: =IF($D62="","",IF($K62="Completed","Done",IF($K62="Cancelled","-",IF($I62="","No date",IF($I62<TODAY(),"OVERDUE",IF($I62=TODAY(),"TODAY",IF($I62<=TODAY()+7,"This week",IF($I62<=TODAY()+30,"This month","Upcoming")))))))) -> Upcoming
B63: T057 | C63: Guests & RSVP | D63: Close the RSVP list and give the venue a provisional number | E63: Couple | G63: Critical | I63: =WeddingDate-35 -> 46598 | J63: =IF($I63="","",$I63-TODAY()) -> 330 | K63: Not Started | L63: =IF($D63="","",IF($K63="Completed","Done",IF($K63="Cancelled","-",IF($I63="","No date",IF($I63<TODAY(),"OVERDUE",IF($I63=TODAY(),"TODAY",IF($I63<=TODAY()+7,"This week",IF($I63<=TODAY()+30,"This month","Upcoming")))))))) -> Upcoming
B64: T058 | C64: Guests & RSVP | D64: Draft the seating plan (10 RSVP & Seating) | E64: Couple | G64: Critical | I64: =WeddingDate-30 -> 46603 | J64: =IF($I64="","",$I64-TODAY()) -> 335 | K64: Not Started | L64: =IF($D64="","",IF($K64="Completed","Done",IF($K64="Cancelled","-",IF($I64="","No date",IF($I64<TODAY(),"OVERDUE",IF($I64=TODAY(),"TODAY",IF($I64<=TODAY()+7,"This week",IF($I64<=TODAY()+30,"This month","Upcoming")))))))) -> Upcoming
B65: T059 | C65: Logistics | D65: Confirm arrival and setup times with every vendor | E65: Coordinator | G65: Critical | I65: =WeddingDate-28 -> 46605 | J65: =IF($I65="","",$I65-TODAY()) -> 337 | K65: Not Started | L65: =IF($D65="","",IF($K65="Completed","Done",IF($K65="Cancelled","-",IF($I65="","No date",IF($I65<TODAY(),"OVERDUE",IF($I65=TODAY(),"TODAY",IF($I65<=TODAY()+7,"This week",IF($I65<=TODAY()+30,"This month","Upcoming")))))))) -> Upcoming
B66: T060 | C66: Finance | D66: Review 03 Budget line by line and settle any overspend | E66: Couple | G66: Critical | I66: =WeddingDate-28 -> 46605 | J66: =IF($I66="","",$I66-TODAY()) -> 337 | K66: Not Started | L66: =IF($D66="","",IF($K66="Completed","Done",IF($K66="Cancelled","-",IF($I66="","No date",IF($I66<TODAY(),"OVERDUE",IF($I66=TODAY(),"TODAY",IF($I66<=TODAY()+7,"This week",IF($I66<=TODAY()+30,"This month","Upcoming")))))))) -> Upcoming
B67: T061 | C67: Attire | D67: Final bridal fitting - no more alterations after this | E67: Bride | G67: Critical | I67: =WeddingDate-25 -> 46608 | J67: =IF($I67="","",$I67-TODAY()) -> 340 | K67: Not Started | L67: =IF($D67="","",IF($K67="Completed","Done",IF($K67="Cancelled","-",IF($I67="","No date",IF($I67<TODAY(),"OVERDUE",IF($I67=TODAY(),"TODAY",IF($I67<=TODAY()+7,"This week",IF($I67<=TODAY()+30,"This month","Upcoming")))))))) -> Upcoming
B68: T062 | C68: Attire | D68: Final groom's fitting | E68: Groom | G68: High | I68: =WeddingDate-25 -> 46608 | J68: =IF($I68="","",$I68-TODAY()) -> 340 | K68: Not Started | L68: =IF($D68="","",IF($K68="Completed","Done",IF($K68="Cancelled","-",IF($I68="","No date",IF($I68<TODAY(),"OVERDUE",IF($I68=TODAY(),"TODAY",IF($I68<=TODAY()+7,"This week",IF($I68<=TODAY()+30,"This month","Upcoming")))))))) -> Upcoming
B69: T063 | C69: Logistics | D69: Build the wedding-day timeline (20 Day Timeline) | E69: Coordinator | G69: Critical | I69: =WeddingDate-21 -> 46612 | J69: =IF($I69="","",$I69-TODAY()) -> 344 | K69: Not Started | L69: =IF($D69="","",IF($K69="Completed","Done",IF($K69="Cancelled","-",IF($I69="","No date",IF($I69<TODAY(),"OVERDUE",IF($I69=TODAY(),"TODAY",IF($I69<=TODAY()+7,"This week",IF($I69<=TODAY()+30,"This month","Upcoming")))))))) -> Upcoming
B70: T064 | C70: Reception | D70: Give the venue the confirmed guest number | E70: Couple | G70: Critical | I70: =WeddingDate-21 -> 46612 | J70: =IF($I70="","",$I70-TODAY()) -> 344 | K70: Not Started | L70: =IF($D70="","",IF($K70="Completed","Done",IF($K70="Cancelled","-",IF($I70="","No date",IF($I70<TODAY(),"OVERDUE",IF($I70=TODAY(),"TODAY",IF($I70<=TODAY()+7,"This week",IF($I70<=TODAY()+30,"This month","Upcoming")))))))) -> Upcoming
B71: T065 | C71: Food & Beverage | D71: Confirm vegetarian, child and special meal counts | E71: Couple | G71: High | I71: =WeddingDate-21 -> 46612 | J71: =IF($I71="","",$I71-TODAY()) -> 344 | K71: Not Started | L71: =IF($D71="","",IF($K71="Completed","Done",IF($K71="Cancelled","-",IF($I71="","No date",IF($I71<TODAY(),"OVERDUE",IF($I71=TODAY(),"TODAY",IF($I71<=TODAY()+7,"This week",IF($I71<=TODAY()+30,"This month","Upcoming")))))))) -> Upcoming
B72: T066 | C72: Decor & Florals | D72: Confirm the fresh flower order and colours | E72: Couple | G72: High | I72: =WeddingDate-21 -> 46612 | J72: =IF($I72="","",$I72-TODAY()) -> 344 | K72: Not Started | L72: =IF($D72="","",IF($K72="Completed","Done",IF($K72="Cancelled","-",IF($I72="","No date",IF($I72<TODAY(),"OVERDUE",IF($I72=TODAY(),"TODAY",IF($I72<=TODAY()+7,"This week",IF($I72<=TODAY()+30,"This month","Upcoming")))))))) -> Upcoming
B73: T067 | C73: Invitations | D73: Print table numbers, place cards and the seating board | E73: Couple | G73: Medium | I73: =WeddingDate-18 -> 46615 | J73: =IF($I73="","",$I73-TODAY()) -> 347 | K73: Not Started | L73: =IF($D73="","",IF($K73="Completed","Done",IF($K73="Cancelled","-",IF($I73="","No date",IF($I73<TODAY(),"OVERDUE",IF($I73=TODAY(),"TODAY",IF($I73<=TODAY()+7,"This week",IF($I73<=TODAY()+30,"This month","Upcoming")))))))) -> Upcoming
B74: T068 | C74: Logistics | D74: Print the wedding-day contact sheet (22 Contact Sheet) | E74: Coordinator | G74: High | I74: =WeddingDate-14 -> 46619 | J74: =IF($I74="","",$I74-TODAY()) -> 351 | K74: Not Started | L74: =IF($D74="","",IF($K74="Completed","Done",IF($K74="Cancelled","-",IF($I74="","No date",IF($I74<TODAY(),"OVERDUE",IF($I74=TODAY(),"TODAY",IF($I74<=TODAY()+7,"This week",IF($I74<=TODAY()+30,"This month","Upcoming")))))))) -> Upcoming
B75: T069 | C75: Guests & RSVP | D75: Chase the last outstanding RSVPs by phone | E75: Couple | G75: High | I75: =WeddingDate-14 -> 46619 | J75: =IF($I75="","",$I75-TODAY()) -> 351 | K75: Not Started | L75: =IF($D75="","",IF($K75="Completed","Done",IF($K75="Cancelled","-",IF($I75="","No date",IF($I75<TODAY(),"OVERDUE",IF($I75=TODAY(),"TODAY",IF($I75<=TODAY()+7,"This week",IF($I75<=TODAY()+30,"This month","Upcoming")))))))) -> Upcoming
B76: T070 | C76: Beauty & Grooming | D76: Bride's final facial / skin treatment | E76: Bride | G76: Medium | I76: =WeddingDate-14 -> 46619 | J76: =IF($I76="","",$I76-TODAY()) -> 351 | K76: Not Started | L76: =IF($D76="","",IF($K76="Completed","Done",IF($K76="Cancelled","-",IF($I76="","No date",IF($I76<TODAY(),"OVERDUE",IF($I76=TODAY(),"TODAY",IF($I76<=TODAY()+7,"This week",IF($I76<=TODAY()+30,"This month","Upcoming")))))))) -> Upcoming
B77: T071 | C77: Finance | D77: Confirm every vendor's final balance and payment date | E77: Couple | G77: Critical | I77: =WeddingDate-14 -> 46619 | J77: =IF($I77="","",$I77-TODAY()) -> 351 | K77: Not Started | L77: =IF($D77="","",IF($K77="Completed","Done",IF($K77="Cancelled","-",IF($I77="","No date",IF($I77<TODAY(),"OVERDUE",IF($I77=TODAY(),"TODAY",IF($I77<=TODAY()+7,"This week",IF($I77<=TODAY()+30,"This month","Upcoming")))))))) -> Upcoming
B78: T072 | C78: Ceremony | D78: Buy the Poruwa items - betel, coconut flower, thread, oil lamp | E78: Groom's Family | G78: Critical | I78: =WeddingDate-10 -> 46623 | J78: =IF($I78="","",$I78-TODAY()) -> 355 | K78: Not Started | L78: =IF($D78="","",IF($K78="Completed","Done",IF($K78="Cancelled","-",IF($I78="","No date",IF($I78<TODAY(),"OVERDUE",IF($I78=TODAY(),"TODAY",IF($I78<=TODAY()+7,"This week",IF($I78<=TODAY()+30,"This month","Upcoming")))))))) -> Upcoming
B79: T073 | C79: Ceremony | D79: Confirm the Jayamangala Gatha singers and rehearse the entrance | E79: Groom's Family | G79: High | I79: =WeddingDate-10 -> 46623 | J79: =IF($I79="","",$I79-TODAY()) -> 355 | K79: Not Started | L79: =IF($D79="","",IF($K79="Completed","Done",IF($K79="Cancelled","-",IF($I79="","No date",IF($I79<TODAY(),"OVERDUE",IF($I79=TODAY(),"TODAY",IF($I79<=TODAY()+7,"This week",IF($I79<=TODAY()+30,"This month","Upcoming")))))))) -> Upcoming
B80: T074 | C80: Logistics | D80: Confirm transport pick-up times with every driver | E80: Coordinator | G80: Critical | I80: =WeddingDate-10 -> 46623 | J80: =IF($I80="","",$I80-TODAY()) -> 355 | K80: Not Started | L80: =IF($D80="","",IF($K80="Completed","Done",IF($K80="Cancelled","-",IF($I80="","No date",IF($I80<TODAY(),"OVERDUE",IF($I80=TODAY(),"TODAY",IF($I80<=TODAY()+7,"This week",IF($I80<=TODAY()+30,"This month","Upcoming")))))))) -> Upcoming
B81: T075 | C81: Registration & Legal | D81: Collect NICs / passports and birth certificates in one folder | E81: Couple | G81: Critical | I81: =WeddingDate-7 -> 46626 | J81: =IF($I81="","",$I81-TODAY()) -> 358 | K81: Not Started | L81: =IF($D81="","",IF($K81="Completed","Done",IF($K81="Cancelled","-",IF($I81="","No date",IF($I81<TODAY(),"OVERDUE",IF($I81=TODAY(),"TODAY",IF($I81<=TODAY()+7,"This week",IF($I81<=TODAY()+30,"This month","Upcoming")))))))) -> Upcoming
B82: T076 | C82: Beauty & Grooming | D82: Groom's haircut | E82: Groom | G82: High | I82: =WeddingDate-7 -> 46626 | J82: =IF($I82="","",$I82-TODAY()) -> 358 | K82: Not Started | L82: =IF($D82="","",IF($K82="Completed","Done",IF($K82="Cancelled","-",IF($I82="","No date",IF($I82<TODAY(),"OVERDUE",IF($I82=TODAY(),"TODAY",IF($I82<=TODAY()+7,"This week",IF($I82<=TODAY()+30,"This month","Upcoming")))))))) -> Upcoming
B83: T077 | C83: Beauty & Grooming | D83: Bride's nails and final hair treatment | E83: Bride | G83: Medium | I83: =WeddingDate-5 -> 46628 | J83: =IF($I83="","",$I83-TODAY()) -> 360 | K83: Not Started | L83: =IF($D83="","",IF($K83="Completed","Done",IF($K83="Cancelled","-",IF($I83="","No date",IF($I83<TODAY(),"OVERDUE",IF($I83=TODAY(),"TODAY",IF($I83<=TODAY()+7,"This week",IF($I83<=TODAY()+30,"This month","Upcoming")))))))) -> Upcoming
B84: T078 | C84: Logistics | D84: Pack everything on 23 Procurement & Packing | E84: Couple | G84: Critical | I84: =WeddingDate-4 -> 46629 | J84: =IF($I84="","",$I84-TODAY()) -> 361 | K84: Not Started | L84: =IF($D84="","",IF($K84="Completed","Done",IF($K84="Cancelled","-",IF($I84="","No date",IF($I84<TODAY(),"OVERDUE",IF($I84=TODAY(),"TODAY",IF($I84<=TODAY()+7,"This week",IF($I84<=TODAY()+30,"This month","Upcoming")))))))) -> Upcoming
B85: T079 | C85: Reception | D85: Give the venue the final headcount and seating chart | E85: Coordinator | G85: Critical | I85: =WeddingDate-3 -> 46630 | J85: =IF($I85="","",$I85-TODAY()) -> 362 | K85: Not Started | L85: =IF($D85="","",IF($K85="Completed","Done",IF($K85="Cancelled","-",IF($I85="","No date",IF($I85<TODAY(),"OVERDUE",IF($I85=TODAY(),"TODAY",IF($I85<=TODAY()+7,"This week",IF($I85<=TODAY()+30,"This month","Upcoming")))))))) -> Upcoming
B86: T080 | C86: Finance | D86: Draw the cash needed for tips and day-of payments | E86: Couple | G86: Critical | I86: =WeddingDate-3 -> 46630 | J86: =IF($I86="","",$I86-TODAY()) -> 362 | K86: Not Started | L86: =IF($D86="","",IF($K86="Completed","Done",IF($K86="Cancelled","-",IF($I86="","No date",IF($I86<TODAY(),"OVERDUE",IF($I86=TODAY(),"TODAY",IF($I86<=TODAY()+7,"This week",IF($I86<=TODAY()+30,"This month","Upcoming")))))))) -> Upcoming
B87: T081 | C87: Logistics | D87: Brief the coordinator and the family on the timeline | E87: Couple | G87: Critical | I87: =WeddingDate-2 -> 46631 | J87: =IF($I87="","",$I87-TODAY()) -> 363 | K87: Not Started | L87: =IF($D87="","",IF($K87="Completed","Done",IF($K87="Cancelled","-",IF($I87="","No date",IF($I87<TODAY(),"OVERDUE",IF($I87=TODAY(),"TODAY",IF($I87<=TODAY()+7,"This week",IF($I87<=TODAY()+30,"This month","Upcoming")))))))) -> Upcoming
B88: T082 | C88: Logistics | D88: Charge every phone, camera and power bank | E88: Couple | G88: High | I88: =WeddingDate-1 -> 46632 | J88: =IF($I88="","",$I88-TODAY()) -> 364 | K88: Not Started | L88: =IF($D88="","",IF($K88="Completed","Done",IF($K88="Cancelled","-",IF($I88="","No date",IF($I88<TODAY(),"OVERDUE",IF($I88=TODAY(),"TODAY",IF($I88<=TODAY()+7,"This week",IF($I88<=TODAY()+30,"This month","Upcoming")))))))) -> Upcoming
B89: T083 | C89: Logistics | D89: Load the cars - jewellery, documents, emergency kit, gifts | E89: Couple | G89: Critical | I89: =WeddingDate-1 -> 46632 | J89: =IF($I89="","",$I89-TODAY()) -> 364 | K89: Not Started | L89: =IF($D89="","",IF($K89="Completed","Done",IF($K89="Cancelled","-",IF($I89="","No date",IF($I89<TODAY(),"OVERDUE",IF($I89=TODAY(),"TODAY",IF($I89<=TODAY()+7,"This week",IF($I89<=TODAY()+30,"This month","Upcoming")))))))) -> Upcoming
B90: T084 | C90: Jewellery | D90: Collect the jewellery from the vault / jeweller | E90: Groom | G90: Critical | I90: =WeddingDate-1 -> 46632 | J90: =IF($I90="","",$I90-TODAY()) -> 364 | K90: Waiting | L90: =IF($D90="","",IF($K90="Completed","Done",IF($K90="Cancelled","-",IF($I90="","No date",IF($I90<TODAY(),"OVERDUE",IF($I90=TODAY(),"TODAY",IF($I90<=TODAY()+7,"This week",IF($I90<=TODAY()+30,"This month","Upcoming")))))))) -> Upcoming
B91: T085 | C91: Ceremony | D91: WEDDING DAY | E91: Couple | G91: Critical | I91: =WeddingDate-0 -> 46633 | J91: =IF($I91="","",$I91-TODAY()) -> 365 | K91: Not Started | L91: =IF($D91="","",IF($K91="Completed","Done",IF($K91="Cancelled","-",IF($I91="","No date",IF($I91<TODAY(),"OVERDUE",IF($I91=TODAY(),"TODAY",IF($I91<=TODAY()+7,"This week",IF($I91<=TODAY()+30,"This month","Upcoming")))))))) -> Upcoming
B92: T086 | C92: Finance | D92: Settle all final vendor balances | E92: Couple | G92: Critical | I92: =WeddingDate+1 -> 46634 | J92: =IF($I92="","",$I92-TODAY()) -> 366 | K92: Not Started | L92: =IF($D92="","",IF($K92="Completed","Done",IF($K92="Cancelled","-",IF($I92="","No date",IF($I92<TODAY(),"OVERDUE",IF($I92=TODAY(),"TODAY",IF($I92<=TODAY()+7,"This week",IF($I92<=TODAY()+30,"This month","Upcoming")))))))) -> Upcoming
B93: T087 | C93: Jewellery | D93: Return rented jewellery and reclaim the deposit | E93: Groom | G93: Critical | I93: =WeddingDate+2 -> 46635 | J93: =IF($I93="","",$I93-TODAY()) -> 367 | K93: Not Started | L93: =IF($D93="","",IF($K93="Completed","Done",IF($K93="Cancelled","-",IF($I93="","No date",IF($I93<TODAY(),"OVERDUE",IF($I93=TODAY(),"TODAY",IF($I93<=TODAY()+7,"This week",IF($I93<=TODAY()+30,"This month","Upcoming")))))))) -> Upcoming
B94: T088 | C94: Logistics | D94: Return rented decor, AV and hired items | E94: Coordinator | G94: High | I94: =WeddingDate+3 -> 46636 | J94: =IF($I94="","",$I94-TODAY()) -> 368 | K94: Not Started | L94: =IF($D94="","",IF($K94="Completed","Done",IF($K94="Cancelled","-",IF($I94="","No date",IF($I94<TODAY(),"OVERDUE",IF($I94=TODAY(),"TODAY",IF($I94<=TODAY()+7,"This week",IF($I94<=TODAY()+30,"This month","Upcoming")))))))) -> Upcoming
B95: T089 | C95: Gifts & Favours | D95: Record every gift received in 09 Guests | E95: Couple | G95: High | I95: =WeddingDate+5 -> 46638 | J95: =IF($I95="","",$I95-TODAY()) -> 370 | K95: Not Started | L95: =IF($D95="","",IF($K95="Completed","Done",IF($K95="Cancelled","-",IF($I95="","No date",IF($I95<TODAY(),"OVERDUE",IF($I95=TODAY(),"TODAY",IF($I95<=TODAY()+7,"This week",IF($I95<=TODAY()+30,"This month","Upcoming")))))))) -> Upcoming
B96: T090 | C96: Attire | D96: Dry-clean and store the saree and suit | E96: Bride | G96: Medium | I96: =WeddingDate+10 -> 46643 | J96: =IF($I96="","",$I96-TODAY()) -> 375 | K96: Not Started | L96: =IF($D96="","",IF($K96="Completed","Done",IF($K96="Cancelled","-",IF($I96="","No date",IF($I96<TODAY(),"OVERDUE",IF($I96=TODAY(),"TODAY",IF($I96<=TODAY()+7,"This week",IF($I96<=TODAY()+30,"This month","Upcoming")))))))) -> Upcoming
B97: T091 | C97: Photography | D97: Follow up on the photo album and video delivery | E97: Couple | G97: Medium | I97: =WeddingDate+30 -> 46663 | J97: =IF($I97="","",$I97-TODAY()) -> 395 | K97: Not Started | L97: =IF($D97="","",IF($K97="Completed","Done",IF($K97="Cancelled","-",IF($I97="","No date",IF($I97<TODAY(),"OVERDUE",IF($I97=TODAY(),"TODAY",IF($I97<=TODAY()+7,"This week",IF($I97<=TODAY()+30,"This month","Upcoming")))))))) -> Upcoming
B98: T092 | C98: Gifts & Favours | D98: Send thank-you cards | E98: Couple | G98: High | I98: =WeddingDate+30 -> 46663 | J98: =IF($I98="","",$I98-TODAY()) -> 395 | K98: Not Started | L98: =IF($D98="","",IF($K98="Completed","Done",IF($K98="Cancelled","-",IF($I98="","No date",IF($I98<TODAY(),"OVERDUE",IF($I98=TODAY(),"TODAY",IF($I98<=TODAY()+7,"This week",IF($I98<=TODAY()+30,"This month","Upcoming")))))))) -> Upcoming
B99: T093 | C99: Finance | D99: Reconcile the final wedding cost (25 Post-Wedding) | E99: Couple | G99: High | I99: =WeddingDate+30 -> 46663 | J99: =IF($I99="","",$I99-TODAY()) -> 395 | K99: Not Started | L99: =IF($D99="","",IF($K99="Completed","Done",IF($K99="Cancelled","-",IF($I99="","No date",IF($I99<TODAY(),"OVERDUE",IF($I99=TODAY(),"TODAY",IF($I99<=TODAY()+7,"This week",IF($I99<=TODAY()+30,"This month","Upcoming")))))))) -> Upcoming
J100: =IF($I100="","",$I100-TODAY()) | L100: =IF($D100="","",IF($K100="Completed","Done",IF($K100="Cancelled","-",IF($I100="","No date",IF($I100<TODAY(),"OVERDUE",IF($I100=TODAY(),"TODAY",IF($I100<=TODAY()+7,"This week",IF($I100<=TODAY()+30,"This month","Upcoming"))))))))
J101: =IF($I101="","",$I101-TODAY()) | L101: =IF($D101="","",IF($K101="Completed","Done",IF($K101="Cancelled","-",IF($I101="","No date",IF($I101<TODAY(),"OVERDUE",IF($I101=TODAY(),"TODAY",IF($I101<=TODAY()+7,"This week",IF($I101<=TODAY()+30,"This month","Upcoming"))))))))
J102: =IF($I102="","",$I102-TODAY()) | L102: =IF($D102="","",IF($K102="Completed","Done",IF($K102="Cancelled","-",IF($I102="","No date",IF($I102<TODAY(),"OVERDUE",IF($I102=TODAY(),"TODAY",IF($I102<=TODAY()+7,"This week",IF($I102<=TODAY()+30,"This month","Upcoming"))))))))
...

Sheet 08 Countdown
B2: FINAL COUNTDOWN CHECKLIST
B3: The last month, day by day, then the day after. Dates recalculate from the wedding date. There is no homecoming, so nothing here refers to one.
D5: ="Completed: "&COUNTIF(F7:F74,"Yes")&" of "&COUNTIF(F7:F74,"<>") -> Completed: 0 of 59
B6: Window | C6: Date | D6: Check | E6: Owner | F6: Done? | G6: Notes
B7: 30 days before | C7: =WeddingDate-30 -> 46603
B8: 30 days before | C8: =WeddingDate-30 -> 46603 | D8: Close the guest list - no more additions after today | E8: Couple | F8: No
B9: 30 days before | C9: =WeddingDate-30 -> 46603 | D9: Give the venue a provisional headcount | E9: Couple | F9: No
B10: 30 days before | C10: =WeddingDate-30 -> 46603 | D10: Confirm every vendor balance and the date each is due | E10: Couple | F10: No
B11: 30 days before | C11: =WeddingDate-30 -> 46603 | D11: Confirm the registrar's attendance in writing | E11: Couple | F11: No
B12: 30 days before | C12: =WeddingDate-30 -> 46603 | D12: Start the seating plan | E12: Couple | F12: No
B13: 30 days before | C13: =WeddingDate-30 -> 46603 | D13: Confirm the Poruwa design and dimensions with the decorator | E13: Couple | F13: No
B14: 21 days before | C14: =WeddingDate-21 -> 46612
B15: 21 days before | C15: =WeddingDate-21 -> 46612 | D15: Build the wedding-day timeline and circulate it to the family | E15: Coordinator | F15: No
B16: 21 days before | C16: =WeddingDate-21 -> 46612 | D16: Confirm arrival, setup and finish times with every vendor | E16: Coordinator | F16: No
B17: 21 days before | C17: =WeddingDate-21 -> 46612 | D17: Confirm vegetarian, child and special meal numbers | E17: Couple | F17: No
B18: 21 days before | C18: =WeddingDate-21 -> 46612 | D18: Final bridal fitting - stop all alterations after this | E18: Bride | F18: No
B19: 21 days before | C19: =WeddingDate-21 -> 46612 | D19: Final groom's fitting | E19: Groom | F19: No
B20: 21 days before | C20: =WeddingDate-21 -> 46612 | D20: Confirm the fresh flower order | E20: Couple | F20: No
B21: 14 days before | C21: =WeddingDate-14 -> 46619
B22: 14 days before | C22: =WeddingDate-14 -> 46619 | D22: Chase every outstanding RSVP by phone | E22: Couple | F22: No
B23: 14 days before | C23: =WeddingDate-14 -> 46619 | D23: Finalise the seating plan and print the seating board | E23: Couple | F23: No
B24: 14 days before | C24: =WeddingDate-14 -> 46619 | D24: Print table numbers and place cards | E24: Couple | F24: No
B25: 14 days before | C25: =WeddingDate-14 -> 46619 | D25: Print the wedding-day contact sheet and timeline | E25: Coordinator | F25: No
B26: 14 days before | C26: =WeddingDate-14 -> 46619 | D26: Confirm the bridal car, family cars and guest buses | E26: Coordinator | F26: No
B27: 14 days before | C27: =WeddingDate-14 -> 46619 | D27: Bride's final facial | E27: Bride | F27: No
B28: 14 days before | C28: =WeddingDate-14 -> 46619 | D28: Confirm the cake design, weight and delivery time | E28: Couple | F28: No
B29: 7 days before | C29: =WeddingDate-7 -> 46626
B30: 7 days before | C30: =WeddingDate-7 -> 46626 | D30: Give the venue the final headcount | E30: Couple | F30: No
B31: 7 days before | C31: =WeddingDate-7 -> 46626 | D31: Collect NICs, birth certificates and registration papers in one folder | E31: Couple | F31: No
B32: 7 days before | C32: =WeddingDate-7 -> 46626 | D32: Groom's haircut | E32: Groom | F32: No
B33: 7 days before | C33: =WeddingDate-7 -> 46626 | D33: Confirm the MC's running order and name pronunciations | E33: Couple | F33: No
B34: 7 days before | C34: =WeddingDate-7 -> 46626 | D34: Give the DJ the must-play and do-not-play list | E34: Couple | F34: No
B35: 7 days before | C35: =WeddingDate-7 -> 46626 | D35: Buy the Poruwa items and check nothing is missing | E35: Groom's Family | F35: No
B36: 7 days before | C36: =WeddingDate-7 -> 46626 | D36: Check the weather forecast and confirm the wet-weather plan | E36: Coordinator | F36: No
B37: 3 days before | C37: =WeddingDate-3 -> 46630
B38: 3 days before | C38: =WeddingDate-3 -> 46630 | D38: Confirm pick-up times with every driver | E38: Coordinator | F38: No
B39: 3 days before | C39: =WeddingDate-3 -> 46630 | D39: Draw the cash needed for tips and day-of payments | E39: Couple | F39: No
B40: 3 days before | C40: =WeddingDate-3 -> 46630 | D40: Bride's nails | E40: Bride | F40: No
B41: 3 days before | C41: =WeddingDate-3 -> 46630 | D41: Brief the bridal party on where to be and when | E41: Bride | F41: No
B42: 3 days before | C42: =WeddingDate-3 -> 46630 | D42: Confirm the photographer's and videographer's arrival times | E42: Couple | F42: No
B43: 2 days before | C43: =WeddingDate-2 -> 46631
B44: 2 days before | C44: =WeddingDate-2 -> 46631 | D44: Pack everything on 23 Procurement & Packing | E44: Couple | F44: No
B45: 2 days before | C45: =WeddingDate-2 -> 46631 | D45: Lay out the saree, suit, shoes and accessories | E45: Couple | F45: No
B46: 2 days before | C46: =WeddingDate-2 -> 46631 | D46: Check the emergency kit is complete | E46: Bride | F46: No
B47: 2 days before | C47: =WeddingDate-2 -> 46631 | D47: Confirm the bridal suite check-in time | E47: Couple | F47: No
B48: 2 days before | C48: =WeddingDate-2 -> 46631 | D48: Rest - no late nights from here | E48: Couple | F48: No
B49: 1 day before | C49: =WeddingDate-1 -> 46632
B50: 1 day before | C50: =WeddingDate-1 -> 46632 | D50: Collect the jewellery from the vault or jeweller | E50: Groom | F50: No
B51: 1 day before | C51: =WeddingDate-1 -> 46632 | D51: Charge every phone, camera and power bank | E51: Couple | F51: No
B52: 1 day before | C52: =WeddingDate-1 -> 46632 | D52: Load the cars - jewellery, documents, emergency kit, gifts, favours | E52: Couple | F52: No
B53: 1 day before | C53: =WeddingDate-1 -> 46632 | D53: Final call to the venue banquet manager | E53: Coordinator | F53: No
B54: 1 day before | C54: =WeddingDate-1 -> 46632 | D54: Hand the timeline and contact sheet to the coordinator | E54: Couple | F54: No
B55: 1 day before | C55: =WeddingDate-1 -> 46632 | D55: Confirm the dresser's arrival time at the bridal suite | E55: Bride | F55: No
B56: 1 day before | C56: =WeddingDate-1 -> 46632 | D56: Eat properly and sleep early | E56: Couple | F56: No
B57: WEDDING DAY | C57: =WeddingDate-0 -> 46633
B58: WEDDING DAY | C58: =WeddingDate-0 -> 46633 | D58: Eat breakfast - both of you | E58: Couple | F58: No
B59: WEDDING DAY | C59: =WeddingDate-0 -> 46633 | D59: Bride's dressing starts on time (see 20 Day Timeline) | E59: Bride | F59: No
B60: WEDDING DAY | C60: =WeddingDate-0 -> 46633 | D60: Hand the ring box to the best man / maid of honour | E60: Couple | F60: No
B61: WEDDING DAY | C61: =WeddingDate-0 -> 46633 | D61: Hand the registration folder to the coordinator | E61: Couple | F61: No
B62: WEDDING DAY | C62: =WeddingDate-0 -> 46633 | D62: Coordinator checks each vendor in on arrival | E62: Coordinator | F62: No
B63: WEDDING DAY | C63: =WeddingDate-0 -> 46633 | D63: Check the Poruwa, stage and cake table before guests arrive | E63: Coordinator | F63: No
B64: WEDDING DAY | C64: =WeddingDate-0 -> 46633 | D64: Assign one person to guard the gift table all evening | E64: Coordinator | F64: No
B65: WEDDING DAY | C65: =WeddingDate-0 -> 46633 | D65: Assign one person to collect the jewellery at the end of the night | E65: Groom's Family | F65: No
B66: WEDDING DAY | C66: =WeddingDate-0 -> 46633 | D66: Pay any day-of balances and tips | E66: Couple | F66: No
B67: Day after | C67: =WeddingDate+1 -> 46634
B68: Day after | C68: =WeddingDate+1 -> 46634 | D68: Collect all personal belongings from the venue and suite | E68: Couple | F68: No
B69: Day after | C69: =WeddingDate+1 -> 46634 | D69: Count and log the gifts received | E69: Couple | F69: No
B70: Day after | C70: =WeddingDate+1 -> 46634 | D70: Settle any remaining vendor balances | E70: Couple | F70: No
B71: Day after | C71: =WeddingDate+1 -> 46634 | D71: Return rented jewellery and reclaim the deposit | E71: Groom | F71: No
B72: Day after | C72: =WeddingDate+1 -> 46634 | D72: Return rented decor, AV and hired items | E72: Coordinator | F72: No
B73: Day after | C73: =WeddingDate+1 -> 46634 | D73: Check out of the hotel and reclaim any room deposit | E73: Couple | F73: No
B74: Day after | C74: =WeddingDate+1 -> 46634 | D74: Thank the vendors and the family who helped | E74: Couple | F74: No

Sheet 09 Guests
B2: GUEST MASTER
B3: Your 84 guest groups have been carried across and structured. One row per household. The cash-gift columns feed the net-cost figure on 01 START HERE.
D5: TOTALS | I5: =SUM(I7:I300) -> 156 | J5: =SUM(J7:J300) -> 0 | K5: =SUM(K7:K300) -> 156 | W5: =SUM(W7:W300) -> 0 | X5: =SUM(X7:X300) -> 0 | Y5: =SUM(Y7:Y300) -> 0 | AE5: =SUM(AE7:AE300) -> 605000 | AF5: =SUM(AF7:AF300) -> 0
B6: ID | C6: Group | D6: Household / guest name | E6: Relationship | F6: Side | G6: Category | H6: VIP? | I6: Adults invited | J6: Children invited | K6: Total invited | L6: Phone | M6: WhatsApp | N6: Email | O6: City | P6: District | Q6: Country | R6: Invitation type | S6: Invitation sent? | T6: Sent on | U6: RSVP | V6: RSVP on | W6: Adults attending | X6: Children attending | Y6: Total attending | Z6: Dietary | AA6: Needs room? | AB6: Needs transport? | AC6: Transport type | AD6: Table # | AE6: Expected cash gift | AF6: Cash gift received | AG6: Gift description | AH6: Thank-you sent? | AI6: Notes
B7: G001 | C7: Family & Relatives | D7: Nayana nanda | F7: Groom | G7: Relatives | I7: 4 | J7: 0 | K7: =IF($D7="","",I7+J7) -> 4 | U7: Pending | Y7: =IF($D7="","",W7+X7) -> 0 | AE7: 10000
B8: G002 | C8: Family & Relatives | D8: Anusha nanda | F8: Groom | G8: Relatives | I8: 4 | J8: 0 | K8: =IF($D8="","",I8+J8) -> 4 | U8: Pending | Y8: =IF($D8="","",W8+X8) -> 0 | AE8: 5000
B9: G003 | C9: Family & Relatives | D9: Rangini Nanda | F9: Groom | G9: Relatives | I9: 3 | J9: 0 | K9: =IF($D9="","",I9+J9) -> 3 | U9: Pending | Y9: =IF($D9="","",W9+X9) -> 0 | AE9: 5000
B10: G004 | C10: Family & Relatives | D10: Udeni akka | F10: Groom | G10: Relatives | I10: 3 | J10: 0 | K10: =IF($D10="","",I10+J10) -> 3 | U10: Pending | Y10: =IF($D10="","",W10+X10) -> 0 | AE10: 5000
B11: G005 | C11: Family & Relatives | D11: sudda | F11: Groom | G11: Relatives | I11: 2 | J11: 0 | K11: =IF($D11="","",I11+J11) -> 2 | U11: Pending | Y11: =IF($D11="","",W11+X11) -> 0 | AE11: 5000
B12: G006 | C12: Family & Relatives | D12: kasun | F12: Groom | G12: Relatives | I12: 1 | J12: 0 | K12: =IF($D12="","",I12+J12) -> 1 | U12: Pending | Y12: =IF($D12="","",W12+X12) -> 0 | AE12: 5000
B13: G007 | C13: Family & Relatives | D13: chuti aunty | F13: Groom | G13: Relatives | I13: 2 | J13: 0 | K13: =IF($D13="","",I13+J13) -> 2 | U13: Pending | Y13: =IF($D13="","",W13+X13) -> 0 | AE13: 5000
B14: G008 | C14: Family & Relatives | D14: namali aunty | F14: Groom | G14: Relatives | I14: 1 | J14: 0 | K14: =IF($D14="","",I14+J14) -> 1 | U14: Pending | Y14: =IF($D14="","",W14+X14) -> 0 | AE14: 5000
B15: G009 | C15: Family & Relatives | D15: darshana uncle | F15: Groom | G15: Relatives | I15: 2 | J15: 0 | K15: =IF($D15="","",I15+J15) -> 2 | U15: Pending | Y15: =IF($D15="","",W15+X15) -> 0 | AE15: 5000
B16: G010 | C16: Family & Relatives | D16: kalu mama | F16: Groom | G16: Relatives | I16: 1 | J16: 0 | K16: =IF($D16="","",I16+J16) -> 1 | U16: Pending | Y16: =IF($D16="","",W16+X16) -> 0 | AE16: 5000
B17: G011 | C17: Family & Relatives | D17: sigithi | F17: Groom | G17: Relatives | I17: 1 | J17: 0 | K17: =IF($D17="","",I17+J17) -> 1 | U17: Pending | Y17: =IF($D17="","",W17+X17) -> 0 | AE17: 5000
B18: G012 | C18: Family & Relatives | D18: jayantha mama(sarath) | F18: Groom | G18: Relatives | I18: 1 | J18: 0 | K18: =IF($D18="","",I18+J18) -> 1 | U18: Pending | Y18: =IF($D18="","",W18+X18) -> 0 | AE18: 5000
... B86: G080 | C86: Friends - IFS | D86: yohan | F86: Groom | G86: Friends / Work | I86: 1 | J86: 0 | K86: =IF($D86="","",I86+J86) -> 1 | U86: Pending | Y86: =IF($D86="","",W86+X86) -> 0 | AE86: 5000
K87: =IF($D87="","",I87+J87) | Y87: =IF($D87="","",W87+X87)
K88: =IF($D88="","",I88+J88) | Y88: =IF($D88="","",W88+X88)
K89: =IF($D89="","",I89+J89) | Y89: =IF($D89="","",W89+X89)
K90: =IF($D90="","",I90+J90) | Y90: =IF($D90="","",W90+X90)
K91: =IF($D91="","",I91+J91) | Y91: =IF($D91="","",W91+X91)
K92: =IF($D92="","",I92+J92) | Y92: =IF($D92="","",W92+X92)
K93: =IF($D93="","",I93+J93) | Y93: =IF($D93="","",W93+X93)
K94: =IF($D94="","",I94+J94) | Y94: =IF($D94="","",W94+X94)
K95: =IF($D95="","",I95+J95) | Y95: =IF($D95="","",W95+X95)
K96: =IF($D96="","",I96+J96) | Y96: =IF($D96="","",W96+X96)
K97: =IF($D97="","",I97+J97) | Y97: =IF($D97="","",W97+X97)
K98: =IF($D98="","",I98+J98) | Y98: =IF($D98="","",W98+X98)
... K300: =IF($D300="","",I300+J300) | Y300: =IF($D300="","",W300+X300)

Sheet 10 RSVP & Seating
B2: RSVP SUMMARY & SEATING PLAN
B3: Everything here reads from 09 Guests. Assign a table number in column AD of 09 Guests and the seat counts below fill in automatically.
B5: RSVP POSITION
B6: Guest groups invited | C6: =COUNTA('09 Guests'!$D$7:$D$300) -> 80 | E6: People invited (pax) | F6: =SUM('09 Guests'!$K$7:$K$300) -> 156
B7: Groups accepted | C7: =COUNTIF('09 Guests'!$U$7:$U$300,"Accepted") -> 0 | E7: People attending (confirmed) | F7: =SUM('09 Guests'!$Y$7:$Y$300) -> 0
B8: Groups declined | C8: =COUNTIF('09 Guests'!$U$7:$U$300,"Declined") -> 0 | E8: Adults attending | F8: =SUM('09 Guests'!$W$7:$W$300) -> 0
B9: Groups pending / no response | C9: =COUNTIF('09 Guests'!$U$7:$U$300,"Pending")+COUNTIF('09 Guests'!$U$7:$U$300,"No Response")+COUNTIF('09 Guests'!$U$7:$U$300,"Maybe") -> 80 | E9: Children attending | F9: =SUM('09 Guests'!$X$7:$X$300) -> 0
B10: RSVP response rate | C10: =IFERROR((COUNTIF('09 Guests'!$U$7:$U$300,"Accepted")+COUNTIF('09 Guests'!$U$7:$U$300,"Declined"))/COUNTA('09 Guests'!$D$7:$D$300),0) -> 0 | E10: Acceptance rate (of those who replied) | F10: =IFERROR(COUNTIF('09 Guests'!$U$7:$U$300,"Accepted")/(COUNTIF('09 Guests'!$U$7:$U$300,"Accepted")+COUNTIF('09 Guests'!$U$7:$U$300,"Declined")),0) -> 0
B11: Bride's side attending | C11: =SUMIFS('09 Guests'!$Y$7:$Y$300,'09 Guests'!$F$7:$F$300,"Bride") -> 0 | E11: Groom's side attending | F11: =SUMIFS('09 Guests'!$Y$7:$Y$300,'09 Guests'!$F$7:$F$300,"Groom") -> 0
B12: VIP guests attending | C12: =SUMIFS('09 Guests'!$Y$7:$Y$300,'09 Guests'!$H$7:$H$300,"Yes") -> 0 | E12: Outstation guests needing a room | F12: =SUMIFS('09 Guests'!$Y$7:$Y$300,'09 Guests'!$AA$7:$AA$300,"Yes") -> 0
B13: Guests needing transport | C13: =SUMIFS('09 Guests'!$Y$7:$Y$300,'09 Guests'!$AB$7:$AB$300,"Yes") -> 0 | E13: Vegetarian meals required | F13: =SUMIFS('09 Guests'!$Y$7:$Y$300,'09 Guests'!$Z$7:$Z$300,"Vegetarian") -> 0
B14: Special / allergy meals | C14: =SUMIFS('09 Guests'!$Y$7:$Y$300,'09 Guests'!$Z$7:$Z$300,"Allergy - see notes") -> 0 | E14: Child meals required | F14: =SUM('09 Guests'!$X$7:$X$300) -> 0
B15: ATTENDING BUT NOT YET SEATED | C15: =SUMIFS('09 Guests'!$Y$7:$Y$300,'09 Guests'!$U$7:$U$300,"Accepted",'09 Guests'!$AD$7:$AD$300,"") -> 0 | E15: Invitations sent but no reply | F15: =COUNTIFS('09 Guests'!$S$7:$S$300,"Yes",'09 Guests'!$U$7:$U$300,"Pending") -> 0
H18: TABLE PLAN | K18: ="Seats laid: "&SUM(J20:J49) -> Seats laid: 298 | M18: ="Seated: "&SUM(K20:K49) -> Seated: 0
H19: Table # | I19: Table type | J19: Capacity | K19: Seated | L19: Free seats | M19: Bride side | N19: Groom side | O19: Warning | P19: Notes
H20: Head Table | I20: Round | J20: 8 | K20: =IF($H20="","",SUMIFS('09 Guests'!$Y$7:$Y$300,'09 Guests'!$AD$7:$AD$300,$H20)) -> 0 | L20: =IF($H20="","",$J20-$K20) -> 8 | M20: =IF($H20="","",SUMIFS('09 Guests'!$Y$7:$Y$300,'09 Guests'!$AD$7:$AD$300,$H20,'09 Guests'!$F$7:$F$300,"Bride")) -> 0 | N20: =IF($H20="","",SUMIFS('09 Guests'!$Y$7:$Y$300,'09 Guests'!$AD$7:$AD$300,$H20,'09 Guests'!$F$7:$F$300,"Groom")) -> 0 | O20: =IF($H20="","",IF($K20>$J20,"OVER CAPACITY",IF($K20=0,"Empty","OK"))) -> Empty
H21: Family Table 1 | I21: Round | J21: 10 | K21: =IF($H21="","",SUMIFS('09 Guests'!$Y$7:$Y$300,'09 Guests'!$AD$7:$AD$300,$H21)) -> 0 | L21: =IF($H21="","",$J21-$K21) -> 10 | M21: =IF($H21="","",SUMIFS('09 Guests'!$Y$7:$Y$300,'09 Guests'!$AD$7:$AD$300,$H21,'09 Guests'!$F$7:$F$300,"Bride")) -> 0 | N21: =IF($H21="","",SUMIFS('09 Guests'!$Y$7:$Y$300,'09 Guests'!$AD$7:$AD$300,$H21,'09 Guests'!$F$7:$F$300,"Groom")) -> 0 | O21: =IF($H21="","",IF($K21>$J21,"OVER CAPACITY",IF($K21=0,"Empty","OK"))) -> Empty
H22: Family Table 2 | I22: Round | J22: 10 | K22: =IF($H22="","",SUMIFS('09 Guests'!$Y$7:$Y$300,'09 Guests'!$AD$7:$AD$300,$H22)) -> 0 | L22: =IF($H22="","",$J22-$K22) -> 10 | M22: =IF($H22="","",SUMIFS('09 Guests'!$Y$7:$Y$300,'09 Guests'!$AD$7:$AD$300,$H22,'09 Guests'!$F$7:$F$300,"Bride")) -> 0 | N22: =IF($H22="","",SUMIFS('09 Guests'!$Y$7:$Y$300,'09 Guests'!$AD$7:$AD$300,$H22,'09 Guests'!$F$7:$F$300,"Groom")) -> 0 | O22: =IF($H22="","",IF($K22>$J22,"OVER CAPACITY",IF($K22=0,"Empty","OK"))) -> Empty
H23: VIP Table | I23: Round | J23: 10 | K23: =IF($H23="","",SUMIFS('09 Guests'!$Y$7:$Y$300,'09 Guests'!$AD$7:$AD$300,$H23)) -> 0 | L23: =IF($H23="","",$J23-$K23) -> 10 | M23: =IF($H23="","",SUMIFS('09 Guests'!$Y$7:$Y$300,'09 Guests'!$AD$7:$AD$300,$H23,'09 Guests'!$F$7:$F$300,"Bride")) -> 0 | N23: =IF($H23="","",SUMIFS('09 Guests'!$Y$7:$Y$300,'09 Guests'!$AD$7:$AD$300,$H23,'09 Guests'!$F$7:$F$300,"Groom")) -> 0 | O23: =IF($H23="","",IF($K23>$J23,"OVER CAPACITY",IF($K23=0,"Empty","OK"))) -> Empty
H24: Bridal Party | I24: Round | J24: 10 | K24: =IF($H24="","",SUMIFS('09 Guests'!$Y$7:$Y$300,'09 Guests'!$AD$7:$AD$300,$H24)) -> 0 | L24: =IF($H24="","",$J24-$K24) -> 10 | M24: =IF($H24="","",SUMIFS('09 Guests'!$Y$7:$Y$300,'09 Guests'!$AD$7:$AD$300,$H24,'09 Guests'!$F$7:$F$300,"Bride")) -> 0 | N24: =IF($H24="","",SUMIFS('09 Guests'!$Y$7:$Y$300,'09 Guests'!$AD$7:$AD$300,$H24,'09 Guests'!$F$7:$F$300,"Groom")) -> 0 | O24: =IF($H24="","",IF($K24>$J24,"OVER CAPACITY",IF($K24=0,"Empty","OK"))) -> Empty
H25: Table 1 | I25: Round | J25: 10 | K25: =IF($H25="","",SUMIFS('09 Guests'!$Y$7:$Y$300,'09 Guests'!$AD$7:$AD$300,$H25)) -> 0 | L25: =IF($H25="","",$J25-$K25) -> 10 | M25: =IF($H25="","",SUMIFS('09 Guests'!$Y$7:$Y$300,'09 Guests'!$AD$7:$AD$300,$H25,'09 Guests'!$F$7:$F$300,"Bride")) -> 0 | N25: =IF($H25="","",SUMIFS('09 Guests'!$Y$7:$Y$300,'09 Guests'!$AD$7:$AD$300,$H25,'09 Guests'!$F$7:$F$300,"Groom")) -> 0 | O25: =IF($H25="","",IF($K25>$J25,"OVER CAPACITY",IF($K25=0,"Empty","OK"))) -> Empty
H26: Table 2 | I26: Round | J26: 10 | K26: =IF($H26="","",SUMIFS('09 Guests'!$Y$7:$Y$300,'09 Guests'!$AD$7:$AD$300,$H26)) -> 0 | L26: =IF($H26="","",$J26-$K26) -> 10 | M26: =IF($H26="","",SUMIFS('09 Guests'!$Y$7:$Y$300,'09 Guests'!$AD$7:$AD$300,$H26,'09 Guests'!$F$7:$F$300,"Bride")) -> 0 | N26: =IF($H26="","",SUMIFS('09 Guests'!$Y$7:$Y$300,'09 Guests'!$AD$7:$AD$300,$H26,'09 Guests'!$F$7:$F$300,"Groom")) -> 0 | O26: =IF($H26="","",IF($K26>$J26,"OVER CAPACITY",IF($K26=0,"Empty","OK"))) -> Empty
H27: Table 3 | I27: Round | J27: 10 | K27: =IF($H27="","",SUMIFS('09 Guests'!$Y$7:$Y$300,'09 Guests'!$AD$7:$AD$300,$H27)) -> 0 | L27: =IF($H27="","",$J27-$K27) -> 10 | M27: =IF($H27="","",SUMIFS('09 Guests'!$Y$7:$Y$300,'09 Guests'!$AD$7:$AD$300,$H27,'09 Guests'!$F$7:$F$300,"Bride")) -> 0 | N27: =IF($H27="","",SUMIFS('09 Guests'!$Y$7:$Y$300,'09 Guests'!$AD$7:$AD$300,$H27,'09 Guests'!$F$7:$F$300,"Groom")) -> 0 | O27: =IF($H27="","",IF($K27>$J27,"OVER CAPACITY",IF($K27=0,"Empty","OK"))) -> Empty
H28: Table 4 | I28: Round | J28: 10 | K28: =IF($H28="","",SUMIFS('09 Guests'!$Y$7:$Y$300,'09 Guests'!$AD$7:$AD$300,$H28)) -> 0 | L28: =IF($H28="","",$J28-$K28) -> 10 | M28: =IF($H28="","",SUMIFS('09 Guests'!$Y$7:$Y$300,'09 Guests'!$AD$7:$AD$300,$H28,'09 Guests'!$F$7:$F$300,"Bride")) -> 0 | N28: =IF($H28="","",SUMIFS('09 Guests'!$Y$7:$Y$300,'09 Guests'!$AD$7:$AD$300,$H28,'09 Guests'!$F$7:$F$300,"Groom")) -> 0 | O28: =IF($H28="","",IF($K28>$J28,"OVER CAPACITY",IF($K28=0,"Empty","OK"))) -> Empty
H29: Table 5 | I29: Round | J29: 10 | K29: =IF($H29="","",SUMIFS('09 Guests'!$Y$7:$Y$300,'09 Guests'!$AD$7:$AD$300,$H29)) -> 0 | L29: =IF($H29="","",$J29-$K29) -> 10 | M29: =IF($H29="","",SUMIFS('09 Guests'!$Y$7:$Y$300,'09 Guests'!$AD$7:$AD$300,$H29,'09 Guests'!$F$7:$F$300,"Bride")) -> 0 | N29: =IF($H29="","",SUMIFS('09 Guests'!$Y$7:$Y$300,'09 Guests'!$AD$7:$AD$300,$H29,'09 Guests'!$F$7:$F$300,"Groom")) -> 0 | O29: =IF($H29="","",IF($K29>$J29,"OVER CAPACITY",IF($K29=0,"Empty","OK"))) -> Empty
H30: Table 6 | I30: Round | J30: 10 | K30: =IF($H30="","",SUMIFS('09 Guests'!$Y$7:$Y$300,'09 Guests'!$AD$7:$AD$300,$H30)) -> 0 | L30: =IF($H30="","",$J30-$K30) -> 10 | M30: =IF($H30="","",SUMIFS('09 Guests'!$Y$7:$Y$300,'09 Guests'!$AD$7:$AD$300,$H30,'09 Guests'!$F$7:$F$300,"Bride")) -> 0 | N30: =IF($H30="","",SUMIFS('09 Guests'!$Y$7:$Y$300,'09 Guests'!$AD$7:$AD$300,$H30,'09 Guests'!$F$7:$F$300,"Groom")) -> 0 | O30: =IF($H30="","",IF($K30>$J30,"OVER CAPACITY",IF($K30=0,"Empty","OK"))) -> Empty
H31: Table 7 | I31: Round | J31: 10 | K31: =IF($H31="","",SUMIFS('09 Guests'!$Y$7:$Y$300,'09 Guests'!$AD$7:$AD$300,$H31)) -> 0 | L31: =IF($H31="","",$J31-$K31) -> 10 | M31: =IF($H31="","",SUMIFS('09 Guests'!$Y$7:$Y$300,'09 Guests'!$AD$7:$AD$300,$H31,'09 Guests'!$F$7:$F$300,"Bride")) -> 0 | N31: =IF($H31="","",SUMIFS('09 Guests'!$Y$7:$Y$300,'09 Guests'!$AD$7:$AD$300,$H31,'09 Guests'!$F$7:$F$300,"Groom")) -> 0 | O31: =IF($H31="","",IF($K31>$J31,"OVER CAPACITY",IF($K31=0,"Empty","OK"))) -> Empty
... H49: Table 25 | I49: Round | J49: 10 | K49: =IF($H49="","",SUMIFS('09 Guests'!$Y$7:$Y$300,'09 Guests'!$AD$7:$AD$300,$H49)) -> 0 | L49: =IF($H49="","",$J49-$K49) -> 10 | M49: =IF($H49="","",SUMIFS('09 Guests'!$Y$7:$Y$300,'09 Guests'!$AD$7:$AD$300,$H49,'09 Guests'!$F$7:$F$300,"Bride")) -> 0 | N49: =IF($H49="","",SUMIFS('09 Guests'!$Y$7:$Y$300,'09 Guests'!$AD$7:$AD$300,$H49,'09 Guests'!$F$7:$F$300,"Groom")) -> 0 | O49: =IF($H49="","",IF($K49>$J49,"OVER CAPACITY",IF($K49=0,"Empty","OK"))) -> Empty

Sheet 11 Wedding Party
B2: WEDDING PARTY & KEY PEOPLE
B3: Everyone with a job on the day. 'Be at venue by' feeds nothing automatically - copy the times into 20 Day Timeline so there is one version of the truth.
B6: Role | C6: Name | D6: Phone | E6: WhatsApp | F6: Side | G6: Outfit / what to wear | H6: Outfit ready? | I6: Accessories | J6: Responsibilities on the day | K6: Be at venue by | L6: Transport | M6: Room needed? | N6: Gift given? | O6: Notes
B7: Bride | F7: Bride
B8: Groom | F8: Groom
B9: Bride's father | F9: Bride
B10: Bride's mother | F10: Bride
B11: Groom's father | F11: Groom
B12: Groom's mother | F12: Groom
B13: Maid / Matron of Honour | F13: Bride
B14: Best Man | F14: Groom
B15: Bridesmaid 1 | F15: Bride
B16: Bridesmaid 2 | F16: Bride
B17: Bridesmaid 3 | F17: Bride
B18: Groomsman 1 | F18: Groom
... B34: Speech - speaker 2 | F34: Bride

Sheet 12 Attire & Jewellery
B2: ATTIRE & JEWELLERY
B3: Two registers. The jewellery register is a security document - fill in who holds each item and when it must go back.
B5: ATTIRE REGISTER
B6: Who | C6: Item | D6: Required? | E6: Shop / designer | F6: Fitting 1 | G6: Fitting 2 | H6: Final fitting | I6: Alterations? | J6: Collect by | K6: Cost | L6: Paid | M6: Status | N6: Notes
B7: Bride | C7: Kandyan / Poruwa saree (osari) | D7: Required | M7: Not Started
B8: Bride | C8: Saree blouse | D8: Required | M8: Not Started
B9: Bride | C9: Reception / going-away outfit | D9: Optional | M9: Not Started
B10: Bride | C10: Bridal shoes | D10: Required | M10: Not Started
B11: Bride | C11: Veil | D11: Optional | M11: Not Started
B12: Bride | C12: Undergarments & shapewear | D12: Required | M12: Not Started
B13: Bride | C13: Saree pins, falls and petticoat | D13: Required | M13: Not Started
B14: Groom | C14: Wedding suit / national dress | D14: Required | M14: Not Started
B15: Groom | C15: Shirt | D15: Required | M15: Not Started
B16: Groom | C16: Tie / bow tie | D16: Required | M16: Not Started
B17: Groom | C17: Shoes | D17: Required | M17: Not Started
B18: Groom | C18: Belt | D18: Required | M18: Not Started
... B33: Groom's father | C33: Suit / national dress | D33: Required | M33: Not Started
B41: JEWELLERY REGISTER - security document | F41: =SUM(F43:F60) -> 0
B42: Item | C42: Description | D42: Owner / source | E42: Bought / rented | F42: Value (LKR) | G42: Deposit paid | H42: Stored where | I42: Who is responsible | J42: Collect on | K42: Return by | L42: Returned? | M42: Deposit back? | N42: Notes
B43: Bridal necklace set | L43: N/A
B44: Earrings | L44: N/A
B45: Bangles | L45: N/A
B46: Nalalpata (forehead ornament) | L46: N/A
B47: Konda mal / hair jewellery | L47: N/A
B48: Waist chain (hawadiya) | L48: N/A
B49: Anklets | L49: N/A
B50: Bride's wedding ring | L50: N/A
B51: Groom's wedding ring | L51: N/A
B52: Engagement ring | L52: N/A
B53: Groom's chain | L53: N/A
B54: Bride's mother's jewellery | L54: N/A
B55: Borrowed family heirloom | L55: N/A

Sheet 13 Beauty & Grooming
B2: BEAUTY & GROOMING SCHEDULE
B3: Dates count back from the wedding date. Nothing new on the face within 7 days of the wedding - keep the last week to touch-ups only.
B6: Who | C6: Treatment / appointment | D6: Required? | E6: Provider | F6: Date | G6: Time | H6: Location | I6: Duration | J6: Cost | K6: Paid? | L6: Status | M6: Notes
B7: Bride | C7: Skin consultation with a dermatologist / salon | D7: Optional | F7: =WeddingDate-180 -> 46453 | L7: Not Started
B8: Bride | C8: Facial course - session 1 | D8: Required | F8: =WeddingDate-150 -> 46483 | L8: Not Started
B9: Bride | C9: Facial course - session 2 | D9: Required | F9: =WeddingDate-120 -> 46513 | L9: Not Started
B10: Bride | C10: Hair treatment / trim | D10: Optional | F10: =WeddingDate-110 -> 46523 | L10: Not Started
B11: Bride | C11: Makeup and hair trial (wear the trial for a full evening) | D11: Required | F11: =WeddingDate-100 -> 46533 | L11: Not Started
B12: Bride | C12: Facial course - session 3 | D12: Required | F12: =WeddingDate-90 -> 46543 | L12: Not Started
B13: Bride | C13: Second makeup trial if the first was not right | D13: Optional | F13: =WeddingDate-70 -> 46563 | L13: Not Started
B14: Bride | C14: Facial course - session 4 | D14: Required | F14: =WeddingDate-45 -> 46588 | L14: Not Started
B15: Bride | C15: Hair colour / gloss | D15: Optional | F15: =WeddingDate-30 -> 46603 | L15: Not Started
B16: Bride | C16: Final facial - nothing new after this | D16: Required | F16: =WeddingDate-14 -> 46619 | L16: Not Started
B17: Bride | C17: Threading / waxing | D17: Required | F17: =WeddingDate-7 -> 46626 | L17: Not Started
B18: Bride | C18: Manicure and pedicure | D18: Required | F18: =WeddingDate-3 -> 46630 | L18: Not Started
B19: Bride | C19: WEDDING DAY - dresser arrives, hair & makeup | D19: Required | F19: =WeddingDate-0 -> 46633 | L19: Not Started
B20: Groom | C20: Facial / grooming treatment | D20: Optional | F20: =WeddingDate-30 -> 46603 | L20: Not Started
B21: Groom | C21: Haircut - practice cut | D21: Optional | F21: =WeddingDate-21 -> 46612 | L21: Not Started
B22: Groom | C22: Haircut - final | D22: Required | F22: =WeddingDate-5 -> 46628 | L22: Not Started
B23: Groom | C23: Beard shape / clean shave | D23: Required | F23: =WeddingDate-1 -> 46632 | L23: Not Started
B24: Groom | C24: WEDDING DAY - grooming and dressing | D24: Required | F24: =WeddingDate-0 -> 46633 | L24: Not Started
B25: Bridesmaids | C25: Hair & makeup trial (optional, group booking) | D25: Optional | F25: =WeddingDate-45 -> 46588 | L25: Not Started
B26: Bridesmaids | C26: WEDDING DAY - hair & makeup | D26: Required | F26: =WeddingDate-0 -> 46633 | L26: Not Started
B27: Bride's mother | C27: WEDDING DAY - hair & makeup | D27: Required | F27: =WeddingDate-0 -> 46633 | L27: Not Started
B28: Groom's mother | C28: WEDDING DAY - hair & makeup | D28: Required | F28: =WeddingDate-0 -> 46633 | L28: Not Started

Sheet 14 Ceremony & Legal
B2: CEREMONY COMPONENTS & LEGAL REGISTRATION
B3: Switch components on or off in the 'Applies?' column - nothing is assumed. Items marked VERIFY must be confirmed with your Registrar / Divisional Secretariat.
B5: CEREMONY RUNNING ORDER | J5: ="Active minutes: "&SUMIFS(J7:J30,D7:D30,"Required") -> Active minutes: 93
B6: Order | C6: Component | D6: Applies? | E6: Time | F6: Location | G6: Who leads | H6: Items needed | I6: Vendor | J6: Duration (min) | K6: Status | L6: Notes
B7: 1 | C7: Guests seated, Hewisi drummers at the entrance | D7: Required | F7: Ballroom | G7: Coordinator | H7: Drums, seating ushers | J7: 10 | K7: Not Started
B8: 2 | C8: Kandyan dancers lead the groom's procession in | D8: Required | F8: Ballroom | G8: Vendor | H8: Dance troupe, drummers | J8: 5 | K8: Not Started
B9: 3 | C9: Groom takes his place at the Poruwa | D9: Required | F9: Poruwa | G9: Groom | H9: - | J9: 2 | K9: Not Started
B10: 4 | C10: Bride enters with her father / brother | D10: Required | F10: Ballroom | G10: Bride's Family | H10: Bouquet, veil | J10: 3 | K10: Not Started
B11: 5 | C11: Couple step onto the Poruwa - right foot first | D11: Required | F11: Poruwa | G11: Vendor | H11: Poruwa, white cloth | J11: 2 | K11: Not Started
B12: 6 | C12: Ashtaka chanting | D12: Required | F12: Poruwa | G12: Vendor | H12: Ashtaka chanter | J12: 5 | K12: Not Started
B13: 7 | C13: Betel leaves offered to the four corners | D13: Required | F13: Poruwa | G13: Vendor | H13: Bulath thattuwa (betel tray) | J13: 3 | K13: Not Started
B14: 8 | C14: Exchange of rings | D14: Required | F14: Poruwa | G14: Couple | H14: Ring box, ring bearer | J14: 3 | K14: Not Started
B15: 9 | C15: Bride's little finger tied to groom's with gold thread | D15: Required | F15: Poruwa | G15: Vendor | H15: Gold thread | J15: 2 | K15: Not Started
B16: 10 | C16: Water poured over the tied hands | D16: Required | F16: Poruwa | G16: Vendor | H16: Kalasa pot, water | J16: 2 | K16: Not Started
B17: 11 | C17: Jayamangala Gatha sung | D17: Required | F17: Poruwa | G17: Vendor | H17: Singers | J17: 4 | K17: Not Started
B18: 12 | C18: Groom gifts the white cloth to the bride's mother | D18: Required | F18: Poruwa | G18: Groom | H18: White cloth | J18: 2 | K18: Not Started
... B30: 24 | C30: Recessional - couple exit | D30: Required | F30: Ballroom | G30: Couple | H30: - | J30: 3 | K30: Not Started
B36: MARRIAGE REGISTRATION CHECKLIST - VERIFY EVERY ITEM WITH YOUR REGISTRAR
B37: # | C37: Requirement | D37: Applies? | E37: Who is responsible | F37: Documents needed | G37: Where / office | H37: Target date | I37: Done on | J37: Status | K37: VERIFY? | L37: Notes
B38: 1 | C38: Confirm which registrar covers your venue's division | D38: Required | E38: Couple | F38: Venue address | G38: Divisional Secretariat | H38: =WeddingDate-200 -> 46433 | J38: Not Started | K38: VERIFY
B39: 2 | C39: Confirm the fee schedule for a registrar attending the venue | D39: Required | E39: Couple | F39: - | G39: Registrar | H39: =WeddingDate-200 -> 46433 | J39: Not Started | K39: VERIFY
B40: 3 | C40: Give notice of marriage | D40: Required | E40: Couple | F40: NICs / passports, birth certificates | G40: Registrar's office | H40: =WeddingDate-90 -> 46543 | J40: Not Started | K40: VERIFY
B41: 4 | C41: Pay the notice fee and keep the receipt | D41: Required | E41: Couple | F41: Receipt | G41: Registrar's office | H41: =WeddingDate-90 -> 46543 | J41: Not Started | K41: No
B42: 5 | C42: Confirm the waiting period before the marriage may be registered | D42: Required | E42: Couple | F42: - | G42: Registrar | H42: =WeddingDate-90 -> 46543 | J42: Not Started | K42: VERIFY
B43: 6 | C43: Confirm the registrar's attendance at the venue in writing | D43: Required | E43: Couple | F43: Written confirmation | G43: Registrar | H43: =WeddingDate-85 -> 46548 | J43: Not Started | K43: No
B44: 7 | C44: Identify two witnesses aged 18+ with valid NICs | D44: Required | E44: Couple | F44: Witness NICs | G44: - | H44: =WeddingDate-80 -> 46553 | J44: Not Started | K44: VERIFY
B45: 8 | C45: Check both NICs / passports are valid and names match the birth certificates | D45: Required | E45: Couple | F45: NIC, passport, birth certificate | G45: - | H45: =WeddingDate-80 -> 46553 | J45: Not Started | K45: No
B46: 9 | C46: Obtain certified English translations if any document is not in Sinhala/Tamil/English | D46: Required | E46: Couple | F46: Original + translation | G46: Registrar / translator | H46: =WeddingDate-75 -> 46558 | J46: Not Started | K46: VERIFY
B47: 10 | C47: If either party was previously married - obtain the divorce decree or death certificate | D47: Required | E47: Couple | F47: Decree absolute / death certificate | G47: Courts | H47: =WeddingDate-120 -> 46513 | J47: Not Started | K47: VERIFY
B48: 11 | C48: If either party is a foreign national - confirm the additional documents required | D48: Required | E48: Couple | F48: Passport, certificate of no impediment | G48: Registrar / Embassy | H48: =WeddingDate-150 -> 46483 | J48: Not Started | K48: VERIFY
B49: 12 | C49: Confirm whether the General or Kandyan marriage law applies to you | D49: Required | E49: Couple | F49: - | G49: Registrar | H49: =WeddingDate-150 -> 46483 | J49: Not Started | K49: VERIFY
B50: 13 | C50: Confirm any religious registration requirement (Muslim / other) | D50: Required | E50: Couple | F50: - | G50: Relevant registrar | H50: =WeddingDate-150 -> 46483 | J50: Not Started | K50: VERIFY
B51: 14 | C51: Assemble every document in ONE labelled folder | D51: Required | E51: Couple | F51: All of the above | G51: - | H51: =WeddingDate-7 -> 46626 | J51: Not Started | K51: No
B52: 15 | C52: Hand the folder to the coordinator on the morning | D52: Required | E52: Couple | F52: Folder | G52: Venue | H52: =WeddingDate-0 -> 46633 | J52: Not Started | K52: No
B53: 16 | C53: Apply for certified copies of the marriage certificate | D53: Required | E53: Couple | F53: Registration reference | G53: Registrar's office | H53: =WeddingDate+14 -> 46647 | J53: Not Started | K53: VERIFY
B54: 17 | C54: Update NIC, passport and bank records if changing name | D54: Required | E54: Bride | F54: Marriage certificate | G54: Relevant offices | H54: =WeddingDate+60 -> 46693 | J54: Not Started | K54: VERIFY

Sheet 15 Decor & Design
B2: DECOR & DESIGN CHECKLIST
B3: Every physical item that has to appear in the room, who brings it, and when it goes up and comes down. Print this for the decorator on setup day.
B6: Area | C6: Item | D6: Applies? | E6: Qty | F6: Supplier | G6: Cost | H6: Setup by | I6: Remove after | J6: Responsible | K6: Checked on the day? | L6: Status | M6: Notes
B7: Entrance | C7: Welcome arch / entrance decoration | D7: Required | E7: 1
B8: Entrance | C8: Welcome board with the couple's names | D8: Required | E8: 1
B9: Entrance | C9: Directional signage from the car park | D9: Required | E9: 2
B10: Entrance | C10: Oil lamp (pahana) at the door | D10: Required | E10: 1
B11: Welcome area | C11: Guest book and pen table | D11: Required | E11: 1
B12: Welcome area | C12: Gift table (with a lockable box) | D12: Required | E12: 1
B13: Welcome area | C13: Seating chart board | D13: Required | E13: 1
B14: Welcome area | C14: Welcome drinks station decor | D14: Required | E14: 1
B15: Ceremony | C15: PORUWA structure | D15: Required | E15: 1
B16: Ceremony | C16: Poruwa floral decoration | D16: Required | E16: 1
B17: Ceremony | C17: White cloth for the Poruwa steps | D17: Required | E17: 1
B18: Ceremony | C18: Kalasa pots | D18: Required | E18: 2
... B46: Extras | C46: Wet-weather cover (check the forecast) | D46: Optional | E46: 1

Sheet 16 Food & Beverage
B2: FOOD, BEVERAGE & CAKE
B3: Headcounts pull from 09 Guests so the catering number is never out of date. Confirm the final number with the venue 3 days out.
B5: HEADCOUNT (live from 09 Guests)
B6: Adults invited | C6: =SUM('09 Guests'!$I$7:$I$300) -> 156 | E6: Adults confirmed | F6: =SUM('09 Guests'!$W$7:$W$300) -> 0
B7: Children invited | C7: =SUM('09 Guests'!$J$7:$J$300) -> 0 | E7: Children confirmed | F7: =SUM('09 Guests'!$X$7:$X$300) -> 0
B8: TOTAL invited | C8: =SUM('09 Guests'!$K$7:$K$300) -> 156 | E8: TOTAL confirmed | F8: =SUM('09 Guests'!$Y$7:$Y$300) -> 0
B9: Vegetarian meals | C9: =SUMIFS('09 Guests'!$Y$7:$Y$300,'09 Guests'!$Z$7:$Z$300,"Vegetarian") -> 0 | E9: Vegan meals | F9: =SUMIFS('09 Guests'!$Y$7:$Y$300,'09 Guests'!$Z$7:$Z$300,"Vegan") -> 0
B10: Halal meals | C10: =SUMIFS('09 Guests'!$Y$7:$Y$300,'09 Guests'!$Z$7:$Z$300,"Halal") -> 0 | E10: No pork / no beef | F10: =SUMIFS('09 Guests'!$Y$7:$Y$300,'09 Guests'!$Z$7:$Z$300,"No Pork")+SUMIFS('09 Guests'!$Y$7:$Y$300,'09 Guests'!$Z$7:$Z$300,"No Beef") -> 0
B11: Allergy meals - check notes | C11: =SUMIFS('09 Guests'!$Y$7:$Y$300,'09 Guests'!$Z$7:$Z$300,"Allergy - see notes") -> 0 | E11: Child meals | F11: =SUM('09 Guests'!$X$7:$X$300) -> 0
B12: Vendor & crew meals (enter manually) | C12: 12 | E12: CATER FOR (confirmed + crew + 5% buffer) | F12: =ROUNDUP(SUM('09 Guests'!$Y$7:$Y$300)*1.05,0)+C12 -> 12
B14: WEDDING CAKE | H14: MENU & SERVICE
B15: Baker / vendor | H15: Course / service | I15: Item | J15: Applies? | K15: Confirmed with caterer? | L15: Serve at | M15: Notes
B16: Design / style | H16: Welcome | I16: Welcome drinks (non-alcoholic) | J16: Required | K16: No
B17: Flavour | H17: Welcome | I17: Welcome drinks (alcoholic) | J17: Optional | K17: No
B18: Number of tiers | C18: 3 | H18: Welcome | I18: Canapes / short eats passed around | J18: Required | K18: No
B19: Total weight (kg) | C19: 8 | H19: Ceremony | I19: Kiribath and sweets for the Poruwa | J19: Required | K19: No
B20: Number of slices needed | C20: =F12 -> 12 | H20: Buffet | I20: Rice - white / yellow / basmati | J20: Required | K20: No
B21: Boxed pieces for guests? | C21: Yes | H21: Buffet | I21: Chicken curry | J21: Required | K21: No
B22: Cake stand arranged? | C22: No | H22: Buffet | I22: Fish / seafood dish | J22: Required | K22: No
B23: Cake knife arranged? | C23: No | H23: Buffet | I23: Beef or mutton dish | J23: Optional | K23: No
B24: Cake topper | H24: Buffet | I24: Vegetarian mains (at least 3) | J24: Required | K24: No
B25: Delivery time to venue | C25: 0.66666667 | H25: Buffet | I25: Dhal, mallum, papadam, chutney | J25: Required | K25: No
B26: Setup complete by | C26: 0.72916667 | H26: Buffet | I26: Noodles / pasta / western option | J26: Optional | K26: No
B27: Cutting time | C27: 0.89583333 | H27: Buffet | I27: Salad bar | J27: Required | K27: No
B28: Cost | C28: 0 | H28: Buffet | I28: Live cooking station (hoppers / kottu) | J28: Optional | K28: No
B29: Deposit paid | C29: 0 | H29: Buffet | I29: Bread and butter | J29: Required | K29: No
B30: Final confirmation date | C30: =WeddingDate-40 -> 46593 | H30: Dessert | I30: Watalappan | J30: Required | K30: No
B31: Notes | H31: Dessert | I31: Curd and treacle | J31: Optional | K31: No
H32: Dessert | I32: Ice cream / western desserts | J32: Required | K32: No
H33: Dessert | I33: Fresh fruit | J33: Required | K33: No
H34: Dessert | I34: Wedding cake pieces | J34: Required | K34: No
H35: Beverage | I35: Bottled water on every table | J35: Required | K35: No
H36: Beverage | I36: Soft drinks | J36: Required | K36: No
H37: Beverage | I37: Fresh juice | J37: Optional | K37: No
H38: Beverage | I38: Tea / coffee station | J38: Required | K38: No
H39: Beverage | I39: Beer / arrack / spirits | J39: Optional | K39: No
H40: Beverage | I40: Wine | J40: Optional | K40: No
H41: Service | I41: Children's meals | J41: Required | K41: No
H42: Service | I42: Vendor and crew meals | J42: Required | K42: No
H43: Service | I43: Head table served first | J43: Required | K43: No
... H45: Service | I45: Take-away boxes for the family | J45: Optional | K45: No

Sheet 17 Transport & Stay
B2: TRANSPORT & ACCOMMODATION
B3: Two registers: every vehicle movement on the day, and every room booked. Print the transport table for the drivers.
B5: TRANSPORT - WEDDING DAY MOVEMENTS
B6: Leg | C6: Vehicle / type | D6: Applies? | E6: Driver | F6: Driver phone | G6: Passengers | H6: Pick up from | I6: Pick up at | J6: Destination | K6: Arrive by | L6: Return trip? | M6: Cost | N6: Paid? | O6: Backup contact | P6: Notes
B7: Dresser to bridal suite | C7: Van | D7: Required | I7: 0.54166667 | K7: 0.66666667
B8: Photographer to bridal suite | C8: Car | D8: Required | I8: 0.60416667 | K8: 0.625
B9: Bride's family to venue | C9: Car | D9: Required | I9: 0.70833333 | K9: 0.73958333
B10: Groom's family to venue | C10: Car | D10: Required | I10: 0.70833333 | K10: 0.73958333
B11: Groom to venue | C11: Car | D11: Required | I11: 0.72916667 | K11: 0.75
B12: Bride to venue (bridal car) | C12: Decorated car | D12: Required | I12: 0.76041667 | K12: 0.78125
B13: Bridal party to venue | C13: Van | D13: Required | I13: 0.72916667 | K13: 0.75
B14: Guest bus - pick-up point 1 | C14: Bus | D14: Required | I14: 0.70833333 | K14: 0.77083333
B15: Guest bus - pick-up point 2 | C15: Bus | D15: Optional | I15: 0.70833333 | K15: 0.77083333
B16: Kandyan dancers & drummers | C16: Van | D16: Required | I16: 0.70833333 | K16: 0.75
B17: Registrar to venue | C17: Car | D17: Required | I17: 0.78125 | K17: 0.80208333
B18: Cake delivery | C18: Van | D18: Required | I18: 0.64583333 | K18: 0.66666667
... B23: Jewellery back to safe custody | C23: Car | D23: Required | I23: 0.98958333 | K23: 0.020833333
B24: Airport transfer - overseas guests | C24: Van | D24: Optional
B33: ACCOMMODATION | J33: =SUM(J35:J54) -> 0
B34: Guest / party | C34: Hotel | D34: Room type | E34: Room # | F34: Check in | G34: Check out | H34: Nights | I34: Rate per night | J34: Total | K34: Paid by | L34: Booking reference | M34: Confirmed? | N34: Special requests | O34: Transport needed? | P34: Notes
B35: Bride & Groom - bridal suite | D35: Suite | H35: =IF(OR(F35="",G35=""),"",G35-F35) | J35: =IF(H35="","",H35*I35) | M35: No
B36: Bride - getting ready | D36: Deluxe | H36: =IF(OR(F36="",G36=""),"",G36-F36) | J36: =IF(H36="","",H36*I36) | M36: No
B37: Groom - getting ready | D37: Deluxe | H37: =IF(OR(F37="",G37=""),"",G37-F37) | J37: =IF(H37="","",H37*I37) | M37: No
B38: Bride's parents | D38: Double | H38: =IF(OR(F38="",G38=""),"",G38-F38) | J38: =IF(H38="","",H38*I38) | M38: No
B39: Groom's parents | D39: Double | H39: =IF(OR(F39="",G39=""),"",G39-F39) | J39: =IF(H39="","",H39*I39) | M39: No
B40: Bride's siblings | D40: Double | H40: =IF(OR(F40="",G40=""),"",G40-F40) | J40: =IF(H40="","",H40*I40) | M40: No
B41: Groom's siblings | D41: Double | H41: =IF(OR(F41="",G41=""),"",G41-F41) | J41: =IF(H41="","",H41*I41) | M41: No
B42: Outstation family 1 | D42: Double | H42: =IF(OR(F42="",G42=""),"",G42-F42) | J42: =IF(H42="","",H42*I42) | M42: No
B43: Outstation family 2 | D43: Double | H43: =IF(OR(F43="",G43=""),"",G43-F43) | J43: =IF(H43="","",H43*I43) | M43: No
B44: Outstation family 3 | D44: Double | H44: =IF(OR(F44="",G44=""),"",G44-F44) | J44: =IF(H44="","",H44*I44) | M44: No
B45: VIP guest | D45: Double | H45: =IF(OR(F45="",G45=""),"",G45-F45) | J45: =IF(H45="","",H45*I45) | M45: No
B46: Bridal dresser (if staying) | D46: Single | H46: =IF(OR(F46="",G46=""),"",G46-F46) | J46: =IF(H46="","",H46*I46) | M46: No
H47: =IF(OR(F47="",G47=""),"",G47-F47) | J47: =IF(H47="","",H47*I47)
H48: =IF(OR(F48="",G48=""),"",G48-F48) | J48: =IF(H48="","",H48*I48)
H49: =IF(OR(F49="",G49=""),"",G49-F49) | J49: =IF(H49="","",H49*I49)
H50: =IF(OR(F50="",G50=""),"",G50-F50) | J50: =IF(H50="","",H50*I50)
H51: =IF(OR(F51="",G51=""),"",G51-F51) | J51: =IF(H51="","",H51*I51)
H52: =IF(OR(F52="",G52=""),"",G52-F52) | J52: =IF(H52="","",H52*I52)
H53: =IF(OR(F53="",G53=""),"",G53-F53) | J53: =IF(H53="","",H53*I53)
H54: =IF(OR(F54="",G54=""),"",G54-F54) | J54: =IF(H54="","",H54*I54)

Sheet 18 Photo & Video Plan
B2: PHOTOGRAPHY & VIDEOGRAPHY SHOT LIST
B3: Print this and give a copy to the photographer, the videographer and one family member on each side who can round people up. Tick 'Got it' on the night.
C5: ="Must-have shots: "&COUNTIF(D7:D80,"Must")&" | Captured: "&COUNTIFS(D7:D80,"Must",I7:I80,"Yes") -> Must-have shots: 52 | Captured: 0
B6: Section | C6: Shot | D6: Priority | E6: People needed | F6: Location | G6: Planned time | H6: Assigned to | I6: Got it? | J6: Notes
B7: Preparation | C7: Bride's dress / saree hanging | D7: Must | E7: Bride | F7: Bridal suite
B8: Preparation | C8: Jewellery, rings and shoes flat-lay | D8: Must | E8: Bride | F8: Bridal suite
B9: Preparation | C9: Invitation card detail shot | D9: Nice | E9: - | F9: Bridal suite
B10: Preparation | C10: Bride having hair & makeup done | D10: Must | E10: Bride | F10: Bridal suite
B11: Preparation | C11: Bride's mother helping with the saree | D11: Must | E11: Bride + mother | F11: Bridal suite
B12: Preparation | C12: Bride's father seeing her for the first time | D12: Must | E12: Bride + father | F12: Bridal suite
B13: Preparation | C13: Bride with bridesmaids | D13: Must | E13: Bride + bridesmaids | F13: Bridal suite
B14: Preparation | C14: Bride alone - full length portrait | D14: Must | E14: Bride | F14: Bridal suite
B15: Preparation | C15: Groom getting ready / tying the tie | D15: Must | E15: Groom | F15: Groom's room
B16: Preparation | C16: Groom with his father | D16: Must | E16: Groom + father | F16: Groom's room
B17: Preparation | C17: Groom with his mother | D17: Must | E17: Groom + mother | F17: Groom's room
B18: Preparation | C18: Groom with groomsmen | D18: Must | E18: Groom + groomsmen | F18: Groom's room
... B68: Video | C68: Same-day edit handover to the DJ | D68: Optional | E68: - | F68: AV desk

Sheet 19 Responsibilities
B2: RESPONSIBILITY MATRIX (RACI)
B3: R = does the work. A = accountable if it goes wrong. C = consulted. I = kept informed. Fill in real names in the 'Person' column so nobody assumes someone else has it.
B6: Area | C6: Activity | D6: Responsible (does it) | E6: Accountable (owns it) | F6: Consulted | G6: Informed | H6: Person (name) | I6: Phone | J6: Deadline | K6: Status | L6: Notes
B7: Money | C7: Approving any spend above the budget line | D7: Couple | E7: Couple | F7: Both families | G7: Coordinator
B8: Money | C8: Paying vendor deposits and balances | D8: Couple | E8: Groom | F8: Both families | G8: Vendor
B9: Money | C9: Carrying day-of cash and paying tips | D9: Best Man | E9: Groom | F9: Couple | G9: Coordinator
B10: Money | C10: Guarding the gift table and cash gifts | D10: Gift table attendant | E10: Groom's Family | F10: Coordinator | G10: Couple
B11: Guests | C11: Owning the guest list and RSVPs | D11: Couple | E11: Couple | F11: Both families | G11: Coordinator
B12: Guests | C12: Welcoming and seating guests | D12: Ushers | E12: Coordinator | F12: Both families | G12: Venue
B13: Guests | C13: Looking after elderly relatives | D13: Family reps | E13: Both families | F13: Coordinator | G13: Venue
B14: Guests | C14: Looking after overseas / outstation guests | D14: Family reps | E14: Couple | F14: Coordinator | G14: Hotel
B15: Ceremony | C15: Poruwa items - buying and bringing them | D15: Groom's Family | E15: Groom's Family | F15: Officiant | G15: Coordinator
B16: Ceremony | C16: Registration folder - NICs, certificates | D16: Couple | E16: Couple | F16: Registrar | G16: Coordinator
B17: Ceremony | C17: Producing the two witnesses on time | D17: Coordinator | E17: Couple | F17: Witnesses | G17: Registrar
B18: Ceremony | C18: Ring custody until the exchange | D18: Best Man | E18: Groom | F18: Maid of Honour | G18: Couple
... B36: After | C36: Logging gifts and sending thank-yous | D36: Couple | E36: Bride | F36: Both families | G36: -

Sheet 20 Day Timeline
B2: WEDDING-DAY MASTER TIMELINE
B3: The single running order for the day. Every other schedule must agree with this one. Print it. Times are a realistic starting draft for a 7.00pm Poruwa - adjust to your nekath and your venue.
B6: Phase | C6: Time | D6: Ends | E6: Mins | F6: What happens | G6: Who | H6: Where | I6: Vendor | J6: Applies? | K6: Done? | L6: Notes
B7: Setup | C7: 0.29166667 | D7: =IF($C7="","",$C7+TIME(0,$E7,0)) -> 0.33333333 | E7: 60 | F7: Venue opens - coordinator arrives, collects keys and floor plan | G7: Coordinator | H7: Venue | J7: Required | K7: No
B8: Setup | C8: 0.33333333 | D8: =IF($C8="","",$C8+TIME(0,$E8,0)) -> 0.375 | E8: 60 | F8: Decor team arrives, unloads, marks out the room | G8: Vendor | H8: Ballroom | I8: Decorator | J8: Required | K8: No
B9: Setup | C9: 0.375 | D9: =IF($C9="","",$C9+TIME(0,$E9,0)) -> 0.5 | E9: 180 | F9: PORUWA build and decoration | G9: Vendor | H9: Ballroom | I9: Decorator | J9: Required | K9: No
B10: Setup | C10: 0.375 | D10: =IF($C10="","",$C10+TIME(0,$E10,0)) -> 0.45833333 | E10: 120 | F10: Table layout, linen, chair covers | G10: Vendor | H10: Ballroom | I10: Venue | J10: Required | K10: No
B11: Setup | C11: 0.45833333 | D11: =IF($C11="","",$C11+TIME(0,$E11,0)) -> 0.52083333 | E11: 90 | F11: Sound, lighting and AV rig | G11: Vendor | H11: Ballroom | I11: Sound & AV | J11: Required | K11: No
B12: Setup | C12: 0.5 | D12: =IF($C12="","",$C12+TIME(0,$E12,0)) -> 0.5625 | E12: 90 | F12: Stage, backdrop and head table | G12: Vendor | H12: Ballroom | I12: Decorator | J12: Required | K12: No
B13: Preparation | C13: 0.54166667 | D13: =IF($C13="","",$C13+TIME(0,$E13,0)) -> 0.5625 | E13: 30 | F13: Bridal dresser arrives at the suite | G13: Vendor | H13: Bridal suite | I13: Makeup Artist | J13: Required | K13: No
B14: Preparation | C14: 0.5625 | D14: =IF($C14="","",$C14+TIME(0,$E14,0)) -> 0.66666667 | E14: 150 | F14: BRIDE - hair and makeup | G14: Bride | H14: Bridal suite | I14: Makeup Artist | J14: Required | K14: No
B15: Preparation | C15: 0.5625 | D15: =IF($C15="","",$C15+TIME(0,$E15,0)) -> 0.625 | E15: 90 | F15: Bridesmaids - hair and makeup | G15: Bridesmaids | H15: Bridal suite | I15: Makeup Artist | J15: Required | K15: No
B16: Preparation | C16: 0.60416667 | D16: =IF($C16="","",$C16+TIME(0,$E16,0)) -> 0.625 | E16: 30 | F16: Photographer and videographer arrive at the suite | G16: Vendor | H16: Bridal suite | I16: Photographer | J16: Required | K16: No
B17: Preparation | C17: 0.60416667 | D17: =IF($C17="","",$C17+TIME(0,$E17,0)) -> 0.64583333 | E17: 60 | F17: Detail shots - saree, jewellery, rings, shoes, invitation | G17: Vendor | H17: Bridal suite | I17: Photographer | J17: Required | K17: No
B18: Setup | C18: 0.58333333 | D18: =IF($C18="","",$C18+TIME(0,$E18,0)) -> 0.66666667 | E18: 120 | F18: Fresh flowers delivered and placed | G18: Vendor | H18: Ballroom | I18: Florist | J18: Required | K18: No
B19: Setup | C19: 0.64583333 | D19: =IF($C19="","",$C19+TIME(0,$E19,0)) -> 0.66666667 | E19: 30 | F19: CAKE delivered and set on the cake table | G19: Vendor | H19: Ballroom | I19: Cake | J19: Required | K19: No
B20: Preparation | C20: 0.64583333 | D20: =IF($C20="","",$C20+TIME(0,$E20,0)) -> 0.6875 | E20: 60 | F20: GROOM - grooming and dressing | G20: Groom | H20: Groom's room | J20: Required | K20: No
B21: Preparation | C21: 0.66666667 | D21: =IF($C21="","",$C21+TIME(0,$E21,0)) -> 0.69791667 | E21: 45 | F21: Groom's portraits and shots with his family | G21: Groom | H21: Groom's room | I21: Photographer | J21: Required | K21: No
B22: Setup | C22: 0.66666667 | D22: =IF($C22="","",$C22+TIME(0,$E22,0)) -> 0.70833333 | E22: 60 | F22: Signage, seating board, table numbers, place cards placed | G22: Coordinator | H22: Welcome area | J22: Required | K22: No
B23: Setup | C23: 0.6875 | D23: =IF($C23="","",$C23+TIME(0,$E23,0)) -> 0.70833333 | E23: 30 | F23: Gift table, guest book and favour display set | G23: Coordinator | H23: Welcome area | J23: Required | K23: No
B24: Preparation | C24: 0.66666667 | D24: =IF($C24="","",$C24+TIME(0,$E24,0)) -> 0.70833333 | E24: 60 | F24: Bride into the saree - dresser and mother | G24: Bride | H24: Bridal suite | I24: Makeup Artist | J24: Required | K24: No
B25: Preparation | C25: 0.70833333 | D25: =IF($C25="","",$C25+TIME(0,$E25,0)) -> 0.72916667 | E25: 30 | F25: Bride's first-look with her father | G25: Bride | H25: Bridal suite | I25: Photographer | J25: Required | K25: No
B26: Preparation | C26: 0.70833333 | D26: =IF($C26="","",$C26+TIME(0,$E26,0)) -> 0.73958333 | E26: 45 | F26: Bride's portraits and shots with bridesmaids | G26: Bride | H26: Bridal suite | I26: Photographer | J26: Required | K26: No
B27: Setup | C27: 0.70833333 | D27: =IF($C27="","",$C27+TIME(0,$E27,0)) -> 0.73958333 | E27: 45 | F27: DECOR SIGN-OFF - coordinator and couple walk the room | G27: Coordinator | H27: Ballroom | I27: Decorator | J27: Required | K27: No
B28: Setup | C28: 0.70833333 | D28: =IF($C28="","",$C28+TIME(0,$E28,0)) -> 0.75 | E28: 60 | F28: Kandyan dancers and drummers arrive, change, sound check | G28: Vendor | H28: Backstage | I28: Kandyan Dancers | J28: Required | K28: No
B29: Setup | C29: 0.72916667 | D29: =IF($C29="","",$C29+TIME(0,$E29,0)) -> 0.75 | E29: 30 | F29: Sound check - MC, officiant and speech microphones | G29: Vendor | H29: Ballroom | I29: Sound & AV | J29: Required | K29: No
B30: Setup | C30: 0.72916667 | D30: =IF($C30="","",$C30+TIME(0,$E30,0)) -> 0.75 | E30: 30 | F30: Welcome drinks station ready | G30: Vendor | H30: Welcome area | I30: Caterer | J30: Required | K30: No
B31: Arrival | C31: 0.72916667 | D31: =IF($C31="","",$C31+TIME(0,$E31,0)) -> 0.75 | E31: 30 | F31: Groom and his family leave for the venue | G31: Groom | H31: En route | J31: Required | K31: No
B32: Arrival | C32: 0.75 | D32: =IF($C32="","",$C32+TIME(0,$E32,0)) -> 0.79166667 | E32: 60 | F32: GUESTS ARRIVE - ushers seat them, welcome drinks served | G32: Ushers | H32: Welcome area | I32: Venue | J32: Required | K32: No
B33: Arrival | C33: 0.76041667 | D33: =IF($C33="","",$C33+TIME(0,$E33,0)) -> 0.78125 | E33: 30 | F33: Bride leaves for the venue in the bridal car | G33: Bride | H33: En route | J33: Required | K33: No
B34: Arrival | C34: 0.78125 | D34: =IF($C34="","",$C34+TIME(0,$E34,0)) -> 0.79166667 | E34: 15 | F34: Registrar arrives - coordinator receives the document folder | G34: Coordinator | H34: Venue | J34: Required | K34: No
B35: Arrival | C35: 0.78472222 | D35: =IF($C35="","",$C35+TIME(0,$E35,0)) -> 0.79166667 | E35: 10 | F35: Guests seated, doors closed, phones to silent announcement | G35: MC | H35: Ballroom | I35: MC | J35: Required | K35: No
B36: Ceremony | C36: 0.79166667 | D36: =IF($C36="","",$C36+TIME(0,$E36,0)) -> 0.79513889 | E36: 5 | F36: Hewisi drummers and Kandyan dancers lead the groom in | G36: Vendor | H36: Ballroom | I36: Kandyan Dancers | J36: Required | K36: No
B37: Ceremony | C37: 0.79513889 | D37: =IF($C37="","",$C37+TIME(0,$E37,0)) -> 0.79861111 | E37: 5 | F37: Bride enters with her father | G37: Bride | H37: Ballroom | J37: Required | K37: No
B38: Ceremony | C38: 0.79861111 | D38: =IF($C38="","",$C38+TIME(0,$E38,0)) -> 0.8125 | E38: 20 | F38: PORUWA CEREMONY - see 14 Ceremony & Legal for the full order | G38: Couple | H38: Poruwa | I38: Poruwa Officiant | J38: Required | K38: No
B39: Ceremony | C39: 0.8125 | D39: =IF($C39="","",$C39+TIME(0,$E39,0)) -> 0.82291667 | E39: 15 | F39: MARRIAGE REGISTRATION - couple and witnesses sign | G39: Couple | H39: Signing table | J39: Required | K39: No
B40: Ceremony | C40: 0.82291667 | D40: =IF($C40="","",$C40+TIME(0,$E40,0)) -> 0.82986111 | E40: 10 | F40: Blessings from the elders | G40: Couple | H40: Ballroom | J40: Required | K40: No
B41: Reception | C41: 0.82986111 | D41: =IF($C41="","",$C41+TIME(0,$E41,0)) -> 0.84722222 | E41: 25 | F41: FAMILY GROUP PHOTOGRAPHS - see the list on 18 Photo & Video | G41: Coordinator | H41: Stage | I41: Photographer | J41: Required | K41: No
B42: Reception | C42: 0.82986111 | D42: =IF($C42="","",$C42+TIME(0,$E42,0)) -> 0.84722222 | E42: 25 | F42: Guests move through to the reception, music on | G42: Ushers | H42: Ballroom | I42: DJ | J42: Required | K42: No
B43: Reception | C43: 0.84722222 | D43: =IF($C43="","",$C43+TIME(0,$E43,0)) -> 0.85416667 | E43: 10 | F43: Couple's entrance to the reception | G43: Couple | H43: Ballroom | I43: MC | J43: Required | K43: No
B44: Reception | C44: 0.85416667 | D44: =IF($C44="","",$C44+TIME(0,$E44,0)) -> 0.86458333 | E44: 15 | F44: Welcome speech | G44: Groom's Family | H44: Stage | I44: MC | J44: Required | K44: No
B45: Reception | C45: 0.86458333 | D45: =IF($C45="","",$C45+TIME(0,$E45,0)) -> 0.875 | E45: 15 | F45: Traditional dance performance | G45: Vendor | H45: Dance floor | I45: Kandyan Dancers | J45: Required | K45: No
B46: Reception | C46: 0.875 | D46: =IF($C46="","",$C46+TIME(0,$E46,0)) -> 0.91666667 | E46: 60 | F46: DINNER SERVICE - head table and elderly guests first | G46: Vendor | H46: Ballroom | I46: Caterer | J46: Required | K46: No
B47: Reception | C47: 0.875 | D47: =IF($C47="","",$C47+TIME(0,$E47,0)) -> 0.90625 | E47: 45 | F47: Couple's portraits while guests eat | G47: Couple | H47: Garden | I47: Photographer | J47: Required | K47: No
B48: Reception | C48: 0.89583333 | D48: =IF($C48="","",$C48+TIME(0,$E48,0)) -> 0.90277778 | E48: 10 | F48: CAKE CUTTING | G48: Couple | H48: Cake table | I48: MC | J48: Required | K48: No
B49: Reception | C49: 0.90625 | D49: =IF($C49="","",$C49+TIME(0,$E49,0)) -> 0.92013889 | E49: 20 | F49: Speeches - best man, maid of honour, fathers | G49: Speakers | H49: Stage | I49: MC | J49: Required | K49: No
B50: Reception | C50: 0.92013889 | D50: =IF($C50="","",$C50+TIME(0,$E50,0)) -> 0.92708333 | E50: 10 | F50: First dance | G50: Couple | H50: Dance floor | I50: DJ | J50: Required | K50: No
B51: Reception | C51: 0.92708333 | D51: =IF($C51="","",$C51+TIME(0,$E51,0)) -> 0.96875 | E51: 60 | F51: Music, dancing and table rounds by the couple | G51: Couple | H51: Ballroom | I51: DJ | J51: Required | K51: No
B52: Reception | C52: 0.92708333 | D52: =IF($C52="","",$C52+TIME(0,$E52,0)) -> 0.95833333 | E52: 45 | F52: Photographer covers every table | G52: Vendor | H52: Ballroom | I52: Photographer | J52: Required | K52: No
B53: Close | C53: 0.96875 | D53: =IF($C53="","",$C53+TIME(0,$E53,0)) -> 0.97569444 | E53: 10 | F53: Final announcements and thank-you from the couple | G53: Couple | H53: Stage | I53: MC | J53: Required | K53: No
B54: Close | C54: 0.97569444 | D54: =IF($C54="","",$C54+TIME(0,$E54,0)) -> 0.97916667 | E54: 5 | F54: Cake boxes and favours handed out at the door | G54: Ushers | H54: Welcome area | J54: Required | K54: No
B55: Close | C55: 0.97916667 | D55: =IF($C55="","",$C55+TIME(0,$E55,0)) -> 1 | E55: 30 | F55: GUESTS DEPART - buses leave | G55: Coordinator | H55: Entrance | I55: Transport | J55: Required | K55: No
B56: Close | C56: 0.97916667 | D56: =IF($C56="","",$C56+TIME(0,$E56,0)) -> 0.98958333 | E56: 15 | F56: GIFT TABLE cleared to a locked room - two people, count together | G56: Groom's Family | H56: Welcome area | J56: Required | K56: No
B57: Close | C57: 0.98263889 | D57: =IF($C57="","",$C57+TIME(0,$E57,0)) -> 1 | E57: 25 | F57: JEWELLERY removed, checked against 12 Attire & Jewellery, secured | G57: Groom | H57: Bridal suite | J57: Required | K57: No
B58: Close | C58: 0.98611111 | D58: =IF($C58="","",$C58+TIME(0,$E58,0)) -> 1 | E58: 20 | F58: Personal belongings collected from both rooms and the stage | G58: Bridesmaids | H58: Venue | J58: Required | K58: No
B59: Close | C59: 0.98958333 | D59: =IF($C59="","",$C59+TIME(0,$E59,0)) -> 1.0104167 | E59: 30 | F59: Vendor sign-off - coordinator checks each one out | G59: Coordinator | H59: Venue | J59: Required | K59: No
B60: Close | C60: 0.98958333 | D60: =IF($C60="","",$C60+TIME(0,$E60,0)) -> 1.0034722 | E60: 20 | F60: Day-of balances and tips paid | G60: Best Man | H60: Venue | J60: Required | K60: No
B61: Close | C61: 0 | D61: =IF($C61="","",$C61+TIME(0,$E61,0)) -> 0.03125 | E61: 45 | F61: Decor and AV breakdown begins | G61: Vendor | H61: Ballroom | I61: Decorator | J61: Required | K61: No
B62: Close | C62: 0.010416667 | D62: =IF($C62="","",$C62+TIME(0,$E62,0)) -> 0.020833333 | E62: 15 | F62: FINAL VENUE WALKTHROUGH - nothing left behind | G62: Coordinator | H62: Venue | I62: Venue / Hotel | J62: Required | K62: No
B65: MUSIC & MC CUES - give this to the DJ and the MC two weeks out | K65: ="Confirmed with DJ: "&COUNTIF(K67:K91,"Yes")&" of "&COUNTA(B67:B91) -> Confirmed with DJ: 0 of 25
B66: Moment | F66: What plays | G66: Artist / source | H66: Who cues it | I66: Live or recorded | J66: Applies? | K66: Confirmed with DJ? | L66: Notes
B67: Guests arriving / welcome drinks | F67: Instrumental background | G67: DJ | H67: MC | I67: Recorded | J67: Required | K67: No
B68: Groom's procession in | F68: Hewisi drums + Kandyan dancers | G68: Drummers | H68: MC | I68: Live | J68: Required | K68: No
B69: Bride's entrance | F69: Chosen entrance piece | G69: DJ | H69: MC | I69: Recorded | J69: Required | K69: No
B70: Stepping onto the Poruwa | F70: Ashtaka chanting | G70: Officiant | H70: MC | I70: Live | J70: Required | K70: No
B71: During the Poruwa rituals | F71: No music - chanting only | G71: - | H71: MC | I71: Live | J71: Required | K71: No
B72: Thread tying / water pouring | F72: Jayamangala Gatha | G72: Singers | H72: MC | I72: Live | J72: Required | K72: No
B73: Signing the register | F73: Soft instrumental | G73: DJ | H73: MC | I73: Recorded | J73: Required | K73: No
B74: Family photographs | F74: Light background music | G74: DJ | H74: MC | I74: Recorded | J74: Required | K74: No
B75: Couple's entrance to the reception | F75: Upbeat entrance song | G75: DJ | H75: MC | I75: Recorded | J75: Required | K75: No
B76: Welcome speech | F76: Music off, mic on | G76: MC | H76: MC | I76: - | J76: Required | K76: No
B77: Traditional dance performance | F77: Troupe's own track | G77: Dance troupe | H77: MC | I77: Live | J77: Optional | K77: No
B78: Dinner service | F78: Background playlist - low volume | G78: DJ | H78: MC | I78: Recorded | J78: Required | K78: No
... B86: Guests departing | F86: Gentle background | G86: DJ | H86: MC | I86: Recorded | J86: Required | K86: No
B87: MUST PLAY 1 | H87: MC | I87: Recorded | J87: Optional | K87: No
B88: MUST PLAY 2 | H88: MC | I88: Recorded | J88: Optional | K88: No
B89: MUST PLAY 3 | H89: MC | I89: Recorded | J89: Optional | K89: No
B90: DO NOT PLAY 1 | H90: MC | I90: - | J90: Required | K90: No
B91: DO NOT PLAY 2 | H91: MC | I91: - | J91: Required | K91: No

Sheet 21 Vendor Schedule
B2: VENDOR ARRIVAL & SETUP SCHEDULE
B3: Operational sheet for the coordinator - sorted by arrival time. Tick each vendor in on arrival and out at the end. Contact details pull from 05 Vendors.
B6: Arrival | C6: Vendor | D6: Service | E6: Setup starts | F6: Setup done by | G6: On duty from | H6: On duty until | I6: Breakdown from | J6: Departs | K6: Where in the venue | L6: Contact person | M6: Phone | N6: Checked IN | O6: Checked OUT | P6: Notes
B7: 0.29166667 | C7: Coordinator | D7: Venue opening, floor plan, keys | E7: 0.29166667 | F7: 0.3125 | G7: 0.29166667 | H7: 0.020833333 | I7: 0.010416667 | J7: 0.03125 | K7: Whole venue | L7: {=IFERROR(INDEX('05 Vendors'!$E$7:$E$200,MATCH($C7,'05 Vendors'!$C$7:$C$200,0))&"","")} | M7: {=IFERROR(INDEX('05 Vendors'!$F$7:$F$200,MATCH($C7,'05 Vendors'!$C$7:$C$200,0))&"","")} | N7: No | O7: No
B8: 0.33333333 | C8: Decorator | D8: Poruwa, stage, tables, backdrop | E8: 0.33333333 | F8: 0.70833333 | G8: 0.70833333 | H8: 0.97916667 | I8: 0 | J8: 0.041666667 | K8: Ballroom | L8: {=IFERROR(INDEX('05 Vendors'!$E$7:$E$200,MATCH($C8,'05 Vendors'!$C$7:$C$200,0))&"","")} | M8: {=IFERROR(INDEX('05 Vendors'!$F$7:$F$200,MATCH($C8,'05 Vendors'!$C$7:$C$200,0))&"","")} | N8: No | O8: No
B9: 0.45833333 | C9: Sound & AV | D9: PA, mics, uplighting, screen | E9: 0.45833333 | F9: 0.52083333 | G9: 0.75 | H9: 0.97916667 | I9: 0 | J9: 0.03125 | K9: Ballroom / AV desk | L9: {=IFERROR(INDEX('05 Vendors'!$E$7:$E$200,MATCH($C9,'05 Vendors'!$C$7:$C$200,0))&"","")} | M9: {=IFERROR(INDEX('05 Vendors'!$F$7:$F$200,MATCH($C9,'05 Vendors'!$C$7:$C$200,0))&"","")} | N9: No | O9: No
B10: 0.54166667 | C10: Makeup Artist | D10: Bride and bridesmaids | E10: 0.54166667 | F10: 0.5625 | G10: 0.5625 | H10: 0.76041667 | J10: 0.77083333 | K10: Bridal suite | L10: {=IFERROR(INDEX('05 Vendors'!$E$7:$E$200,MATCH($C10,'05 Vendors'!$C$7:$C$200,0))&"","")} | M10: {=IFERROR(INDEX('05 Vendors'!$F$7:$F$200,MATCH($C10,'05 Vendors'!$C$7:$C$200,0))&"","")} | N10: No | O10: No
B11: 0.58333333 | C11: Florist | D11: Fresh flowers, bouquets, centrepieces | E11: 0.58333333 | F11: 0.66666667 | G11: 0.66666667 | J11: 0.6875 | K11: Ballroom / suite | L11: {=IFERROR(INDEX('05 Vendors'!$E$7:$E$200,MATCH($C11,'05 Vendors'!$C$7:$C$200,0))&"","")} | M11: {=IFERROR(INDEX('05 Vendors'!$F$7:$F$200,MATCH($C11,'05 Vendors'!$C$7:$C$200,0))&"","")} | N11: No | O11: No
B12: 0.60416667 | C12: Photographer | D12: Full day coverage | G12: 0.60416667 | H12: 0.97916667 | J12: 0.98958333 | K12: Everywhere | L12: {=IFERROR(INDEX('05 Vendors'!$E$7:$E$200,MATCH($C12,'05 Vendors'!$C$7:$C$200,0))&"","")} | M12: {=IFERROR(INDEX('05 Vendors'!$F$7:$F$200,MATCH($C12,'05 Vendors'!$C$7:$C$200,0))&"","")} | N12: No | O12: No
B13: 0.60416667 | C13: Videographer | D13: Full day coverage | G13: 0.60416667 | H13: 0.97916667 | J13: 0.98958333 | K13: Everywhere | L13: {=IFERROR(INDEX('05 Vendors'!$E$7:$E$200,MATCH($C13,'05 Vendors'!$C$7:$C$200,0))&"","")} | M13: {=IFERROR(INDEX('05 Vendors'!$F$7:$F$200,MATCH($C13,'05 Vendors'!$C$7:$C$200,0))&"","")} | N13: No | O13: No
B14: 0.64583333 | C14: Cake | D14: Cake delivery and setup | E14: 0.64583333 | F14: 0.66666667 | J14: 0.67708333 | K14: Cake table | L14: {=IFERROR(INDEX('05 Vendors'!$E$7:$E$200,MATCH($C14,'05 Vendors'!$C$7:$C$200,0))&"","")} | M14: {=IFERROR(INDEX('05 Vendors'!$F$7:$F$200,MATCH($C14,'05 Vendors'!$C$7:$C$200,0))&"","")} | N14: No | O14: No
B15: 0.70833333 | C15: Kandyan Dancers | D15: Procession and performance | E15: 0.70833333 | F15: 0.77083333 | G15: 0.79166667 | H15: 0.875 | J15: 0.89583333 | K15: Backstage / ballroom | L15: {=IFERROR(INDEX('05 Vendors'!$E$7:$E$200,MATCH($C15,'05 Vendors'!$C$7:$C$200,0))&"","")} | M15: {=IFERROR(INDEX('05 Vendors'!$F$7:$F$200,MATCH($C15,'05 Vendors'!$C$7:$C$200,0))&"","")} | N15: No | O15: No
B16: 0.70833333 | C16: Drummers | D16: Hewisi at the entrance | E16: 0.70833333 | F16: 0.77083333 | G16: 0.78125 | H16: 0.80208333 | J16: 0.89583333 | K16: Entrance | L16: {=IFERROR(INDEX('05 Vendors'!$E$7:$E$200,MATCH($C16,'05 Vendors'!$C$7:$C$200,0))&"","")} | M16: {=IFERROR(INDEX('05 Vendors'!$F$7:$F$200,MATCH($C16,'05 Vendors'!$C$7:$C$200,0))&"","")} | N16: No | O16: No
B17: 0.70833333 | C17: Transport | D17: Bridal car, family cars, guest buses | G17: 0.54166667 | H17: 0.041666667 | J17: 0.041666667 | K17: Entrance / car park | L17: {=IFERROR(INDEX('05 Vendors'!$E$7:$E$200,MATCH($C17,'05 Vendors'!$C$7:$C$200,0))&"","")} | M17: {=IFERROR(INDEX('05 Vendors'!$F$7:$F$200,MATCH($C17,'05 Vendors'!$C$7:$C$200,0))&"","")} | N17: No | O17: No
B18: 0.72916667 | C18: MC | D18: Compere the evening | G18: 0.78125 | H18: 0.97916667 | J18: 0.98958333 | K18: Stage | L18: {=IFERROR(INDEX('05 Vendors'!$E$7:$E$200,MATCH($C18,'05 Vendors'!$C$7:$C$200,0))&"","")} | M18: {=IFERROR(INDEX('05 Vendors'!$F$7:$F$200,MATCH($C18,'05 Vendors'!$C$7:$C$200,0))&"","")} | N18: No | O18: No
B19: 0.72916667 | C19: DJ | D19: Music through the reception | E19: 0.72916667 | F19: 0.76041667 | G19: 0.82986111 | H19: 0.97916667 | I19: 0.97916667 | J19: 0.010416667 | K19: AV desk | L19: {=IFERROR(INDEX('05 Vendors'!$E$7:$E$200,MATCH($C19,'05 Vendors'!$C$7:$C$200,0))&"","")} | M19: {=IFERROR(INDEX('05 Vendors'!$F$7:$F$200,MATCH($C19,'05 Vendors'!$C$7:$C$200,0))&"","")} | N19: No | O19: No
B20: 0.72916667 | C20: Caterer | D20: Welcome drinks, buffet, service | E20: 0.72916667 | F20: 0.75 | G20: 0.75 | H20: 0.97916667 | I20: 0.97916667 | J20: 0.041666667 | K20: Ballroom / kitchen | L20: {=IFERROR(INDEX('05 Vendors'!$E$7:$E$200,MATCH($C20,'05 Vendors'!$C$7:$C$200,0))&"","")} | M20: {=IFERROR(INDEX('05 Vendors'!$F$7:$F$200,MATCH($C20,'05 Vendors'!$C$7:$C$200,0))&"","")} | N20: No | O20: No
B21: 0.75 | C21: Venue / Hotel | D21: Banquet team, service, security | G21: 0.29166667 | H21: 0.041666667 | K21: Whole venue | L21: {=IFERROR(INDEX('05 Vendors'!$E$7:$E$200,MATCH($C21,'05 Vendors'!$C$7:$C$200,0))&"","")} | M21: {=IFERROR(INDEX('05 Vendors'!$F$7:$F$200,MATCH($C21,'05 Vendors'!$C$7:$C$200,0))&"","")} | N21: No | O21: No
B22: 0.77083333 | C22: Poruwa Officiant | D22: Ashtaka chanting, Poruwa rituals | E22: 0.77083333 | F22: 0.78472222 | G22: 0.79166667 | H22: 0.8125 | J22: 0.82291667 | K22: Poruwa | L22: {=IFERROR(INDEX('05 Vendors'!$E$7:$E$200,MATCH($C22,'05 Vendors'!$C$7:$C$200,0))&"","")} | M22: {=IFERROR(INDEX('05 Vendors'!$F$7:$F$200,MATCH($C22,'05 Vendors'!$C$7:$C$200,0))&"","")} | N22: No | O22: No
B23: 0.78125 | C23: Registrar | D23: Marriage registration | G23: 0.80902778 | H23: 0.82638889 | J23: 0.83333333 | K23: Signing table | L23: {=IFERROR(INDEX('05 Vendors'!$E$7:$E$200,MATCH($C23,'05 Vendors'!$C$7:$C$200,0))&"","")} | M23: {=IFERROR(INDEX('05 Vendors'!$F$7:$F$200,MATCH($C23,'05 Vendors'!$C$7:$C$200,0))&"","")} | N23: No | O23: No
L24: {=IFERROR(INDEX('05 Vendors'!$E$7:$E$200,MATCH($C24,'05 Vendors'!$C$7:$C$200,0))&"","")} | M24: {=IFERROR(INDEX('05 Vendors'!$F$7:$F$200,MATCH($C24,'05 Vendors'!$C$7:$C$200,0))&"","")}
L25: {=IFERROR(INDEX('05 Vendors'!$E$7:$E$200,MATCH($C25,'05 Vendors'!$C$7:$C$200,0)),"")} | M25: {=IFERROR(INDEX('05 Vendors'!$F$7:$F$200,MATCH($C25,'05 Vendors'!$C$7:$C$200,0)),"")}
L26: {=IFERROR(INDEX('05 Vendors'!$E$7:$E$200,MATCH($C26,'05 Vendors'!$C$7:$C$200,0)),"")} | M26: {=IFERROR(INDEX('05 Vendors'!$F$7:$F$200,MATCH($C26,'05 Vendors'!$C$7:$C$200,0)),"")}
L27: {=IFERROR(INDEX('05 Vendors'!$E$7:$E$200,MATCH($C27,'05 Vendors'!$C$7:$C$200,0)),"")} | M27: {=IFERROR(INDEX('05 Vendors'!$F$7:$F$200,MATCH($C27,'05 Vendors'!$C$7:$C$200,0)),"")}
L28: {=IFERROR(INDEX('05 Vendors'!$E$7:$E$200,MATCH($C28,'05 Vendors'!$C$7:$C$200,0)),"")} | M28: {=IFERROR(INDEX('05 Vendors'!$F$7:$F$200,MATCH($C28,'05 Vendors'!$C$7:$C$200,0)),"")}
L29: {=IFERROR(INDEX('05 Vendors'!$E$7:$E$200,MATCH($C29,'05 Vendors'!$C$7:$C$200,0)),"")} | M29: {=IFERROR(INDEX('05 Vendors'!$F$7:$F$200,MATCH($C29,'05 Vendors'!$C$7:$C$200,0)),"")}
L30: {=IFERROR(INDEX('05 Vendors'!$E$7:$E$200,MATCH($C30,'05 Vendors'!$C$7:$C$200,0)),"")} | M30: {=IFERROR(INDEX('05 Vendors'!$F$7:$F$200,MATCH($C30,'05 Vendors'!$C$7:$C$200,0)),"")}
L31: {=IFERROR(INDEX('05 Vendors'!$E$7:$E$200,MATCH($C31,'05 Vendors'!$C$7:$C$200,0)),"")} | M31: {=IFERROR(INDEX('05 Vendors'!$F$7:$F$200,MATCH($C31,'05 Vendors'!$C$7:$C$200,0)),"")}
L32: {=IFERROR(INDEX('05 Vendors'!$E$7:$E$200,MATCH($C32,'05 Vendors'!$C$7:$C$200,0)),"")} | M32: {=IFERROR(INDEX('05 Vendors'!$F$7:$F$200,MATCH($C32,'05 Vendors'!$C$7:$C$200,0)),"")}
L33: {=IFERROR(INDEX('05 Vendors'!$E$7:$E$200,MATCH($C33,'05 Vendors'!$C$7:$C$200,0)),"")} | M33: {=IFERROR(INDEX('05 Vendors'!$F$7:$F$200,MATCH($C33,'05 Vendors'!$C$7:$C$200,0)),"")}

Sheet 22 Contact Sheet
B2: WEDDING-DAY CONTACT SHEET
B3: PRINT THIS. One page, every number anyone might need on the day. Vendor numbers pull from 05 Vendors automatically.
B6: Group | C6: Role | D6: Name | E6: Phone | F6: Backup phone | G6: WhatsApp | H6: Notes
B7: Couple | C7: Bride | D7: =BrideName -> Methuli
B8: Couple | C8: Groom | D8: =GroomName -> Udara
B9: Couple | C9: Maid / Matron of Honour
B10: Couple | C10: Best Man
B11: Family | C11: Bride's father
B12: Family | C12: Bride's mother
